Workbook

Sheet MR Accrual
B1: Coresphere100 Technologies Pvt. Ltd.
B2: Monthly revenue (Accrual)
F3: Amount in INR
B4: Particulars | C4: For the month ended | D4: For the month ended | E4: For the month ended | F4: For the month ended | G4: For the month ended | H4: For the month ended | I4: For the month ended | J4: For the month ended
C5: 45748 | D5: 45748 | E5: 45778 | F5: 45809 | G5: 45839 | H5: 45870 | I5: 45901 | J5: 45931 | K5: Total
B6: Monthly Revenue from B2B subscribers (A) | D6: =SUM(D9:D45) | E6: =SUM(E9:E45) | F6: =SUM(F9:F45) | G6: =SUM(G9:G45) | H6: =SUM(H9:H45) | I6: =SUM(I9:I45) | J6: =SUM(J9:J45) | K6: =SUM(K9:K45)
B8: Annual Subscription
B9: Annual- Half Yearly Payment | D9: =SUMIF(Pivot!$A$45:$A$84,B9,Pivot!$B$45:$B$84)/118% | E9: =SUMIF(Pivot!$A$45:$A$84,B9,Pivot!$C$45:$C$84)/118% | F9: =SUMIF(Pivot!$A$45:$A$84,B9,Pivot!$D$45:$D$84)/118% | G9: =SUMIF(Pivot!$A$45:$A$84,B9,Pivot!$E$45:$E$84)/118% | H9: =SUMIF(Pivot!$A$45:$A$84,B9,Pivot!$F$45:$F$84)/118% | I9: =SUMIF(Pivot!$A$45:$A$84,B9,Pivot!$G$45:$G$84)/118% | J9: =SUMIF(Pivot!$A$45:$H$84,B9,Pivot!$H$45:$H$84)/118% | K9: =SUM(D9:J9)
B10: Annual subscription, Quarterly upfront | D10: =SUMIF(Pivot!$A$45:$A$84,B10,Pivot!$B$45:$B$84)/118% | E10: =SUMIF(Pivot!$A$45:$A$84,B10,Pivot!$C$45:$C$84)/118% | F10: =SUMIF(Pivot!$A$45:$A$84,B10,Pivot!$D$45:$D$84)/118% | G10: =SUMIF(Pivot!$A$45:$A$84,B10,Pivot!$E$45:$E$84)/118% | H10: =SUMIF(Pivot!$A$45:$A$84,B10,Pivot!$F$45:$F$84)/118% | I10: =SUMIF(Pivot!$A$45:$A$84,B10,Pivot!$G$45:$G$84)/118% | J10: =SUMIF(Pivot!$A$45:$H$84,B10,Pivot!$H$45:$H$84)/118% | K10: =SUM(D10:J10)
B11: Annual Upfront | D11: =SUMIF(Pivot!$A$45:$A$84,B11,Pivot!$B$45:$B$84)/118% | E11: =SUMIF(Pivot!$A$45:$A$84,B11,Pivot!$C$45:$C$84)/118% | F11: =SUMIF(Pivot!$A$45:$A$84,B11,Pivot!$D$45:$D$84)/118% | G11: =SUMIF(Pivot!$A$45:$A$84,B11,Pivot!$E$45:$E$84)/118% | H11: =SUMIF(Pivot!$A$45:$A$84,B11,Pivot!$F$45:$F$84)/118% | I11: =SUMIF(Pivot!$A$45:$A$84,B11,Pivot!$G$45:$G$84)/118% | J11: =SUMIF(Pivot!$A$45:$H$84,B11,Pivot!$H$45:$H$84)/118% | K11: =SUM(D11:J11)
B12: Annual-Monthly | D12: =SUMIF(Pivot!$A$45:$A$84,B12,Pivot!$B$45:$B$84)/118% | E12: =SUMIF(Pivot!$A$45:$A$84,B12,Pivot!$C$45:$C$84)/118% | F12: =SUMIF(Pivot!$A$45:$A$84,B12,Pivot!$D$45:$D$84)/118% | G12: =SUMIF(Pivot!$A$45:$A$84,B12,Pivot!$E$45:$E$84)/118% | H12: =SUMIF(Pivot!$A$45:$A$84,B12,Pivot!$F$45:$F$84)/118% | I12: =SUMIF(Pivot!$A$45:$A$84,B12,Pivot!$G$45:$G$84)/118% | J12: =SUMIF(Pivot!$A$45:$H$84,B12,Pivot!$H$45:$H$84)/118% | K12: =SUM(D12:J12)
B13: 2 Year- Upfront | D13: =SUMIF(Pivot!$A$45:$A$84,B13,Pivot!$B$45:$B$84)/118% | E13: =SUMIF(Pivot!$A$45:$A$84,B13,Pivot!$C$45:$C$84)/118% | F13: =SUMIF(Pivot!$A$45:$A$84,B13,Pivot!$D$45:$D$84)/118% | G13: =SUMIF(Pivot!$A$45:$A$84,B13,Pivot!$E$45:$E$84)/118% | H13: =SUMIF(Pivot!$A$45:$A$84,B13,Pivot!$F$45:$F$84)/118% | I13: =SUMIF(Pivot!$A$45:$A$84,B13,Pivot!$G$45:$G$84)/118% | J13: =SUMIF(Pivot!$A$45:$H$84,B13,Pivot!$H$45:$H$84)/118% | K13: =SUM(D13:J13)
D14: =SUMIF(Pivot!$A$45:$A$84,B14,Pivot!$B$45:$B$84)/118% | E14: =SUMIF(Pivot!$A$45:$A$84,B14,Pivot!$C$45:$C$84)/118% | F14: =SUMIF(Pivot!$A$45:$A$84,B14,Pivot!$D$45:$D$84)/118% | G14: =SUMIF(Pivot!$A$45:$A$84,B14,Pivot!$E$45:$E$84)/118% | H14: =SUMIF(Pivot!$A$45:$A$84,B14,Pivot!$F$45:$F$84)/118% | I14: =SUMIF(Pivot!$A$45:$A$84,B14,Pivot!$G$45:$G$84)/118% | J14: =SUMIF(Pivot!$A$45:$H$84,B14,Pivot!$H$45:$H$84)/118% | K14: =SUM(D14:J14)
B15: Other Than Annual Subscriptions | D15: =SUMIF(Pivot!$A$45:$A$84,B15,Pivot!$B$45:$B$84)/118% | E15: =SUMIF(Pivot!$A$45:$A$84,B15,Pivot!$C$45:$C$84)/118% | F15: =SUMIF(Pivot!$A$45:$A$84,B15,Pivot!$D$45:$D$84)/118% | G15: =SUMIF(Pivot!$A$45:$A$84,B15,Pivot!$E$45:$E$84)/118% | H15: =SUMIF(Pivot!$A$45:$A$84,B15,Pivot!$F$45:$F$84)/118% | I15: =SUMIF(Pivot!$A$45:$A$84,B15,Pivot!$G$45:$G$84)/118% | J15: =SUMIF(Pivot!$A$45:$H$84,B15,Pivot!$H$45:$H$84)/118% | K15: =SUM(D15:J15)
B16: 10 -Days -Upfront | D16: =SUMIF(Pivot!$A$45:$A$84,B16,Pivot!$B$45:$B$84)/118% | E16: =SUMIF(Pivot!$A$45:$A$84,B16,Pivot!$C$45:$C$84)/118% | F16: =SUMIF(Pivot!$A$45:$A$84,B16,Pivot!$D$45:$D$84)/118% | G16: =SUMIF(Pivot!$A$45:$A$84,B16,Pivot!$E$45:$E$84)/118% | H16: =SUMIF(Pivot!$A$45:$A$84,B16,Pivot!$F$45:$F$84)/118% | I16: =SUMIF(Pivot!$A$45:$A$84,B16,Pivot!$G$45:$G$84)/118% | J16: =SUMIF(Pivot!$A$45:$H$84,B16,Pivot!$H$45:$H$84)/118% | K16: =SUM(D16:J16)
B17: 12 -Days -Upfront | D17: =SUMIF(Pivot!$A$45:$A$84,B17,Pivot!$B$45:$B$84)/118% | E17: =SUMIF(Pivot!$A$45:$A$84,B17,Pivot!$C$45:$C$84)/118% | F17: =SUMIF(Pivot!$A$45:$A$84,B17,Pivot!$D$45:$D$84)/118% | G17: =SUMIF(Pivot!$A$45:$A$84,B17,Pivot!$E$45:$E$84)/118% | H17: =SUMIF(Pivot!$A$45:$A$84,B17,Pivot!$F$45:$F$84)/118% | I17: =SUMIF(Pivot!$A$45:$A$84,B17,Pivot!$G$45:$G$84)/118% | J17: =SUMIF(Pivot!$A$45:$H$84,B17,Pivot!$H$45:$H$84)/118% | K17: =SUM(D17:J17)
B18: 15 -Days -Upfront | D18: =SUMIF(Pivot!$A$45:$A$84,B18,Pivot!$B$45:$B$84)/118% | E18: =SUMIF(Pivot!$A$45:$A$84,B18,Pivot!$C$45:$C$84)/118% | F18: =SUMIF(Pivot!$A$45:$A$84,B18,Pivot!$D$45:$D$84)/118% | G18: =SUMIF(Pivot!$A$45:$A$84,B18,Pivot!$E$45:$E$84)/118% | H18: =SUMIF(Pivot!$A$45:$A$84,B18,Pivot!$F$45:$F$84)/118% | I18: =SUMIF(Pivot!$A$45:$A$84,B18,Pivot!$G$45:$G$84)/118% | J18: =SUMIF(Pivot!$A$45:$H$84,B18,Pivot!$H$45:$H$84)/118% | K18: =SUM(D18:J18)
B19: 13 month-Upfront | D19: =SUMIF(Pivot!$A$45:$A$84,B19,Pivot!$B$45:$B$84)/118% | E19: =SUMIF(Pivot!$A$45:$A$84,B19,Pivot!$C$45:$C$84)/118% | F19: =SUMIF(Pivot!$A$45:$A$84,B19,Pivot!$D$45:$D$84)/118% | G19: =SUMIF(Pivot!$A$45:$A$84,B19,Pivot!$E$45:$E$84)/118% | H19: =SUMIF(Pivot!$A$45:$A$84,B19,Pivot!$F$45:$F$84)/118% | I19: =SUMIF(Pivot!$A$45:$A$84,B19,Pivot!$G$45:$G$84)/118% | J19: =SUMIF(Pivot!$A$45:$H$84,B19,Pivot!$H$45:$H$84)/118% | K19: =SUM(D19:J19)
B20: 19 -Days -Upfront | D20: =SUMIF(Pivot!$A$45:$A$84,B20,Pivot!$B$45:$B$84)/118% | E20: =SUMIF(Pivot!$A$45:$A$84,B20,Pivot!$C$45:$C$84)/118% | F20: =SUMIF(Pivot!$A$45:$A$84,B20,Pivot!$D$45:$D$84)/118% | G20: =SUMIF(Pivot!$A$45:$A$84,B20,Pivot!$E$45:$E$84)/118% | H20: =SUMIF(Pivot!$A$45:$A$84,B20,Pivot!$F$45:$F$84)/118% | I20: =SUMIF(Pivot!$A$45:$A$84,B20,Pivot!$G$45:$G$84)/118% | J20: =SUMIF(Pivot!$A$45:$H$84,B20,Pivot!$H$45:$H$84)/118% | K20: =SUM(D20:J20)
B21: 38 -Days -Upfront | D21: =SUMIF(Pivot!$A$45:$A$84,B21,Pivot!$B$45:$B$84)/118% | E21: =SUMIF(Pivot!$A$45:$A$84,B21,Pivot!$C$45:$C$84)/118% | F21: =SUMIF(Pivot!$A$45:$A$84,B21,Pivot!$D$45:$D$84)/118% | G21: =SUMIF(Pivot!$A$45:$A$84,B21,Pivot!$E$45:$E$84)/118% | H21: =SUMIF(Pivot!$A$45:$A$84,B21,Pivot!$F$45:$F$84)/118% | I21: =SUMIF(Pivot!$A$45:$A$84,B21,Pivot!$G$45:$G$84)/118% | J21: =SUMIF(Pivot!$A$45:$H$84,B21,Pivot!$H$45:$H$84)/118% | K21: =SUM(D21:J21)
B22: 1 month-Upfront | D22: =SUMIF(Pivot!$A$45:$A$84,B22,Pivot!$B$45:$B$84)/118% | E22: =SUMIF(Pivot!$A$45:$A$84,B22,Pivot!$C$45:$C$84)/118% | F22: =SUMIF(Pivot!$A$45:$A$84,B22,Pivot!$D$45:$D$84)/118% | G22: =SUMIF(Pivot!$A$45:$A$84,B22,Pivot!$E$45:$E$84)/118% | H22: =SUMIF(Pivot!$A$45:$A$84,B22,Pivot!$F$45:$F$84)/118% | I22: =SUMIF(Pivot!$A$45:$A$84,B22,Pivot!$G$45:$G$84)/118% | J22: =SUMIF(Pivot!$A$45:$H$84,B22,Pivot!$H$45:$H$84)/118% | K22: =SUM(D22:J22)
B23: 2 months subscription, Monthly | D23: =SUMIF(Pivot!$A$45:$A$84,B23,Pivot!$B$45:$B$84)/118% | E23: =SUMIF(Pivot!$A$45:$A$84,B23,Pivot!$C$45:$C$84)/118% | F23: =SUMIF(Pivot!$A$45:$A$84,B23,Pivot!$D$45:$D$84)/118% | G23: =SUMIF(Pivot!$A$45:$A$84,B23,Pivot!$E$45:$E$84)/118% | H23: =SUMIF(Pivot!$A$45:$A$84,B23,Pivot!$F$45:$F$84)/118% | I23: =SUMIF(Pivot!$A$45:$A$84,B23,Pivot!$G$45:$G$84)/118% | J23: =SUMIF(Pivot!$A$45:$H$84,B23,Pivot!$H$45:$H$84)/118% | K23: =SUM(D23:J23)
B24: 2 months- Upfront | D24: =SUMIF(Pivot!$A$45:$A$84,B24,Pivot!$B$45:$B$84)/118% | E24: =SUMIF(Pivot!$A$45:$A$84,B24,Pivot!$C$45:$C$84)/118% | F24: =SUMIF(Pivot!$A$45:$A$84,B24,Pivot!$D$45:$D$84)/118% | G24: =SUMIF(Pivot!$A$45:$A$84,B24,Pivot!$E$45:$E$84)/118% | H24: =SUMIF(Pivot!$A$45:$A$84,B24,Pivot!$F$45:$F$84)/118% | I24: =SUMIF(Pivot!$A$45:$A$84,B24,Pivot!$G$45:$G$84)/118% | J24: =SUMIF(Pivot!$A$45:$H$84,B24,Pivot!$H$45:$H$84)/118% | K24: =SUM(D24:J24)
B25: 2 month & 13 Days-Upfront | D25: =SUMIF(Pivot!$A$45:$A$84,B25,Pivot!$B$45:$B$84)/118% | E25: =SUMIF(Pivot!$A$45:$A$84,B25,Pivot!$C$45:$C$84)/118% | F25: =SUMIF(Pivot!$A$45:$A$84,B25,Pivot!$D$45:$D$84)/118% | G25: =SUMIF(Pivot!$A$45:$A$84,B25,Pivot!$E$45:$E$84)/118% | H25: =SUMIF(Pivot!$A$45:$A$84,B25,Pivot!$F$45:$F$84)/118% | I25: =SUMIF(Pivot!$A$45:$A$84,B25,Pivot!$G$45:$G$84)/118% | J25: =SUMIF(Pivot!$A$45:$H$84,B25,Pivot!$H$45:$H$84)/118% | K25: =SUM(D25:J25)
B26: 3 months subscription, Monthly | D26: =SUMIF(Pivot!$A$45:$A$84,B26,Pivot!$B$45:$B$84)/118% | E26: =SUMIF(Pivot!$A$45:$A$84,B26,Pivot!$C$45:$C$84)/118% | F26: =SUMIF(Pivot!$A$45:$A$84,B26,Pivot!$D$45:$D$84)/118% | G26: =SUMIF(Pivot!$A$45:$A$84,B26,Pivot!$E$45:$E$84)/118% | H26: =SUMIF(Pivot!$A$45:$A$84,B26,Pivot!$F$45:$F$84)/118% | I26: =SUMIF(Pivot!$A$45:$A$84,B26,Pivot!$G$45:$G$84)/118% | J26: =SUMIF(Pivot!$A$45:$H$84,B26,Pivot!$H$45:$H$84)/118% | K26: =SUM(D26:J26)
... B45: 1year & 6 months - Half Yearly Payment | D45: =SUMIF(Pivot!$A$45:$A$84,B45,Pivot!$B$45:$B$84)/118% | E45: =SUMIF(Pivot!$A$45:$A$84,B45,Pivot!$C$45:$C$84)/118% | F45: =SUMIF(Pivot!$A$45:$A$84,B45,Pivot!$D$45:$D$84)/118% | G45: =SUMIF(Pivot!$A$45:$A$84,B45,Pivot!$E$45:$E$84)/118% | H45: =SUMIF(Pivot!$A$45:$A$84,B45,Pivot!$F$45:$F$84)/118% | I45: =SUMIF(Pivot!$A$45:$A$84,B45,Pivot!$G$45:$G$84)/118% | J45: =SUMIF(Pivot!$A$45:$H$84,B45,Pivot!$H$45:$H$84)/118% | K45: =SUM(D45:J45)
B47: Monthly Revenue from B2C subscribers (B) | D47: ='MR-AR'!C48 | E47: ='MR-AR'!D48 | F47: ='MR-AR'!E48 | G47: =Invoices!M16 | H47: =Invoices!M17 | I47: =Invoices!M18 | J47: =Invoices!M20 | K47: =SUM(D47:J47)
B49: Monthly Revenue from B2B and B2C C=A+B | D49: =D6+D47 | E49: =E6+E47 | F49: =F6+F47 | G49: =G6+G47 | H49: =H6+H47 | I49: =I6+I47 | J49: =J6+J47 | K49: =SUM(D49:J49)

Sheet FY 25-26-Accrual
A1: Coresphere100 Technologies Pvt. Ltd. | F1: Contracts expiring within | G1: 30 | H1: 45777 | I1: 45748 | N1: 45778 | O1: 45808 | R1: 45809 | W1: 45870
A2: Invoices Details | I2: =SUBTOTAL(9,I4:I1944) | J2: =SUBTOTAL(9,J4:J1944) | K2: =SUBTOTAL(9,K4:K1944) | N2: =SUBTOTAL(9,N4:N1944) | P2: =SUBTOTAL(9,P4:P1944) | Q2: =SUBTOTAL(9,Q4:Q1944) | R2: 45838 | S2: =SUBTOTAL(9,S4:S1944) | T2: =SUBTOTAL(9,T4:T1944) | U2: 45869 | V2: =SUBTOTAL(9,V4:V1944) | W2: 45900 | X2: =SUBTOTAL(9,X4:X1944) | Y2: =SUBTOTAL(9,Y4:Y1944) | Z2: 45930 | AA2: =SUBTOTAL(9,AA4:AA1944) | AB2: =SUBTOTAL(9,AB4:AB1944) | AC2: 45961 | AD2: =SUBTOTAL(9,AD4:AD1944) | AE2: =SUBTOTAL(9,AE4:AE1944)
A3: Contract | B3: Months | C3: Customer Name | D3: Invoice Number | E3: Nature of service | F3: Start Date | G3: End Date | H3: Payment Cycle | I3: Contract Amount | J3: Invoiced amount for April | K3: Invoiced amount for MAY | L3: Contract period | M3: Days in April | N3: April Sales (Days Wise) | O3: Days in May | P3: May Sales (Days Wise) | Q3: June in months | R3: Days in June | S3: June in days | T3: July in months | U3: Days in July | V3: July in days | W3: Days in Aug | X3: Aug Sales in months | Y3: Aug Sales in days | Z3: Days in Sept | AA3: Sept Sales in months | AB3: Sept Sales in days | AC3: Days in Oct | AD3: Oct Sales in months | AE3: Oct Sales in days
A4: 0 | B4: 45748 | C4: Touchstone Partners | D4: INV-25-26-000001, INV-25-26-000507 | E4: subscription based service | F4: 45748 | G4: 45838 | H4: 3 months subscription, upfront | I4: 70800 | J4: 23600 | K4: 23600 | L4: 91 | M4: 30 | N4: 23340.659 | O4: 31 | P4: 24118.681 | Q4: 23600 | R4: 30 | S4: 23340.659 | U4: 31 | W4: 0 | X4: 0 | Y4: 0
A5: Closed- May 25 | B5: 45748 | C5: Bimal Rajasekhar | D5: INV-25-26-000002 | E5: subscription based service | F5: 45748 | G5: 45808 | H5: 2 months- Upfront | I5: 35400 | J5: 17700 | K5: 17700 | L5: 61 | M5: 30 | N5: 17409.836 | O5: 31 | P5: 17990.164 | R5: 30 | U5: 31 | W5: 0 | X5: 0 | Y5: 0
A6: 0 | B6: 45748 | C6: Veritas Legal Advocates and Solicitors | D6: INV-25-26-000003, INV-25-26-000534 | E6: subscription based service | F6: 45749 | G6: 45932 | H6: 6 month-Upfront | I6: 1172448 | J6: 195408 | K6: 195408 | L6: 184 | M6: 29 | N6: 184788 | O6: 31 | P6: 197532 | Q6: 195408 | R6: 30 | S6: 191160 | T6: 195408 | U6: 31 | V6: 197532 | W6: 31 | X6: 195408 | Y6: 197532 | Z6: 30 | AA6: 195408 | AB6: 191160 | AC6: 2 | AD6: 167492.57 | AE6: 12744
A7: 0 | B7: Apr & May 25 | C7: LEGALOGIC CONSULTING LLP | D7: INV-25-26-000004, 104, INV-25-26-000490 | E7: subscription based service | F7: 45748 | G7: 45808 | H7: 2 months subscription, Monthly | I7: 70800 | J7: 35400 | K7: 35400 | L7: 61 | M7: 30 | N7: 34819.672 | O7: 31 | P7: 35980.328 | R7: 30 | U7: 31 | W7: 0 | X7: 0 | Y7: 0
A8: 0 | B8: 45748 | C8: VACUITAS COUNSELLOR LLP | D8: INV-25-26-000005 | E8: subscription based service | F8: 45750 | G8: 46114 | H8: Annual Upfront | I8: 116820 | J8: 9735 | K8: 9735 | L8: 365 | M8: 28 | N8: 8961.534 | O8: 31 | P8: 9921.699 | Q8: 9735 | R8: 30 | S8: 9601.6438 | T8: 9735 | U8: 31 | V8: 9921.6986 | W8: 31 | X8: 9735 | Y8: 9921.699 | Z8: 30 | AA8: 9735 | AB8: 9601.644 | AC8: 31 | AD8: 9735 | AE8: 9921.699
A9: Closed-Apr 25 | B9: 45748 | C9: Tvashta Law | D9: INV-25-26-000006 | E9: One time work | F9: 45748 | G9: 45777 | H9: 1 month-Upfront | I9: 2360 | J9: 2360 | L9: 30 | M9: 30 | N9: 2360 | O9: 0 | P9: 0 | R9: 30 | U9: 31 | W9: 0 | X9: 0 | Y9: 0
A10: 0 | B10: 45748 | C10: U. S. GANDHI & CO. | D10: INV-25-26-000007 | E10: subscription based service | F10: 45754 | G10: 45814 | H10: 2 months- Upfront | I10: 9440 | J10: 4720 | K10: 4720 | L10: 61 | M10: 24 | N10: 3714.098 | O10: 31 | P10: 4797.377 | R10: 6 | S10: 928.52459 | U10: 31 | W10: 0 | X10: 0 | Y10: 0
A11: Credit Note Issue | B11: 45748 | C11: Advocate Rohit Jaiswal | D11: INV-25-26-000009,00107,00177 | E11: subscription based service | F11: 45762 | G11: 45791 | H11: 1 month-Upfront | I11: 5900 | J11: 5900 | K11: 0 | L11: 30 | M11: 16 | N11: 3146.667 | O11: 14 | P11: 2753.333 | S11: 0 | V11: 0 | W11: 0 | X11: 0 | Y11: 0
A12: 0 | B12: 45748 | C12: Dileep Poolakkot | D12: INV-25-26-000010 | E12: subscription based service | F12: 45755 | G12: 46119 | H12: Annual Upfront | I12: 70800 | J12: 5900 | K12: 5900 | L12: 365 | M12: 23 | N12: 4461.37 | O12: 31 | P12: 6013.151 | Q12: 5900 | R12: 30 | S12: 5819.1781 | T12: 5900 | U12: 31 | V12: 6013.1507 | W12: 31 | X12: 5900 | Y12: 6013.151 | Z12: 30 | AA12: 5900 | AB12: 5819.178 | AC12: 31 | AD12: 5900 | AE12: 6013.151
A13: 0 | B13: 45748 | C13: Utkarsh Joshi | D13: INV-25-26-000011 | E13: subscription based service | F13: 45755 | G13: 45815 | H13: 2 months- Upfront | I13: 7080 | J13: 3540 | K13: 3540 | L13: 61 | M13: 23 | N13: 2669.508 | O13: 31 | P13: 3598.033 | R13: 7 | S13: 812.45902 | U13: 31 | W13: 0 | X13: 0 | Y13: 0
A14: 0 | B14: 45748 | C14: Karan Butalia | D14: INV-25-26-000012 | E14: subscription based service | F14: 45755 | G14: 45815 | H14: 2 months- Upfront | I14: 4720 | J14: 2360 | K14: 2360 | L14: 61 | M14: 23 | N14: 1779.672 | O14: 31 | P14: 2398.689 | R14: 7 | S14: 541.63934 | U14: 31 | W14: 0 | X14: 0 | Y14: 0
A15: 0 | B15: Jan & Apr & July & Oct 25 | C15: Agama Law Associates | D15: INV- 46, INV-25-26-000013, 277, 483, INV-25-26- (46-jan), 000013, 000277, 000483 | E15: subscription based service | F15: 45658 | G15: 46022 | H15: Annual subscription, Quarterly upfront | I15: 320000 | J15: 26666.667 | K15: 26666.667 | L15: 365 | M15: 30 | N15: 26301.37 | O15: 31 | P15: 27178.082 | Q15: 26666.667 | R15: 30 | S15: 26301.37 | T15: 26666.667 | U15: 31 | V15: 27178.082 | W15: 31 | X15: 26666.667 | Y15: 27178.082 | Z15: 30 | AA15: 26666.667 | AB15: 26301.37 | AC15: 31 | AD15: 26666.667 | AE15: 27178.082
A16: Closed- May 25 | B16: 45748 | C16: RAJANI ASSOCIATES | D16: INV-25-26-000014 | E16: subscription based service | F16: 45757 | G16: 45786 | H16: 1 month-Upfront | I16: 24780 | J16: 24780 | L16: 30 | M16: 21 | N16: 17346 | O16: 9 | P16: 7434 | R16: 30 | U16: 31 | W16: 0 | X16: 0 | Y16: 0
A17: 0 | B17: 45748 | C17: Venkatesh Dhond | D17: INV-25-26-000015 | E17: subscription based service | F17: 45716 | G17: 45896 | H17: 6 month-Upfront | I17: 100890 | J17: 16815 | K17: 16815 | L17: 181 | M17: 30 | N17: 16722.099 | O17: 31 | P17: 17279.503 | Q17: 16815 | R17: 30 | S17: 16722.099 | T17: 16815 | U17: 31 | V17: 17279.503 | W17: 27 | X17: 0 | Y17: 15049.89
A18: 0 | B18: Mar to June 25 | C18: Harshit Malik | D18: INV-000111, INV-25-26-000016, 0109 | E18: subscription based service | F18: 45725 | G18: 45786 | H18: 2 months subscription, Monthly | I18: 23600 | J18: 11800 | L18: 62 | M18: 30 | N18: 11419.355 | O18: 9 | P18: 3425.806 | R18: 30 | U18: 31 | W18: 0 | X18: 0 | Y18: 0
A19: 0 | B19: 45748 | C19: PSN Legal Advocates and Legal Consultants | D19: INV-25-26-000017 | E19: subscription based service | F19: 45757 | G19: 46121 | H19: Annual Upfront | I19: 177015 | J19: 14751.25 | K19: 14751.25 | L19: 365 | M19: 21 | N19: 10184.425 | O19: 31 | P19: 15034.151 | Q19: 14751.25 | R19: 30 | S19: 14549.178 | T19: 14751.25 | U19: 31 | V19: 15034.151 | W19: 31 | X19: 14751.25 | Y19: 15034.151 | Z19: 30 | AA19: 14751.25 | AB19: 14549.178 | AC19: 31 | AD19: 14751.25 | AE19: 15034.151
A20: 0 | B20: Apr to July 25 | C20: Swapna Sheshadri | D20: INV-25-26-000019, 113, 0184, 259, INV-25-26-000304, 000376, 000459, 000551, 000673 | E20: subscription based service | F20: 45757 | G20: 45878 | H20: 4 months subscription, Monthly | I20: 47200 | J20: 11800 | K20: 11800 | L20: 122 | M20: 21 | N20: 8124.59 | O20: 31 | P20: 11993.443 | Q20: 11800 | R20: 30 | S20: 11606.557 | T20: 11800 | U20: 31 | V20: 11993.443 | W20: 9 | Y20: 3481.967
A21: 0 | B21: 45748 | C21: Vutts & Associates LLP | D21: INV-25-26-000020 | E21: subscription based service | F21: 45758 | G21: 45848 | H21: 3 months subscription, upfront | I21: 35400 | J21: 11800 | K21: 11800 | L21: 91 | M21: 20 | N21: 7780.22 | O21: 31 | P21: 12059.341 | Q21: 11800 | R21: 30 | S21: 11670.33 | U21: 10 | V21: 3890.1099 | W21: 0 | X21: 0 | Y21: 0
A22: 0 | B22: Feb Apr to Oct 25 | C22: Darius J. Khambata | D22: INV-000085, INV-25-26-000021, INV-25-26-000022, 148, 178, 248, 337, 416, 500, 000178, 000248, 000022, 000148, 000337, 000416, 000500, 000600 | E22: subscription based service | F22: 45695 | G22: 46059 | H22: Annual-Monthly | I22: 240000 | J22: 20000 | K22: 20000 | L22: 365 | M22: 30 | N22: 19726.027 | O22: 31 | P22: 20383.562 | Q22: 20000 | R22: 30 | S22: 19726.027 | T22: 20000 | U22: 31 | V22: 20383.562 | W22: 31 | X22: 20000 | Y22: 20383.562 | Z22: 30 | AA22: 20000 | AB22: 19726.027 | AC22: 31 | AD22: 20000 | AE22: 20383.562
A23: 0 | B23: 45748 | C23: Miglani Varma & Co. | D23: INV-25-26-000023 | E23: subscription based service | F23: 45758 | G23: 45848 | H23: 3 months subscription, upfront | I23: 17700 | J23: 5900 | K23: 5900 | L23: 91 | M23: 20 | N23: 3890.11 | O23: 31 | P23: 6029.67 | Q23: 5900 | R23: 30 | S23: 5835.1648 | U23: 10 | V23: 1945.0549 | W23: 0 | X23: 0 | Y23: 0
A24: Closed- May 25 | B24: 45748 | C24: Venkatesh Mohanraj | D24: INV-25-26-000024 | E24: subscription based service | F24: 45759 | G24: 45788 | H24: 1 month-Upfront | I24: 5900 | J24: 5900 | L24: 30 | M24: 19 | N24: 3736.667 | O24: 11 | P24: 2163.333 | R24: 30 | U24: 31 | W24: 0 | X24: 0 | Y24: 0
A25: Closed- May 25 | B25: 45748 | C25: Jade Lex Partners | D25: INV-25-26-000025 | E25: subscription based service | F25: 45759 | G25: 45788 | H25: 1 month-Upfront | I25: 7080 | J25: 7080 | L25: 30 | M25: 19 | N25: 4484 | O25: 11 | P25: 2596 | R25: 30 | U25: 31 | W25: 0 | X25: 0 | Y25: 0
A26: Closed- May 25 | B26: 45748 | C26: Alankrit Bajpai | D26: INV-25-26-000026 | E26: subscription based service | F26: 45759 | G26: 45788 | H26: 1 month-Upfront | I26: 5900 | J26: 5900 | L26: 30 | M26: 19 | N26: 3736.667 | O26: 11 | P26: 2163.333 | R26: 30 | U26: 31 | W26: 0 | X26: 0 | Y26: 0
A27: Closed- May 25 | B27: 45748 | C27: Badar Durrez | D27: INV-25-26-000028 | E27: subscription based service | F27: 45760 | G27: 45789 | H27: 1 month-Upfront | I27: 5900 | J27: 5900 | L27: 30 | M27: 18 | N27: 3540 | O27: 12 | P27: 2360 | R27: 30 | U27: 31 | W27: 0 | X27: 0 | Y27: 0
A28: 0 | B28: 45748 | C28: Rashmikant and Partners | D28: INV-25-26-000029 | E28: subscription based service | F28: 45761 | G28: 46125 | H28: Annual Upfront | I28: 259600 | J28: 21633.333 | K28: 21633.333 | L28: 365 | M28: 17 | N28: 12090.959 | O28: 31 | P28: 22048.219 | Q28: 21633.333 | R28: 30 | S28: 21336.986 | T28: 21633.333 | U28: 31 | V28: 22048.219 | W28: 31 | X28: 21633.333 | Y28: 22048.219 | Z28: 30 | AA28: 21633.333 | AB28: 21336.986 | AC28: 31 | AD28: 21633.333 | AE28: 22048.219
A29: 0 | B29: Apr to June 25 | C29: TLH, Advocates & Solicitors | D29: INV-25-26-000030, 124, 198,271 | E29: subscription based service | F29: 45762 | G29: 45852 | H29: 3 months subscription, Monthly | I29: 531000 | J29: 177000 | K29: 177000 | L29: 91 | M29: 16 | N29: 93362.637 | O29: 31 | P29: 180890.11 | Q29: 177000 | R29: 30 | S29: 175054.95 | U29: 14 | V29: 81692.308 | W29: 0 | X29: 0 | Y29: 0
A30: 0 | B30: 45748 | C30: Shreeyash Lalit | D30: INV-25-26-000032 | E30: subscription based service | F30: 45762 | G30: 45944 | H30: 6 month-Upfront | I30: 42480 | J30: 7080 | K30: 7080 | L30: 183 | M30: 16 | N30: 3714.098 | O30: 31 | P30: 7196.066 | Q30: 7080 | R30: 30 | S30: 6963.9344 | T30: 7080 | U30: 31 | V30: 7196.0656 | W30: 31 | X30: 7080 | Y30: 7196.066 | Z30: 30 | AA30: 7080 | AB30: 6963.934 | AC30: 14 | AD30: 7080 | AE30: 3249.836
A31: 0 | B31: 45748 | C31: Dewani Associates | D31: INV-25-26-000033 | E31: subscription based service | F31: 45762 | G31: 45823 | H31: 2 months- Upfront | I31: 23600 | J31: 11800 | K31: 11800 | L31: 62 | M31: 16 | N31: 6090.323 | O31: 31 | P31: 11800 | R31: 15 | S31: 5709.6774 | U31: 31 | W31: 0 | X31: 0 | Y31: 0
A32: 0 | B32: Apr to Oct 25 | C32: R. Vishnu Kumar, Advocate | D32: INV-25-26-000034, 125, 199, 272, 358, 528, INV-25-26-000034-000125, 000199, 000272, 000358, 000432, 000528, 000631 | E32: subscription based service | F32: 45762 | G32: 46126 | H32: Annual-Monthly | I32: 240000 | J32: 20000 | K32: 20000 | L32: 365 | M32: 16 | N32: 10520.548 | O32: 31 | P32: 20383.562 | Q32: 20000 | R32: 30 | S32: 19726.027 | T32: 20000 | U32: 31 | V32: 20383.562 | W32: 31 | X32: 20000 | Y32: 20383.562 | Z32: 30 | AA32: 20000 | AB32: 19726.027 | AC32: 31 | AD32: 20000 | AE32: 20383.562
A33: 0 | B33: Mar & Apr 25 | C33: Yash Momaya | D33: INV-25-26-000035, 0127, 0200 | E33: subscription based service | F33: 45763 | G33: 45792 | H33: 1 month-Upfront | I33: 11800 | J33: 11800 | L33: 30 | M33: 15 | N33: 5900 | O33: 15 | P33: 5900 | Q33: 0 | R33: 30 | S33: 0 | T33: 0 | U33: 31 | V33: 0 | W33: 0 | X33: 0 | Y33: 0
A34: Closed- May 25 | B34: 45748 | C34: Chetan Dedhia | D34: INV-25-26-000036 | E34: subscription based service | F34: 45763 | G34: 45792 | H34: 1 month-Upfront | I34: 17700 | J34: 17700 | L34: 30 | M34: 15 | N34: 8850 | O34: 15 | P34: 8850 | R34: 30 | U34: 31 | W34: 0 | X34: 0 | Y34: 0
A35: 0 | B35: 45748 | C35: NC Legal | D35: INV-25-26-000037 | E35: subscription based service | F35: 45778 | G35: 46142 | H35: Annual Upfront | I35: 80240 | K35: 6686.667 | L35: 365 | M35: 0 | N35: 0 | O35: 31 | P35: 6814.904 | Q35: 6686.6667 | R35: 30 | S35: 6595.0685 | T35: 6686.6667 | U35: 31 | V35: 6814.9041 | W35: 31 | X35: 6686.667 | Y35: 6814.904 | Z35: 30 | AA35: 6686.667 | AB35: 6595.068 | AC35: 31 | AD35: 6686.667 | AE35: 6814.904
A36: Closed- May 25 | B36: 45748 | C36: Aakash Sharma | D36: INV-25-26-000038 | E36: subscription based service | F36: 45765 | G36: 45795 | H36: 1 month-Upfront | I36: 5900 | J36: 5900 | L36: 31 | M36: 13 | N36: 2474.194 | O36: 18 | P36: 3425.806 | R36: 30 | U36: 31 | W36: 0 | X36: 0 | Y36: 0
A37: Closed- May 25 | B37: 45748 | C37: Saga Legal | D37: INV-25-26-000039 | E37: subscription based service | F37: 45761 | G37: 45791 | H37: 1 month-Upfront | I37: 23600 | J37: 23600 | L37: 31 | M37: 17 | N37: 12941.935 | O37: 14 | P37: 10658.065 | R37: 30 | U37: 31 | W37: 0 | X37: 0 | Y37: 0
A38: 0 | B38: 45748 | C38: RPV LEGAL | D38: INV-25-26-000040 | E38: subscription based service | F38: 45769 | G38: 46133 | H38: Annual Upfront | I38: 175000 | J38: 14583.333 | K38: 14583.333 | L38: 365 | M38: 9 | N38: 4315.068 | O38: 31 | P38: 14863.014 | Q38: 14583.333 | R38: 30 | S38: 14383.562 | T38: 14583.333 | U38: 31 | V38: 14863.014 | W38: 31 | X38: 14583.333 | Y38: 14863.014 | Z38: 30 | AA38: 14583.333 | AB38: 14383.562 | AC38: 31 | AD38: 14583.333 | AE38: 14863.014
A39: 0 | B39: 45748 | C39: AP & Partners, Advocates | D39: INV-25-26-000041 | E39: subscription based service | F39: 45771 | G39: 45860 | H39: 3 months subscription, upfront | I39: 28320 | J39: 9440 | K39: 9440 | L39: 90 | M39: 7 | N39: 2202.667 | O39: 31 | P39: 9754.667 | Q39: 9440 | R39: 30 | S39: 9440 | U39: 22 | V39: 6922.6667 | W39: 0 | X39: 0 | Y39: 0
A40: Credit Note Issue | B40: Apr to June 25 | C40: Pranay Chitale | D40: INV-25-26-000042, 137, 213 | E40: subscription based service | F40: 45770 | G40: 45799 | H40: 1 month-Upfront | I40: 17700 | J40: 17700 | L40: 30 | M40: 8 | N40: 4720 | O40: 22 | P40: 12980 | W40: 0 | X40: 0 | Y40: 0
A41: Closed- May 25 | B41: 45748 | C41: Spark Legal | D41: INV-25-26-000043 | E41: subscription based service | F41: 45771 | G41: 45800 | H41: 1 month-Upfront | I41: 11800 | J41: 11800 | L41: 30 | M41: 7 | N41: 2753.333 | O41: 23 | P41: 9046.667 | R41: 30 | U41: 31 | W41: 0 | X41: 0 | Y41: 0
A42: 0 | B42: 45748 | C42: Bathiya Legal | D42: INV-25-26-000044 | E42: subscription based service | F42: 45771 | G42: 45862 | H42: 3 months subscription, upfront | I42: 35400 | J42: 11800 | K42: 11800 | L42: 92 | M42: 7 | N42: 2693.478 | O42: 31 | P42: 11928.261 | Q42: 11800 | R42: 30 | S42: 11543.478 | U42: 24 | V42: 9234.7826 | W42: 0 | X42: 0 | Y42: 0
A43: 0 | B43: 45748 | C43: Justice (Retd.) Kurian Joseph | D43: INV-25-26-000045 | E43: subscription based service | F43: 45774 | G43: 46138 | H43: Annual Upfront | I43: 177000 | J43: 14750 | K43: 14750 | L43: 365 | M43: 4 | N43: 1939.726 | O43: 31 | P43: 15032.877 | Q43: 14750 | R43: 30 | S43: 14547.945 | T43: 14750 | U43: 31 | V43: 15032.877 | W43: 31 | X43: 14750 | Y43: 15032.877 | Z43: 30 | AA43: 14750 | AB43: 14547.945 | AC43: 31 | AD43: 14750 | AE43: 15032.877
A44: 0 | B44: 45748 | C44: SINHA & COMPANY | D44: INV-25-26-000046 | E44: subscription based service | F44: 45772 | G44: 46136 | H44: Annual Upfront | I44: 203904 | J44: 16992 | K44: 16992 | L44: 365 | M44: 6 | N44: 3351.847 | O44: 31 | P44: 17317.874 | Q44: 16992 | R44: 30 | S44: 16759.233 | T44: 16992 | U44: 31 | V44: 17317.874 | W44: 31 | X44: 16992 | Y44: 17317.874 | Z44: 30 | AA44: 16992 | AB44: 16759.233 | AC44: 31 | AD44: 16992 | AE44: 17317.874
A45: 0 | B45: 45748 | C45: Darshit Jain | D45: INV-25-26-000047 | E45: subscription based service | F45: 45772 | G45: 46136 | H45: Annual Upfront | I45: 25488 | J45: 2124 | K45: 2124 | L45: 365 | M45: 6 | N45: 418.981 | O45: 31 | P45: 2164.734 | Q45: 2124 | R45: 30 | S45: 2094.9041 | T45: 2124 | U45: 31 | V45: 2164.7342 | W45: 31 | X45: 2124 | Y45: 2164.734 | Z45: 30 | AA45: 2124 | AB45: 2094.904 | AC45: 31 | AD45: 2124 | AE45: 2164.734
A46: 0 | B46: 45748 | C46: Sagar Ghogre | D46: INV-25-26-000048 | E46: subscription based service | F46: 45772 | G46: 46136 | H46: Annual Upfront | I46: 25488 | J46: 2124 | K46: 2124 | L46: 365 | M46: 6 | N46: 418.981 | O46: 31 | P46: 2164.734 | Q46: 2124 | R46: 30 | S46: 2094.9041 | T46: 2124 | U46: 31 | V46: 2164.7342 | W46: 31 | X46: 2124 | Y46: 2164.734 | Z46: 30 | AA46: 2124 | AB46: 2094.904 | AC46: 31 | AD46: 2124 | AE46: 2164.734
A47: 0 | B47: 45748 | C47: Chetan shah | D47: INV-25-26-000049 | E47: subscription based service | F47: 45772 | G47: 46136 | H47: Annual Upfront | I47: 25488 | J47: 2124 | K47: 2124 | L47: 365 | M47: 6 | N47: 418.981 | O47: 31 | P47: 2164.734 | Q47: 2124 | R47: 30 | S47: 2094.9041 | T47: 2124 | U47: 31 | V47: 2164.7342 | W47: 31 | X47: 2124 | Y47: 2164.734 | Z47: 30 | AA47: 2124 | AB47: 2094.904 | AC47: 31 | AD47: 2124 | AE47: 2164.734
A48: 0 | B48: 45748 | C48: Sneha Phene | D48: INV-25-26-000050 | E48: subscription based service | F48: 45772 | G48: 46136 | H48: Annual Upfront | I48: 25488 | J48: 2124 | K48: 2124 | L48: 365 | M48: 6 | N48: 418.981 | O48: 31 | P48: 2164.734 | Q48: 2124 | R48: 30 | S48: 2094.9041 | T48: 2124 | U48: 31 | V48: 2164.7342 | W48: 31 | X48: 2124 | Y48: 2164.734 | Z48: 30 | AA48: 2124 | AB48: 2094.904 | AC48: 31 | AD48: 2124 | AE48: 2164.734
A49: 0 | B49: 45748 | C49: Gunjan Mangla | D49: INV-25-26-000051 | E49: subscription based service | F49: 45772 | G49: 46136 | H49: Annual Upfront | I49: 25488 | J49: 2124 | K49: 2124 | L49: 365 | M49: 6 | N49: 418.981 | O49: 31 | P49: 2164.734 | Q49: 2124 | R49: 30 | S49: 2094.9041 | T49: 2124 | U49: 31 | V49: 2164.7342 | W49: 31 | X49: 2124 | Y49: 2164.734 | Z49: 30 | AA49: 2124 | AB49: 2094.904 | AC49: 31 | AD49: 2124 | AE49: 2164.734
A50: 0 | B50: 45748 | C50: Zulfiqar Jariwala | D50: INV-25-26-000052 | E50: subscription based service | F50: 45772 | G50: 46136 | H50: Annual Upfront | I50: 25488 | J50: 2124 | K50: 2124 | L50: 365 | M50: 6 | N50: 418.981 | O50: 31 | P50: 2164.734 | Q50: 2124 | R50: 30 | S50: 2094.9041 | T50: 2124 | U50: 31 | V50: 2164.7342 | W50: 31 | X50: 2124 | Y50: 2164.734 | Z50: 30 | AA50: 2124 | AB50: 2094.904 | AC50: 31 | AD50: 2124 | AE50: 2164.734
A51: 0 | B51: 45748 | C51: Manjari Shah | D51: INV-25-26-000053 | E51: subscription based service | F51: 45772 | G51: 46136 | H51: Annual Upfront | I51: 25488 | J51: 2124 | K51: 2124 | L51: 365 | M51: 6 | N51: 418.981 | O51: 31 | P51: 2164.734 | Q51: 2124 | R51: 30 | S51: 2094.9041 | T51: 2124 | U51: 31 | V51: 2164.7342 | W51: 31 | X51: 2124 | Y51: 2164.734 | Z51: 30 | AA51: 2124 | AB51: 2094.904 | AC51: 31 | AD51: 2124 | AE51: 2164.734
A52: 0 | B52: 45748 | C52: Sagar Sheth | D52: INV-25-26-000054 | E52: subscription based service | F52: 45772 | G52: 46136 | H52: Annual Upfront | I52: 25488 | J52: 2124 | K52: 2124 | L52: 365 | M52: 6 | N52: 418.981 | O52: 31 | P52: 2164.734 | Q52: 2124 | R52: 30 | S52: 2094.9041 | T52: 2124 | U52: 31 | V52: 2164.7342 | W52: 31 | X52: 2124 | Y52: 2164.734 | Z52: 30 | AA52: 2124 | AB52: 2094.904 | AC52: 31 | AD52: 2124 | AE52: 2164.734
A53: 0 | B53: 45748 | C53: Mahek Bookwala | D53: INV-25-26-000055 | E53: subscription based service | F53: 45772 | G53: 46136 | H53: Annual Upfront | I53: 25488 | J53: 2124 | K53: 2124 | L53: 365 | M53: 6 | N53: 418.981 | O53: 31 | P53: 2164.734 | Q53: 2124 | R53: 30 | S53: 2094.9041 | T53: 2124 | U53: 31 | V53: 2164.7342 | W53: 31 | X53: 2124 | Y53: 2164.734 | Z53: 30 | AA53: 2124 | AB53: 2094.904 | AC53: 31 | AD53: 2124 | AE53: 2164.734
A54: 0 | B54: Apr 25 & sept 25 | C54: Pradeep Sancheti | D54: INV-25-26-000056, CN 25 | E54: subscription based service | F54: 45772 | G54: 46136 | H54: Annual Upfront | I54: 0 | J54: 0 | K54: 0 | L54: 365 | M54: 6 | N54: 0 | O54: 31 | P54: 0 | Q54: 0 | R54: 30 | S54: 0 | T54: 0 | U54: 31 | V54: 0 | W54: 31 | X54: 0 | Y54: 0 | Z54: 30 | AA54: 0 | AB54: 0 | AC54: 31 | AD54: 0 | AE54: 0
A55: 0 | B55: 45748 | C55: AHUJA VALECHA & ASSOCIATES LLP | D55: INV-25-26-000057 | E55: subscription based service | F55: 45775 | G55: 45865 | H55: 3 months subscription, upfront | I55: 88500 | J55: 29500 | K55: 29500 | L55: 91 | M55: 3 | N55: 2917.582 | O55: 31 | P55: 30148.352 | Q55: 29500 | R55: 30 | S55: 29175.824 | U55: 27 | V55: 26258.242 | W55: 0 | X55: 0 | Y55: 0
A56: 0 | B56: 45748 | C56: ICL CORPORATE ADVISORY PRIVATE LIMITED | D56: INV-25-26-000058, INV-25-26-000499 | E56: subscription based service | F56: 45772 | G56: 45832 | H56: 2 months- Upfront | I56: 47200 | J56: 23600 | K56: 23600 | L56: 61 | M56: 6 | N56: 4642.623 | O56: 31 | P56: 23986.885 | R56: 24 | S56: 18570.492
A57: Closed- May 25 | B57: 45748 | C57: Argus Partners | D57: INV-25-26-000059 | E57: subscription based service | F57: 45773 | G57: 45803 | H57: 1 month-Upfront | I57: 11800 | J57: 11800 | L57: 31 | M57: 5 | N57: 1903.226 | O57: 26 | P57: 9896.774 | R57: 30 | U57: 31 | W57: 0 | X57: 0 | Y57: 0
B58: Apr to Oct 25 | C58: Pratik Patnaik | D58: INV-25-26-000060, 144, 230, 333, 382, 468, 558, INV-25-26-0060, 0144, 0230, 0333, 0382, 0468, 0558, 0688 | E58: subscription based service | F58: 45773 | G58: 46137 | H58: Annual-Monthly | I58: 169920 | J58: 14160 | K58: 14160 | L58: 365 | M58: 5 | N58: 2327.671 | O58: 360 | P58: 167592.33 | Q58: 14160 | R58: 30 | S58: 13966.027 | T58: 14160 | U58: 31 | V58: 14431.562 | W58: 31 | X58: 14160 | Y58: 14431.562 | Z58: 30 | AA58: 14160 | AB58: 13966.027 | AC58: 31 | AD58: 14160 | AE58: 14431.562
A59: 0 | B59: Jan, Apr & May 25 | C59: Saswat Mohanty | D59: INV-25-26-000061, 145 | E59: subscription based service | F59: 45687 | G59: 46052 | H59: Three Installments of 50k | I59: 159000 | J59: 13250 | K59: 13250 | L59: 366 | M59: 30 | N59: 13032.787 | O59: 31 | P59: 13467.213 | Q59: 13250 | R59: 30 | S59: 13032.787 | T59: 13250 | U59: 31 | V59: 13467.213 | W59: 31 | X59: 13250 | Y59: 13467.213 | Z59: 30 | AA59: 13250 | AB59: 13032.787 | AC59: 31 | AD59: 12230.769 | AE59: 13467.213
A60: 0 | B60: 45748 | C60: Chambers of Aman Vachher | D60: INV-25-26-000062 | E60: subscription based service | F60: 45744 | G60: 46109 | H60: Annual Upfront | I60: 203904 | J60: 16992 | K60: 16992 | L60: 366 | M60: 30 | N60: 16713.443 | O60: 31 | P60: 17270.557 | Q60: 16992 | R60: 30 | S60: 16713.443 | T60: 16992 | U60: 31 | V60: 17270.557 | W60: 31 | X60: 16992 | Y60: 17270.557 | Z60: 30 | AA60: 16992 | AB60: 16713.443 | AC60: 31 | AD60: 15684.923 | AE60: 17270.557
A61: 0 | B61: 45748 | C61: SK Singhi and Partners | D61: INV-25-26-000063 | E61: subscription based service | F61: 45744 | G61: 46109 | H61: Annual Upfront | I61: 318600 | J61: 26550 | K61: 26550 | L61: 366 | M61: 30 | N61: 26114.754 | O61: 31 | P61: 26985.246 | Q61: 26550 | R61: 30 | S61: 26114.754 | T61: 26550 | U61: 31 | V61: 26985.246 | W61: 31 | X61: 26550 | Y61: 26985.246 | Z61: 30 | AA61: 26550 | AB61: 26114.754 | AC61: 31 | AD61: 24507.692 | AE61: 26985.246
A62: Closed- May 25 | B62: 45748 | C62: Centre for Law and Policy Research Trust | D62: INV-25-26-000064 | E62: subscription based service | F62: 45776 | G62: 45805 | H62: 1 month-Upfront | I62: 4720 | J62: 4720 | L62: 30 | M62: 2 | N62: 314.667 | O62: 28 | P62: 4405.333 | R62: 30 | U62: 31 | W62: 0 | X62: 0 | Y62: 0
A63: 0 | B63: Apr to Oct 25 | C63: SKR & associates | D63: INV-25-26-000065, 114, 0185, 260, 344, 425, 510, INV-25-26-000065-000114' 000185, 000260, 000344, 000425, 000510, 000607 | E63: subscription based service | F63: 45757 | G63: 46121 | H63: Annual-Monthly | I63: 123600 | J63: 10300 | K63: 10300 | L63: 365 | M63: 21 | N63: 7111.233 | O63: 31 | P63: 10497.534 | Q63: 10300 | R63: 30 | S63: 10158.904 | T63: 10300 | U63: 31 | V63: 10497.534 | W63: 31 | X63: 10300 | Y63: 10497.534 | Z63: 30 | AA63: 10300 | AB63: 10158.904 | AC63: 31 | AD63: 10300 | AE63: 10497.534
A64: 0 | B64: Apr & Oct 25 | C64: Srivastava & Company | D64: INV-25-26-000066, 564, 000564 | E64: subscription based service | F64: 45776 | G64: 46140 | H64: Annual- Half Yearly Payment | I64: 80000 | J64: 6666.667 | K64: 6666.667 | L64: 365 | M64: 2 | N64: 438.356 | O64: 31 | P64: 6794.521 | Q64: 6666.6667 | R64: 30 | S64: 6575.3425 | T64: 6666.6667 | U64: 31 | V64: 6794.5205 | W64: 31 | X64: 6666.667 | Y64: 6794.521 | Z64: 30 | AA64: 6666.667 | AB64: 6575.342 | AC64: 31 | AD64: 6666.667 | AE64: 6794.521
A65: 0 | B65: 45748 | C65: Piyush Raheja | D65: INV-25-26-000067 | E65: subscription based service | F65: 45776 | G65: 46140 | H65: Annual Upfront | I65: 26000 | J65: 2166.667 | K65: 2166.667 | L65: 365 | M65: 2 | N65: 142.466 | O65: 31 | P65: 2208.219 | Q65: 2166.6667 | R65: 30 | S65: 2136.9863 | T65: 2166.6667 | U65: 31 | V65: 2208.2192 | W65: 31 | X65: 2166.667 | Y65: 2208.219 | Z65: 30 | AA65: 2166.667 | AB65: 2136.986 | AC65: 31 | AD65: 2166.667 | AE65: 2208.219
A66: 0 | B66: 45748 | C66: ⁠Feroze Patel | D66: INV-25-26-000068 | E66: subscription based service | F66: 45776 | G66: 46140 | H66: Annual Upfront | I66: 26000 | J66: 2166.667 | K66: 2166.667 | L66: 365 | M66: 2 | N66: 142.466 | O66: 31 | P66: 2208.219 | Q66: 2166.6667 | R66: 30 | S66: 2136.9863 | T66: 2166.6667 | U66: 31 | V66: 2208.2192 | W66: 31 | X66: 2166.667 | Y66: 2208.219 | Z66: 30 | AA66: 2166.667 | AB66: 2136.986 | AC66: 31 | AD66: 2166.667 | AE66: 2208.219
A67: 0 | B67: 45748 | C67: Kazan Shroff | D67: INV-25-26-000069 | E67: subscription based service | F67: 45776 | G67: 46140 | H67: Annual Upfront | I67: 26000 | J67: 2166.667 | K67: 2166.667 | L67: 365 | M67: 2 | N67: 142.466 | O67: 31 | P67: 2208.219 | Q67: 2166.6667 | R67: 30 | S67: 2136.9863 | T67: 2166.6667 | U67: 31 | V67: 2208.2192 | W67: 31 | X67: 2166.667 | Y67: 2208.219 | Z67: 30 | AA67: 2166.667 | AB67: 2136.986 | AC67: 31 | AD67: 2166.667 | AE67: 2208.219
A68: 0 | B68: 45748 | C68: Kajol Punjabi | D68: INV-25-26-000070 | E68: subscription based service | F68: 45776 | G68: 46140 | H68: Annual Upfront | I68: 26000 | J68: 2166.667 | K68: 2166.667 | L68: 365 | M68: 2 | N68: 142.466 | O68: 31 | P68: 2208.219 | Q68: 2166.6667 | R68: 30 | S68: 2136.9863 | T68: 2166.6667 | U68: 31 | V68: 2208.2192 | W68: 31 | X68: 2166.667 | Y68: 2208.219 | Z68: 30 | AA68: 2166.667 | AB68: 2136.986 | AC68: 31 | AD68: 2166.667 | AE68: 2208.219
A69: 0 | B69: 45748 | C69: Neeta Jain | D69: INV-25-26-000071 | E69: subscription based service | F69: 45776 | G69: 46140 | H69: Annual Upfront | I69: 26000 | J69: 2166.667 | K69: 2166.667 | L69: 365 | M69: 2 | N69: 142.466 | O69: 31 | P69: 2208.219 | Q69: 2166.6667 | R69: 30 | S69: 2136.9863 | T69: 2166.6667 | U69: 31 | V69: 2208.2192 | W69: 31 | X69: 2166.667 | Y69: 2208.219 | Z69: 30 | AA69: 2166.667 | AB69: 2136.986 | AC69: 31 | AD69: 2166.667 | AE69: 2208.219
A70: 0 | B70: 45748 | C70: Amrut Joshi | D70: INV-25-26-000072 | E70: subscription based service | F70: 45776 | G70: 46140 | H70: Annual Upfront | I70: 26000 | J70: 2166.667 | K70: 2166.667 | L70: 365 | M70: 2 | N70: 142.466 | O70: 31 | P70: 2208.219 | Q70: 2166.6667 | R70: 30 | S70: 2136.9863 | T70: 2166.6667 | U70: 31 | V70: 2208.2192 | W70: 31 | X70: 2166.667 | Y70: 2208.219 | Z70: 30 | AA70: 2166.667 | AB70: 2136.986 | AC70: 31 | AD70: 2166.667 | AE70: 2208.219
A71: 0 | B71: Jan & Apr 25 | C71: Gaurav Joshi | D71: INV-25-26-000073 | E71: subscription based service | F71: 45776 | G71: 46140 | H71: Annual subscription, Quarterly upfront | I71: 216000 | J71: 18000 | K71: 18000 | L71: 365 | M71: 30 | N71: 17753.425 | O71: 31 | P71: 18345.205 | Q71: 18000 | R71: 30 | S71: 17753.425 | T71: 18000 | U71: 31 | V71: 18345.205 | W71: 31 | X71: 18000 | Y71: 18345.205 | Z71: 30 | AA71: 18000 | AB71: 17753.425 | AC71: 31 | AD71: 18000 | AE71: 18345.205
A72: 0 | B72: 45748 | C72: Kamaljeet Singh | D72: INV-25-26-000074 | E72: subscription based service | F72: 45776 | G72: 45958 | H72: 6 month-Upfront | I72: 42480 | J72: 7080 | K72: 7080 | L72: 183 | M72: 2 | N72: 464.262 | O72: 31 | P72: 7196.066 | Q72: 7080 | R72: 30 | S72: 6963.9344 | T72: 7080 | U72: 31 | V72: 7196.0656 | W72: 31 | X72: 7080 | Y72: 7196.066 | Z72: 30 | AA72: 7080 | AB72: 6963.934 | AC72: 28 | AD72: 7080 | AE72: 6499.672
A73: Closed- May 25 | B73: 45748 | C73: Saraf and Partners | D73: INV-25-26-000075 | E73: subscription based service | F73: 45778 | G73: 45808 | H73: 1 month-Upfront | I73: 50150 | K73: 50150 | L73: 31 | M73: 0 | N73: 0 | O73: 31 | P73: 50150 | R73: 30 | U73: 31 | W73: 0 | X73: 0 | Y73: 0
A74: Closed- May 25 | B74: 45748 | C74: Pioneer Legal | D74: INV-25-26-000076, INV-25-26-000492 | E74: subscription based service | F74: 45776 | G74: 45808 | H74: 1 month-Upfront | I74: 17700 | J74: 17700 | L74: 33 | M74: 2 | N74: 1072.727 | O74: 31 | P74: 16627.273 | R74: 30 | U74: 31 | W74: 0 | X74: 0 | Y74: 0
A75: 0 | B75: 45748 | C75: Dua Associates | D75: INV-25-26-000077 | E75: subscription based service | F75: 45778 | G75: 45838 | H75: 2 months- Upfront | I75: 18880 | K75: 9440 | L75: 61 | M75: 0 | N75: 0 | O75: 31 | P75: 9594.754 | Q75: 9440 | R75: 30 | S75: 9285.2459 | U75: 31 | W75: 0 | X75: 0 | Y75: 0
A76: 0 | B76: Nov 24 to Oct 25 | C76: Manish kelker | D76: 40, INV-000088, 0112, INV-25-26-000078, 111, 0180, 256, 343, 420, 505, 000111'000180, 000256, 000343, 000420, 000505 | E76: subscription based service | F76: 45605 | G76: 45970 | H76: Annual-Monthly | I76: 47988 | J76: 3999 | K76: 3999 | L76: 366 | M76: 30 | N76: 3933.443 | O76: 31 | P76: 4064.557 | Q76: 3999 | R76: 30 | S76: 3933.4426 | T76: 3999 | U76: 31 | V76: 4064.5574 | W76: 31 | X76: 3999 | Y76: 4064.557 | Z76: 30 | AA76: 3999 | AB76: 3933.443 | AC76: 31 | AD76: 3691.385 | AE76: 4064.557
A77: 0 | B77: Dec 24 to Oct 25 | C77: Diwan Law Associates | D77: INV-000091, 0114, INV-25-26-000079, 115, 191, 263, 346, 513, INV-25-26-000079-000115'000191, 000263, 000346, 000429, 000513, 000612 | E77: subscription based service | F77: 45637 | G77: 46002 | H77: Annual-Monthly | I77: 60000 | J77: 5000 | K77: 5000 | L77: 366 | M77: 30 | N77: 4918.033 | O77: 31 | P77: 5081.967 | Q77: 5000 | R77: 30 | S77: 4918.0328 | T77: 5000 | U77: 31 | V77: 5081.9672 | W77: 31 | X77: 5000 | Y77: 5081.967 | Z77: 30 | AA77: 5000 | AB77: 4918.033 | AC77: 31 | AD77: 4615.385 | AE77: 5081.967
A78: 0 | B78: Sept to Sept 25 | C78: SRCO Legal / Salvador Raghav & Co. | D78: INV-000145,00011, INV-25-26-000080,0106, 0223, 312, 390, 474 | E78: subscription based service | F78: 45594 | G78: 45959 | H78: Annual-Monthly | I78: 96000 | J78: 8000 | K78: 8000 | L78: 366 | M78: 30 | N78: 7868.852 | O78: 31 | P78: 8131.148 | Q78: 8000 | R78: 30 | S78: 7868.8525 | T78: 8000 | U78: 31 | V78: 8131.1475 | W78: 31 | X78: 8000 | Y78: 8131.148 | Z78: 30 | AA78: 8000 | AB78: 7868.852 | AC78: 29 | AD78: 7384.615 | AE78: 7606.557
A79: 0 | B79: 45778 | C79: Sarthak Advocates & Solicitors | D79: INV-25-26-000096, INV-25-26-000297, 000373, 000458, 000550, 000666 | E79: One time work | F79: 45779 | G79: 45809 | H79: 1 month-Upfront | I79: 11800 | K79: 11800 | L79: 31 | O79: 30 | P79: 11419.355 | R79: 1 | S79: 380.64516 | U79: 31 | W79: 0 | X79: 0 | Y79: 0
A80: 0 | B80: 45778 | C80: Gupta Law Associates | D80: INV-25-26-000097 | E80: One time work | F80: 45779 | G80: 45809 | H80: 1 month-Upfront | I80: 17700 | K80: 17700 | L80: 31 | O80: 30 | P80: 17129.032 | R80: 1 | S80: 570.96774 | U80: 31 | W80: 0 | X80: 0 | Y80: 0
A81: Closed- May 25 | B81: 45778 | C81: Saraf and Partners | D81: INV-25-26-000100 | E81: One time work | F81: 45778 | G81: 45808 | H81: 1 month-Upfront | I81: 11800 | K81: 11800 | L81: 31 | O81: 31 | P81: 11800 | R81: 30 | U81: 31 | W81: 0 | X81: 0 | Y81: 0
A82: 0 | B82: 45778 | C82: Kunal Kunango | D82: INV-25-26-000101 | E82: subscription based service | F82: 45780 | G82: 46144 | H82: Annual Upfront | I82: 47988 | K82: 3999 | L82: 365 | O82: 29 | P82: 3812.745 | Q82: 3999 | R82: 30 | S82: 3944.2192 | T82: 3999 | U82: 31 | V82: 4075.6932 | W82: 31 | X82: 3999 | Y82: 4075.693 | Z82: 30 | AA82: 3999 | AB82: 3944.219 | AC82: 31 | AD82: 3999 | AE82: 4075.693
A83: 0 | B83: 45778 | C83: Divyanshu Rai | D83: INV-25-26-000102 | E83: subscription based service | F83: 45782 | G83: 46146 | H83: Annual Upfront | I83: 76464 | K83: 6372 | L83: 365 | O83: 27 | P83: 5656.241 | Q83: 6372 | R83: 30 | S83: 6284.7123 | T83: 6372 | U83: 31 | V83: 6494.2027 | W83: 31 | X83: 6372 | Y83: 6494.203 | Z83: 30 | AA83: 6372 | AB83: 6284.712 | AC83: 31 | AD83: 6372 | AE83: 6494.203
B84: May & Aug 25 | C84: Hamza mir | D84: INV-25-26-000103, 212, 265, 365, INV-25-26-000449, 000544, 000649 | E84: One time work | F84: 45727 | G84: 45910 | H84: 6 months subscription, Monthly | I84: 35400 | J84: 5900 | K84: 5900 | L84: 184 | M84: 30 | N84: 5771.739 | O84: 31 | P84: 5964.13 | Q84: 5900 | R84: 30 | S84: 5771.7391 | T84: 5900 | U84: 31 | V84: 5964.1304 | W84: 31 | X84: 5900 | Y84: 5964.13 | Z84: 10 | AB84: 1923.913
A85: 0 | B85: May to Oct 25 | C85: Chambers of Ninad Laud | D85: INV-25-26-000105, 0171, 246, 332, 415, CN-00029, 496, 000171, 000246, 000332, 000415, 000496, 000596 | E85: subscription based service | F85: 45783 | G85: 46117 | H85: Annual-Monthly | I85: 129800 | K85: 10816.667 | L85: 335 | O85: 26 | P85: 10074.03 | Q85: 10816.667 | R85: 30 | S85: 11638.356 | T85: 10816.667 | U85: 31 | V85: 12026.301 | W85: 31 | X85: 10816.667 | Y85: 12026.301 | Z85: 30 | AA85: 10816.667 | AB85: 11623.881 | AC85: 31 | AD85: 11800 | AE85: 12011.343
A86: 0 | B86: 45778 | C86: Gera Developments Pvt. Ltd. | D86: INV-25-26-000106 | E86: subscription based service | F86: 45783 | G86: 45813 | H86: 1 month-Upfront | I86: 16520 | K86: 16520 | L86: 31 | O86: 26 | P86: 13855.484 | R86: 5 | S86: 2664.5161 | U86: 31 | W86: 0 | X86: 0 | Y86: 0
A87: 0 | B87: 45778 | C87: Gaurav Mehta | D87: INV-25-26-000108 | E87: subscription based service | F87: 45784 | G87: 45875 | H87: 3 months subscription, upfront | I87: 37760 | K87: 12586.667 | L87: 92 | O87: 25 | P87: 10260.87 | Q87: 12586.667 | R87: 30 | S87: 12313.043 | T87: 12586.667 | U87: 31 | V87: 12723.478 | W87: 6 | X87: 0 | Y87: 2462.609
A88: 0 | B88: 45778 | C88: MD&T Partners | D88: INV-25-26-000110 | E88: One time work | F88: 45785 | G88: 45815 | H88: 1 month-Upfront | I88: 4720 | K88: 4720 | L88: 31 | O88: 24 | P88: 3654.194 | R88: 7 | S88: 1065.8065 | U88: 31 | W88: 0 | X88: 0 | Y88: 0
A89: 0 | B89: 45778 | C89: Kachwaha & Partners | D89: INV-25-26-000112 | E89: subscription based service | F89: 45789 | G89: 46153 | H89: Annual Upfront | I89: 254880 | K89: 21240 | L89: 365 | O89: 20 | P89: 13966.027 | Q89: 21240 | R89: 30 | S89: 20949.041 | T89: 21240 | U89: 31 | V89: 21647.342 | W89: 31 | X89: 21240 | Y89: 21647.342 | Z89: 30 | AA89: 21240 | AB89: 20949.041 | AC89: 31 | AD89: 21240 | AE89: 21647.342
A90: Closed- May 25 | B90: 45778 | C90: Zoheb Hossain | D90: INV-25-26-000116 | E90: One time work | F90: 45773 | G90: 45802 | H90: 1 month-Upfront | I90: 15000 | J90: 15000 | L90: 30 | M90: 5 | N90: 2500 | O90: 25 | P90: 12500 | R90: 30 | U90: 31 | W90: 0 | X90: 0 | Y90: 0
A91: 0 | B91: 45778 | C91: Vishal Kanade | D91: INV-25-26-000117 | E91: subscription based service | F91: 45793 | G91: 45823 | H91: 1 month-Upfront | I91: 15000 | K91: 15000.007 | L91: 31 | O91: 16 | P91: 7741.935 | R91: 15 | S91: 7258.0645 | U91: 31 | W91: 0 | X91: 0 | Y91: 0
A92: 0 | B92: 45778 | C92: Vritti Law Partners | D92: INV-25-26-000118 | E92: One time work | F92: 45789 | G92: 45819 | H92: 1 month-Upfront | I92: 7080 | K92: 7080 | L92: 31 | O92: 20 | P92: 4567.742 | R92: 11 | S92: 2512.2581 | U92: 31 | W92: 0 | X92: 0 | Y92: 0
A93: 0 | B93: 45778 | C93: SINHA & COMPANY | D93: INV-25-26-000119 | E93: subscription based service | F93: 45790 | G93: 46154 | H93: Annual Upfront | I93: 177000 | K93: 14750 | L93: 365 | O93: 19 | P93: 9213.699 | Q93: 14750 | R93: 30 | S93: 14547.945 | T93: 14750 | U93: 31 | V93: 15032.877 | W93: 31 | X93: 14750 | Y93: 15032.877 | Z93: 30 | AA93: 14750 | AB93: 14547.945 | AC93: 31 | AD93: 14750 | AE93: 15032.877
A94: 0 | B94: 45778 | C94: C&S Partners | D94: INV-25-26-000120 | E94: One time work | F94: 45791 | G94: 45821 | H94: 1 month-Upfront | I94: 14160 | K94: 14160 | L94: 31 | O94: 18 | P94: 8221.935 | R94: 13 | S94: 5938.0645 | U94: 31 | W94: 0 | X94: 0 | Y94: 0
A95: 0 | B95: 45778 | C95: Asahi Legal LLP | D95: INV-25-26-000121 | E95: subscription based service | F95: 45781 | G95: 45873 | H95: 3 months subscription, upfront | I95: 22500 | K95: 7500 | L95: 93 | O95: 28 | P95: 6774.194 | Q95: 7500 | R95: 30 | S95: 7258.0645 | T95: 7500 | U95: 31 | V95: 7500 | W95: 4 | X95: 0 | Y95: 967.742
A96: 0 | B96: 45778 | C96: Chambers of Moazzam Khan | D96: INV-25-26-000122 | E96: subscription based service | F96: 45790 | G96: 45973 | H96: 6 month-Upfront | I96: 95580 | K96: 15930 | L96: 184 | O96: 19 | P96: 9869.674 | Q96: 15930 | R96: 30 | S96: 15583.696 | T96: 15930 | U96: 31 | V96: 16103.152 | W96: 31 | X96: 15930 | Y96: 16103.152 | Z96: 30 | AA96: 15930 | AB96: 15583.696 | AC96: 31 | AD96: 15930 | AE96: 16103.152
A97: 0 | B97: 45778 | C97: Vis Legis Law Practice | D97: INV-25-26-000123, INV-25-26-000511 | E97: subscription based service | F97: 45782 | G97: 45813 | H97: 1 month-Upfront | I97: 23600 | K97: 23600 | L97: 32 | O97: 27 | P97: 19912.5 | R97: 5 | S97: 3687.5 | U97: 31 | W97: 0 | X97: 0 | Y97: 0
A98: 0 | B98: 45778 | C98: Phoenix Legal | D98: INV-25-26-000126 | E98: subscription based service | F98: 45793 | G98: 45854 | H98: 2 months- Upfront | I98: 118000 | K98: 59000 | L98: 62 | O98: 16 | P98: 30451.613 | Q98: 59000 | R98: 30 | S98: 57096.774 | U98: 16 | V98: 30451.613 | W98: 0 | X98: 0 | Y98: 0
A99: 0 | B99: 45778 | C99: Nikhil Pai | D99: INV-25-26-000128 | E99: subscription based service | F99: 45793 | G99: 46157 | H99: Annual Upfront | I99: 64900 | K99: 5408.333 | L99: 365 | O99: 16 | P99: 2844.932 | Q99: 5408.3333 | R99: 30 | S99: 5334.2466 | T99: 5408.3333 | U99: 31 | V99: 5512.0548 | W99: 31 | X99: 5408.333 | Y99: 5512.055 | Z99: 30 | AA99: 5408.333 | AB99: 5334.247 | AC99: 31 | AD99: 5408.333 | AE99: 5512.055
A100: 0 | B100: 45778 | C100: J INFRATECH LIMITED | D100: INV-25-26-000129 | E100: One time work | F100: 45793 | G100: 45824 | H100: 1 month-Upfront | I100: 4720 | K100: 4720 | L100: 32 | O100: 16 | P100: 2360 | R100: 16 | S100: 2360 | U100: 31 | W100: 0 | X100: 0 | Y100: 0
...

Sheet Invoices
F2: =SUBTOTAL(9,F23:F54) | H2: =SUBTOTAL(9,H23:H54)
A3: Months | B3: Invoice Date | C3: Invoice Number | D3: Invoice Status | E3: Customer Name | F3: Taxable Value | G3: Total Tax | H3: Total | I3: Nature
A4: 45627 | B4: 45628 | C4: INV-000027 | D4: Closed | E4: B2C | F4: 1295 | G4: 0 | H4: 1295 | I4: B2C | K4: Sum of Taxable Value | L4: Nature
A5: 45627 | B5: 45628 | C5: INV-000028 | D5: Closed | E5: Office of ASG (N. Venkatraman) | F5: 195000 | G5: 0 | H5: 195000 | I5: B2B | K5: Months | L5: B2B | M5: B2C | N5: (empty) | O5: Total Result
A6: 45627 | B6: 45635 | C6: INV-000029 | D6: Closed | E6: B2C | F6: 9164 | G6: 0 | H6: 9164 | I6: B2C | K6: 45536 | L6: 3999 | M6: 23809 | O6: 27808
A7: 45627 | B7: 45635 | C7: INV-000030 | D7: Closed | E7: Kanungo & Co. | F7: 3999 | G7: 0 | H7: 3999 | I7: B2B | K7: 45566 | L7: 49997 | M7: 41135 | O7: 91132
A8: 45627 | B8: 45638 | C8: INV-000031 | D8: Closed | E8: B2C | F8: 3786 | G8: 0 | H8: 3786 | I8: B2C | K8: 45597 | L8: 158496 | M8: 20926 | O8: 179422
A9: 45627 | B9: 45638 | C9: INV-000032 | D9: Closed | E9: Diwan Law Associates | F9: 5000 | G9: 0 | H9: 5000 | I9: B2B | K9: 45627 | L9: 514892 | M9: 34284 | O9: 549176
A10: 45627 | B10: 45639 | C10: INV-000033 | D10: Closed | E10: Aditya Sikka / Tvashta Law | F10: 45000 | G10: 0 | H10: 45000 | I10: B2B | K10: 45658 | L10: 1464041 | M10: 32266 | O10: 1496307
A11: 45627 | B11: 45639 | C11: INV-000034 | D11: Closed | E11: B2C | F11: 1493 | G11: 0 | H11: 1493 | I11: B2C | K11: 45689 | L11: 1192593 | M11: 33183 | O11: 1225776
A12: 45627 | B12: 45640 | C12: INV-000035 | D12: Closed | E12: Amrita Panda / Chambers of Amrita Panda | F12: 10000 | G12: 0 | H12: 10000 | I12: B2B | K12: 45717 | L12: 4569923 | M12: 50543 | O12: 4620466
A13: 45627 | B13: 45644 | C13: INV-000036 | D13: Closed | E13: B2C | F13: 5481 | G13: 0 | H13: 5481 | I13: B2C | K13: 45748 | L13: 4040388 | M13: 42252 | O13: 4082640
A14: 45627 | B14: 45644 | C14: INV-000037 | D14: Closed | E14: Ish Jain / Regius Partners LLP | F14: 146994 | G14: 0 | H14: 146994 | I14: B2B | K14: 45778 | L14: 4666763 | M14: 24128 | O14: 4690891
A15: 45627 | B15: 45645 | C15: INV-000038 | D15: Closed | E15: The Guild | Advocates & Associate Counsel | F15: 60000 | G15: 0 | H15: 60000 | I15: B2B | K15: 45809 | L15: 3054847.7 | M15: 24554.28 | O15: 3079401.9
A16: 45627 | B16: 45648 | C16: INV-000039 | D16: Closed | E16: B2C | F16: 2293 | G16: 0 | H16: 2293 | I16: B2C | K16: 45839 | L16: 8195261 | M16: 19474 | O16: 8214735
A17: 45627 | B17: 45648 | C17: INV-000040 | D17: Closed | E17: Manish kelker | F17: 3999 | G17: 0 | H17: 3999 | I17: B2B | K17: 45870 | L17: 9351621 | M17: 18627 | O17: 9370248
A18: 45627 | B18: 45651 | C18: INV-000041 | D18: Closed | E18: B2C | F18: 2095 | G18: 0 | H18: 2095 | I18: B2C | K18: 45901 | L18: 4189179.5 | M18: 14394.92 | O18: 4203574.5
A19: 45627 | B19: 45651 | C19: INV-000042 | D19: Closed | E19: Abhimanyu Garg / Methodica Legal | F19: 36900 | G19: 0 | H19: 36900 | I19: B2B | K19: (empty)
A20: 45627 | B20: 45655 | C20: INV-000043 | D20: Closed | E20: B2C | F20: 3687 | G20: 0 | H20: 3687 | I20: B2C | K20: 45931 | L20: 5730227.7 | M20: 13549.16 | O20: 5743776.8
A21: 45627 | B21: 45655 | C21: INV-000044 | D21: Closed | E21: SRCO Legal / Salvador Raghav & Co. | F21: 8000 | G21: 0 | H21: 8000 | I21: B2B | K21: Total Result | L21: 47182229 | M21: 393125.36 | O21: 47575354
A22: 45627 | B22: 45657 | C22: INV-000045 | D22: Closed | E22: B2C | F22: 4990 | G22: 0 | H22: 4990 | I22: B2C
A23: 45658 | B23: 45658 | C23: INV-000046 | D23: Closed | E23: Agama Law Associates | F23: 80000 | G23: 0 | H23: 80000 | I23: B2B
A24: 45658 | B24: 45662 | C24: INV-000047 | D24: Closed | E24: B2C | F24: 6780 | G24: 0 | H24: 6780 | I24: B2C
A25: 45658 | B25: 45662 | C25: INV-000048 | D25: Closed | E25: Gourab Banerji | F25: 49998 | G25: 0 | H25: 49998 | I25: B2B
A26: 45658 | B26: 45665 | C26: INV-000049 | D26: Closed | E26: B2C | F26: 1691 | G26: 0 | H26: 1691 | I26: B2C
A27: 45658 | B27: 45665 | C27: INV-000050 | D27: Closed | E27: Parakram Legal | F27: 5000 | G27: 0 | H27: 5000 | I27: B2B
A28: 45658 | B28: 45666 | C28: INV-000051 | D28: Closed | E28: Kanungo & Co. | F28: 3999 | G28: 0 | H28: 3999 | I28: B2B
A29: 45658 | B29: 45668 | C29: INV-000052 | D29: Closed | E29: B2C | F29: 4487 | G29: 0 | H29: 4487 | I29: B2C
A30: 45658 | B30: 45668 | C30: INV-000053 | D30: Closed | E30: Diwan Law Associates | F30: 5000 | G30: 0 | H30: 5000 | I30: B2B
A31: 45658 | B31: 45671 | C31: INV-000054 | D31: Closed | E31: B2C | F31: 1889 | G31: 0 | H31: 1889 | I31: B2C
A32: 45658 | B32: 45671 | C32: INV-000055 | D32: Closed | E32: Mustafa S. Doctor | F32: 162000 | G32: 0 | H32: 162000 | I32: B2B
A33: 45658 | B33: 45674 | C33: INV-000056 | D33: Closed | E33: B2C | F33: 5683 | G33: 0 | H33: 5683 | I33: B2C
... A308: 45597 | B308: 45626 | C308: INV-000026 | D308: Closed | E308: B2C | F308: 2293 | G308: 0 | H308: 2293 | I308: B2C
A309: 45809 | B309: 45809 | C309: INV-25-26-000161 | D309: Overdue | E309: LEGALOGIC CONSULTING LLP | F309: 38000 | G309: 6840 | H309: =F309+G309 | I309: B2B | J309: =VLOOKUP(C309,'FY 25-26-Accrual'!$D$192:$D$233,1,0)
A310: 45809 | B310: 45810 | C310: INV-25-26-000162 | D310: Closed | E310: B2C | F310: 6772.88 | G310: 1219.1184 | H310: =F310+G310 | I310: B2C | J310: =VLOOKUP(C310,'FY 25-26-Accrual'!$D$192:$D$233,1,0)
A311: 45809 | B311: 45810 | C311: INV-25-26-000163 | D311: Closed | E311: Poovayya & CO | F311: 20000 | G311: 3600 | H311: =F311+G311 | I311: B2B | J311: =VLOOKUP(C311,'FY 25-26-Accrual'!$D$192:$D$233,1,0)
A312: 45809 | B312: 45810 | C312: INV-25-26-000164 | D312: Closed | E312: Sajan Poovayya | F312: 20000 | G312: 3600 | H312: =F312+G312 | I312: B2B | J312: =VLOOKUP(C312,'FY 25-26-Accrual'!$D$192:$D$233,1,0)
A313: 45809 | B313: 45811 | C313: INV-25-26-000165 | D313: Overdue | E313: Shrey Lodha | F313: 10000 | G313: 1800 | H313: =F313+G313 | I313: B2B | J313: ='FY 25-26-Accrual'!$D$234
A314: 45809 | B314: 45812 | C314: INV-25-26-000166 | D314: Closed | E314: Gupta Law Associates | F314: 15000 | G314: 2700 | H314: =F314+G314 | I314: B2B | J314: =VLOOKUP(C314,'FY 25-26-Accrual'!$D$192:$D$233,1,0)
A315: 45809 | B315: 45812 | C315: INV-25-26-000167 | D315: Overdue | E315: Vardharma Chambers | F315: 7000 | G315: 1260 | H315: =F315+G315 | I315: B2B | J315: =VLOOKUP(C315,'FY 25-26-Accrual'!$D$192:$D$233,1,0)
A316: 45809 | B316: 45812 | C316: INV-25-26-000168 | D316: Closed | E316: Birendra Saraf | F316: 216000 | G316: 38880 | H316: =F316+G316 | I316: B2B | J316: =VLOOKUP(C316,'FY 25-26-Accrual'!$D$192:$D$233,1,0)
A317: 45809 | B317: 45812 | C317: INV-25-26-000169 | D317: Closed | E317: IRIS LEGAL | F317: 8474.58 | G317: 1525.4244 | H317: =F317+G317 | I317: B2B | J317: =VLOOKUP(C317,'FY 25-26-Accrual'!$D$192:$D$233,1,0)
A318: 45809 | B318: 45813 | C318: INV-25-26-000170 | D318: Closed | E318: B2C | F318: 17781.4 | G318: 3200.652 | H318: =F318+G318 | I318: B2C | J318: =VLOOKUP(C318,'FY 25-26-Accrual'!$D$192:$D$233,1,0)
A319: 45809 | B319: 45814 | C319: INV-25-26-000171 | D319: Closed | E319: Chambers of Ninad Laud | F319: 10000 | G319: 1800 | H319: =F319+G319 | I319: B2B | J319: ='FY 25-26-Accrual'!$D$85
A320: 45809 | B320: 45814 | C320: INV-25-26-000172 | D320: Closed | E320: JYOT-A Public Trust | F320: 63000 | G320: 11340 | H320: =F320+G320 | I320: B2B | J320: =VLOOKUP(C320,'FY 25-26-Accrual'!$D$192:$D$233,1,0)
A321: 45809 | B321: 45814 | C321: INV-25-26-000173 | D321: Closed | E321: Yakshay Chheda | F321: 8474.58 | G321: 1525.4244 | H321: =F321+G321 | I321: B2B | J321: =VLOOKUP(C321,'FY 25-26-Accrual'!$D$192:$D$233,1,0)
A322: 45809 | B322: 45814 | C322: INV-25-26-000174 | D322: Closed | E322: Tipping Mr Pink Private Limited | F322: 7000 | G322: 1260 | H322: =F322+G322 | I322: B2B | J322: =VLOOKUP(C322,'FY 25-26-Accrual'!$D$192:$D$233,1,0)
A323: 45809 | B323: 45814 | C323: INV-25-26-000175 | D323: Closed | E323: KUAJ LEGAL | F323: 80000 | G323: 14400 | H323: =F323+G323 | I323: B2B | J323: =VLOOKUP(C323,'FY 25-26-Accrual'!$D$192:$D$233,1,0)
A324: 45809 | B324: 45814 | C324: INV-25-26-000176 | D324: Closed | E324: AJNM LAW INDIA LLP | F324: 20000 | G324: 3600 | H324: =F324+G324 | I324: B2B | J324: =VLOOKUP(C324,'FY 25-26-Accrual'!$D$192:$D$233,1,0)
A325: 45809 | B325: 45815 | C325: INV-25-26-000177 | D325: Closed | E325: Advocate Rohit Jaiswal | F325: 5000 | G325: 900 | H325: =F325+G325 | I325: B2B | J325: ='FY 25-26-Accrual'!$D$11
A326: 45809 | B326: 45815 | C326: INV-25-26-000178 | D326: Overdue | E326: Darius J. Khambata | F326: 16949.15 | G326: 3050.847 | H326: =F326+G326 | I326: B2B | J326: ='FY 25-26-Accrual'!$D$22
A327: 45809 | B327: 45815 | C327: INV-25-26-000179 | D327: Overdue | E327: Harshit Malik | F327: 10000 | G327: 1800 | H327: =F327+G327 | I327: B2B | J327: ='FY 25-26-Accrual'!$D$18
A328: 45809 | B328: 45817 | C328: INV-25-26-000180 | D328: Closed | E328: Manish kelker | F328: 3388.98 | G328: 610.0164 | H328: =F328+G328 | I328: B2B | J328: ='FY 25-26-Accrual'!$D$76
A329: 45809 | B329: 45817 | C329: INV-25-26-000181 | D329: Closed | E329: Agraa Legal | F329: 420000 | G329: 75600 | H329: =F329+G329 | I329: B2B | J329: =VLOOKUP(C329,'FY 25-26-Accrual'!$D$192:$D$233,1,0)
A330: 45809 | B330: 45817 | C330: INV-25-26-000182 | D330: Overdue | E330: KINJAL CIVILCON LLP | F330: 15000 | G330: 2700 | H330: =F330+G330 | I330: B2B | J330: =VLOOKUP(C330,'FY 25-26-Accrual'!$D$192:$D$233,1,0)
A331: 45809 | B331: 45817 | C331: INV-25-26-000183 | D331: Closed | E331: Abhimanyu Garg / Methodica Legal | F331: 31271.19 | G331: 5628.8142 | H331: =F331+G331 | I331: B2B | J331: ='FY 25-26-Accrual'!$D$161
A332: 45809 | B332: 45818 | C332: INV-25-26-000184 | D332: Closed | E332: Swapna Sheshadri | F332: 10000 | G332: 1800 | H332: =F332+G332 | I332: B2B | J332: ='FY 25-26-Accrual'!$D$20
A333: 45809 | B333: 45818 | C333: INV-25-26-000185 | D333: Closed | E333: SKR & associates | F333: 8729 | G333: 1571.22 | H333: =F333+G333 | I333: B2B | J333: ='FY 25-26-Accrual'!$D$63
A334: 45809 | B334: 45818 | C334: INV-25-26-000186 | D334: Closed | E334: Shobit Phutela | F334: 108000 | G334: 19440 | H334: =F334+G334 | I334: B2B | J334: =VLOOKUP(C334,'FY 25-26-Accrual'!$D$192:$D$233,1,0)
A335: 45809 | B335: 45818 | C335: INV-25-26-000187 | D335: Overdue | E335: Narottam Sharma | F335: 108000 | G335: 19440 | H335: =F335+G335 | I335: B2B | J335: =VLOOKUP(C335,'FY 25-26-Accrual'!$D$192:$D$233,1,0)
A336: 45809 | B336: 45818 | C336: INV-25-26-000188 | D336: Closed | E336: Monalisa Kosaria | F336: 30000 | G336: 5400 | H336: =F336+G336 | I336: B2B | J336: =VLOOKUP(C336,'FY 25-26-Accrual'!$D$192:$D$233,1,0)
A337: 45809 | B337: 45819 | C337: INV-25-26-000189 | D337: Closed | E337: Rahul Saboo, Advocate | F337: 8474.58 | G337: 1525.4244 | H337: =F337+G337 | I337: B2B | J337: =VLOOKUP(C337,'FY 25-26-Accrual'!$D$192:$D$233,1,0)
A338: 45809 | B338: 45819 | C338: INV-25-26-000190 | D338: Overdue | E338: DSK Legal | F338: 50000 | G338: 9000 | H338: =F338+G338 | I338: B2B | J338: =VLOOKUP(C338,'FY 25-26-Accrual'!$D$192:$D$233,1,0)
A339: 45809 | B339: 45820 | C339: INV-25-26-000191 | D339: Closed | E339: Diwan Law Associates | F339: 4237.29 | G339: 762.7122 | H339: =F339+G339 | I339: B2B | J339: ='FY 25-26-Accrual'!$D$77
A340: 45809 | B340: 45820 | C340: INV-25-26-000192 | D340: Closed | E340: RAJANI ASSOCIATES | F340: 21000 | G340: 3780 | H340: =F340+G340 | I340: B2B | J340: =VLOOKUP(C340,'FY 25-26-Accrual'!$D$192:$D$233,1,0)
A341: 45809 | B341: 45820 | C341: INV-25-26-000193 | D341: Closed | E341: RAJANI ASSOCIATES | F341: 14000 | G341: 2520 | H341: =F341+G341 | I341: B2B | J341: =VLOOKUP(C341,'FY 25-26-Accrual'!$D$192:$D$233,1,0)
A342: 45809 | B342: 45821 | C342: INV-25-26-000194 | D342: Closed | E342: Meghna Talwar | F342: 60000 | G342: 10800 | H342: =F342+G342 | I342: B2B | J342: =VLOOKUP(C342,'FY 25-26-Accrual'!$D$192:$D$233,1,0)
A343: 45809 | B343: 45821 | C343: INV-25-26-000195 | D343: Closed | E343: Miglani Varma & Co. | F343: 70000 | G343: 12600 | H343: =F343+G343 | I343: B2B | J343: =VLOOKUP(C343,'FY 25-26-Accrual'!$D$192:$D$233,1,0)
A344: 45809 | B344: 45821 | C344: INV-25-26-000196 | D344: Closed | E344: S Priya | F344: 8000 | G344: 1440 | H344: =F344+G344 | I344: B2B | J344: =VLOOKUP(C344,'FY 25-26-Accrual'!$D$192:$D$233,1,0)
A345: 45809 | B345: 45822 | C345: INV-25-26-000197 | D345: Closed | E345: Megha Chandra | F345: 10000 | G345: 1800 | H345: =F345+G345 | I345: B2B | J345: ='FY 25-26-Accrual'!$D$162
A346: 45809 | B346: 45823 | C346: INV-25-26-000198 | D346: Overdue | E346: TLH, Advocates & Solicitors | F346: 150000 | G346: 27000 | H346: =F346+G346 | I346: B2B | J346: ='FY 25-26-Accrual'!$D$29
A347: 45809 | B347: 45823 | C347: INV-25-26-000199 | D347: Closed | E347: R. Vishnu Kumar, Advocate | F347: 16950 | G347: 3051 | H347: =F347+G347 | I347: B2B | J347: ='FY 25-26-Accrual'!$D$32
A348: 45809 | B348: 45824 | C348: INV-25-26-000200 | D348: Overdue | E348: Yash Momaya | F348: 10000 | G348: 1800 | H348: =F348+G348 | I348: B2B | J348: ='FY 25-26-Accrual'!$D$33
A349: 45809 | B349: 45824 | C349: INV-25-26-000201 | D349: Closed | E349: Joy Baxi & Associates | F349: 36000 | G349: 6480 | H349: =F349+G349 | I349: B2B | J349: =VLOOKUP(C349,'FY 25-26-Accrual'!$D$192:$D$233,1,0)
A350: 45809 | B350: 45825 | C350: INV-25-26-000202 | D350: Closed | E350: Dewani Associates | F350: 108000 | G350: 19440 | H350: =F350+G350 | I350: B2B | J350: =VLOOKUP(C350,'FY 25-26-Accrual'!$D$192:$D$233,1,0)
A351: 45809 | B351: 45825 | C351: INV-25-26-000203 | D351: Overdue | E351: Ganesh & Co. | F351: 205000 | G351: 36900 | H351: =F351+G351 | I351: B2B | J351: =VLOOKUP(C351,'FY 25-26-Accrual'!$D$192:$D$233,1,0)
A352: 45809 | B352: 45826 | C352: INV-25-26-000204 | D352: Closed | E352: AMS Legal | F352: 7000 | G352: 1260 | H352: =F352+G352 | I352: B2B | J352: =VLOOKUP(C352,'FY 25-26-Accrual'!$D$192:$D$233,1,0)
A353: 45809 | B353: 45827 | C353: INV-25-26-000205 | D353: Closed | E353: Vis Legis Law Practice | F353: 126000 | G353: 22680 | H353: =F353+G353 | I353: B2B | J353: =VLOOKUP(C353,'FY 25-26-Accrual'!$D$192:$D$233,1,0)
A354: 45809 | B354: 45827 | C354: INV-25-26-000206 | D354: Overdue | E354: U. S. GANDHI & CO. | F354: 18000 | G354: 3240 | H354: =F354+G354 | I354: B2B | J354: =VLOOKUP(C354,'FY 25-26-Accrual'!$D$192:$D$233,1,0)
A355: 45809 | B355: 45827 | C355: INV-25-26-000207 | D355: Closed | E355: Gauri Puri | F355: 5000 | G355: 900 | H355: =F355+G355 | I355: B2B | J355: =VLOOKUP(C355,'FY 25-26-Accrual'!$D$192:$D$233,1,0)
A356: 45809 | B356: 45827 | C356: INV-25-26-000208 | D356: Closed | E356: Amit Bhagat | F356: 5000 | G356: 900 | H356: =F356+G356 | I356: B2B | J356: =VLOOKUP(C356,'FY 25-26-Accrual'!$D$192:$D$233,1,0)
A357: 45809 | B357: 45828 | C357: INV-25-26-000209 | D357: Closed | E357: Vishal Kanade | F357: 162000 | G357: 29160 | H357: =F357+G357 | I357: B2B | J357: =VLOOKUP(C357,'FY 25-26-Accrual'!$D$192:$D$233,1,0)
A358: 45809 | B358: 45829 | C358: INV-25-26-000210 | D358: Overdue | E358: Stride Legal | F358: 10000 | G358: 1800 | H358: =F358+G358 | I358: B2B | J358: ='FY 25-26-Accrual'!$D$107
A359: 45809 | B359: 45829 | C359: INV-25-26-000211 | D359: Closed | E359: Sundeep Karnik | F359: 56000 | G359: 10080 | H359: =F359+G359 | I359: B2B | J359: =VLOOKUP(C359,'FY 25-26-Accrual'!$D$192:$D$233,1,0)
A360: 45809 | B360: 45829 | C360: INV-25-26-000212 | D360: Closed | E360: Hamza mir | F360: 5000 | G360: 900 | H360: =F360+G360 | I360: B2B | J360: ='FY 25-26-Accrual'!$D$84
A361: 45809 | B361: 45831 | C361: INV-25-26-000213 | D361: Overdue | E361: Pranay Chitale | F361: 15000 | G361: 2700 | H361: =F361+G361 | I361: B2B | J361: ='FY 25-26-Accrual'!$D$40
A362: 45809 | B362: 45831 | C362: INV-25-26-000214 | D362: Closed | E362: Rohan Talwar | F362: 35000 | G362: 6300 | H362: =F362+G362 | I362: B2B | J362: =VLOOKUP(C362,'FY 25-26-Accrual'!$D$192:$D$233,1,0)
A363: 45809 | B363: 45831 | C363: INV-25-26-000215 | D363: Overdue | E363: ZEUS Law Associates | F363: 40000 | G363: 7200 | H363: =F363+G363 | I363: B2B | J363: =VLOOKUP(C363,'FY 25-26-Accrual'!$D$192:$D$233,1,0)
A364: 45809 | B364: 45832 | C364: INV-25-26-000216 | D364: Overdue | E364: Aurtus Consulting LLP | F364: 54000 | G364: 9720 | H364: =F364+G364 | I364: B2B | J364: =VLOOKUP(C364,'FY 25-26-Accrual'!$D$192:$D$233,1,0)
A365: 45809 | B365: 45832 | C365: INV-25-26-000217 | D365: Overdue | E365: Tvashta Law | F365: 180000 | G365: 32400 | H365: =F365+G365 | I365: B2B | J365: =VLOOKUP(C365,'FY 25-26-Accrual'!$D$192:$D$233,1,0)
A366: 45809 | B366: 45833 | C366: INV-25-26-000218 | D366: Closed | E366: Abhimanyu Garg / Methodica Legal | F366: 31271.19 | G366: 5628.8142 | H366: =F366+G366 | I366: B2B | J366: ='FY 25-26-Accrual'!$D$161
A367: 45809 | B367: 45834 | C367: INV-25-26-000219 | D367: Closed | E367: The Guild | Advocates & Associate Counsel | F367: 50847.46 | G367: 9152.5428 | H367: =F367+G367 | I367: B2B | J367: ='FY 25-26-Accrual'!$D$160
A368: 45809 | B368: 45834 | C368: CN-00003 | D368: Closed | E368: Advocate Rohit Jaiswal | F368: -5000 | G368: -900 | H368: =F368+G368 | I368: B2B | J368: ='FY 25-26-Accrual'!$D$11
A369: 45809 | B369: 45834 | C369: CN-00004 | D369: Closed | E369: Advocate Rohit Jaiswal | F369: -5000 | G369: -900 | H369: =F369+G369 | I369: B2B | J369: ='FY 25-26-Accrual'!$D$11
A370: 45809 | B370: 45835 | C370: INV-25-26-000220 | D370: Closed | E370: Tejeshwar Singh | F370: 30000 | G370: 5400 | H370: =F370+G370 | I370: B2B | J370: =VLOOKUP(C370,'FY 25-26-Accrual'!$D$192:$D$233,1,0)
A371: 45809 | B371: 45835 | C371: INV-25-26-000221 | D371: Closed | E371: Apoorv Kurup | F371: 35000 | G371: 6300 | H371: =F371+G371 | I371: B2B | J371: =VLOOKUP(C371,'FY 25-26-Accrual'!$D$192:$D$233,1,0)
A372: 45809 | B372: 45836 | C372: INV-25-26-000222 | D372: Closed | E372: Elixir Legal Services | F372: 63000 | G372: 11340 | H372: =F372+G372 | I372: B2B | J372: =VLOOKUP(C372,'FY 25-26-Accrual'!$D$192:$D$233,1,0)
A373: 45809 | B373: 45837 | C373: INV-25-26-000223 | D373: Closed | E373: SRCO Legal / Salvador Raghav & Co. | F373: 6779.66 | G373: 1220.3388 | H373: =F373+G373 | I373: B2B | J373: ='FY 25-26-Accrual'!$D$78
A374: 45809 | B374: 45838 | C374: INV-25-26-000224 | D374: Closed | E374: Deep Cover Law- Chirag Narasimiah | F374: 9000 | G374: 1620 | H374: =F374+G374 | I374: B2B | J374: ='FY 25-26-Accrual'!$D$124
A375: 45809 | B375: 45838 | C375: INV-25-26-000225 | D375: Closed | E375: Harshit Malik | F375: 60000 | G375: 10800 | H375: =F375+G375 | I375: B2B | J375: =VLOOKUP(C375,'FY 25-26-Accrual'!$D$192:$D$233,1,0)
...

Sheet Invoice
A1: Invoice Date | B1: Invoice ID | C1: Invoice Number | D1: Invoice Status | E1: Customer ID | F1: Customer Name | G1: Place of Supply | H1: Place of Supply(With State Code) | I1: GST Treatment | J1: Is Inclusive Tax | K1: Due Date | L1: PurchaseOrder | M1: Currency Code | N1: Exchange Rate | O1: Discount Type | P1: Is Discount Before Tax | Q1: Template Name | R1: Entity Discount Percent | S1: TCS Tax Name | T1: TCS Percentage | U1: TDS Calculation Type | V1: TDS Name | W1: TDS Percentage | X1: TDS Section Code | Y1: TDS Section | Z1: TDS Amount | AA1: SubTotal | AB1: Total | AC1: Balance | AD1: Adjustment | AE1: Adjustment Description | AF1: Expected Payment Date | AG1: Last Payment Date | AH1: Payment Terms | AI1: Payment Terms Label | AJ1: Notes | AK1: Terms & Conditions | AL1: E-WayBill Number | AM1: E-WayBill Generated Time | AN1: E-WayBill Status | AO1: E-WayBill Cancelled Time | AP1: E-WayBill Expired Time | AQ1: Transporter Name | AR1: Transporter ID | AS1: TCS Amount | AT1: Invoice Type | AU1: Entity Discount Amount | AV1: Shipping Charge | AW1: Shipping Charge Tax ID | AX1: Shipping Charge Tax Amount | AY1: Shipping Charge Tax Name | AZ1: Shipping Charge Tax % | BA1: Shipping Charge Tax Type | BB1: Shipping Charge Tax Exemption Code | BC1: Shipping Charge SAC Code | BD1: Item Name | BE1: Item Desc | BF1: Quantity | BG1: Discount | BH1: Discount Amount | BI1: Item Total | BJ1: Usage unit | BK1: Item Price | BL1: Product ID | BM1: Brand | BN1: Sales Order Number | BO1: Expense Reference ID | BP1: Recurrence Name | BQ1: Billing Attention | BR1: Billing Address | BS1: Billing Street2 | BT1: Billing City | BU1: Billing State | BV1: Billing Country | BW1: Billing Code | BX1: Billing Phone | BY1: Billing Fax | BZ1: Shipping Attention | CA1: Shipping Address | CB1: Shipping Street2 | CC1: Shipping City | CD1: Shipping State | CE1: Shipping Country | CF1: Shipping Code | CG1: Shipping Fax | CH1: Shipping Phone Number | CI1: Supplier Org Name | CJ1: Supplier GST Registration Number | CK1: Supplier Street Address | CL1: Supplier City | CM1: Supplier State | CN1: Supplier Country | CO1: Supplier ZipCode | CP1: Supplier Phone | CQ1: Supplier E-Mail | CR1: CGST Rate % | CS1: SGST Rate % | CT1: IGST Rate % | CU1: CESS Rate % | CV1: CGST(FCY) | CW1: SGST(FCY) | CX1: IGST(FCY) | CY1: CESS(FCY) | CZ1: CGST | DA1: SGST | DB1: IGST | DC1: CESS | DD1: Reverse Charge Tax Name | DE1: Reverse Charge Tax Rate | DF1: Reverse Charge Tax Type | DG1: Item TDS Name | DH1: Item TDS Percentage | DI1: Item TDS Amount | DJ1: Item TDS Section Code | DK1: Item TDS Section | DL1: GST Identification Number (GSTIN) | DM1: Nature Of Collection | DN1: Project ID | DO1: Project Name | DP1: HSN/SAC | DQ1: Round Off | DR1: Sales person | DS1: Subject | DT1: Primary Contact EmailID | DU1: Primary Contact Mobile | DV1: Primary Contact Phone | DW1: Estimate Number | DX1: Item Type | DY1: Custom Charges | DZ1: Shipping Bill# | EA1: Shipping Bill Date | EB1: Shipping Bill Total | EC1: PortCode | ED1: Reference Invoice# | EE1: Reference Invoice Date | EF1: Reference Invoice Type | EG1: GST Registration Number(Reference Invoice) | EH1: Reason for issuing Debit Note | EI1: E-Commerce Operator Name | EJ1: E-Commerce Operator GSTIN | EK1: Account | EL1: Account Code | EM1: Supply Type | EN1: Tax ID | EO1: Item Tax | EP1: Item Tax % | EQ1: Item Tax Amount | ER1: Item Tax Type | ES1: Item Tax Exemption Reason | ET1: Kit Combo Item Name
A2: 45748 | B2: 2297152000000050064 | C2: INV-25-26-000001 | D2: Closed | E2: 2297152000000050001 | F2: Touchstone Partners | G2: DL | H2: 07-Delhi | I2: business_none | J2: false | K2: 45748 | M2: INR | N2: 1 | O2: item_level | P2: true | Q2: Tax Invoice | R2: 0.00 | U2: entity_level | V2: Technical Fees (2%) | W2: 2.00 | X2: 194J | Y2: Section 194 J | Z2: 1200.000 | AA2: 60000 | AB2: =69600 | AC2: 0 | AD2: 0 | AE2: Adjustment | AG2: 45749 | AH2: 0 | AI2: Due On Receipt | AJ2: Thanks for your business. | AT2: Invoice | AU2: 0.0 | AV2: 0 | BD2: Jurisphere Enterprise Subscription | BE2: License Period- 1st Apr to 30th June25 Description- 10 licenses for 3 months, at Rs. 2000 each month per license | BF2: 3 | BG2: 0.00 | BH2: 0.00 | BI2: 60000 | BJ2: pcs | BK2: 20000 | BL2: 2297152000000039748 | BR2: 2nd Floor, Block E, The MIRA Plot 1 & 2, | BS2: Ishwar Nagar, Mathura Road, | BT2: New Delhi | BU2: Delhi | BV2: India | BW2: 110065 | CA2: 2nd Floor, Block E, The MIRA Plot 1 & 2, | CB2: Ishwar Nagar, Mathura Road, | CC2: New Delhi | CD2: Delhi | CE2: India | CF2: 110065 | CI2: Coresphere100 Technologies Pvt. Ltd. | CJ2: 09AALCC7037K1Z7 | CK2: 16026, 16th Floor, Tower Oakwood, | CL2: Greater Noida, | CM2: Uttar Pradesh | CN2: India | CO2: 201306 | CP2: 8928163657 | CQ2: manas@jurisphere.ai | CR2: 0.00 | CS2: 0.00 | CT2: 18.00 | CU2: 0.00 | CV2: 0.00 | CW2: 0.00 | CX2: 10800.00 | CY2: 0.00 | CZ2: 0.00 | DA2: 0.00 | DB2: 10800.00 | DC2: 0.00 | DP2: 998313 | DQ2: 0 | DX2: service | EH2: Others | EK2: Sales | EM2: Taxable | EN2: 2297152000000031111 | EO2: IGST18 | EP2: 18.00 | EQ2: 10800 | ER2: ItemAmount
A3: 45748 | B3: 2297152000000050138 | C3: INV-25-26-000002 | D3: Closed | E3: 2297152000000050113 | F3: Bimal Rajasekhar | G3: MH | H3: 27-Maharashtra | I3: business_none | J3: false | K3: 45748 | M3: INR | N3: 1 | O3: item_level | P3: true | Q3: Tax Invoice | R3: 0.00 | U3: item_level | W3: 0.00 | Z3: 0.000 | AA3: 30000 | AB3: 35400 | AC3: 0 | AD3: 0 | AE3: Adjustment | AG3: 45749 | AH3: 0 | AI3: Due On Receipt | AJ3: Thanks for your business. | AK3: 1. FLEXIBLE CANCELLATION, WITH PRO-RATED REFUND 2. ALL UPCOMING FEATURES WILL BE INCLUDED IN THE SUBSCRIPTION | AT3: Invoice | AU3: 0.0 | AV3: 0 | BD3: Jurisphere Enterprise Subscription | BE3: Period - 1st Apr 25 to 31st May 25 Description- Pilot Access of 5 licenses for 2 months of Rs.15000 per month | BF3: 2 | BG3: 0.00 | BH3: 0.00 | BI3: 30000 | BJ3: pcs | BK3: 15000 | BL3: 2297152000000039748 | CI3: Coresphere100 Technologies Pvt. Ltd. | CJ3: 09AALCC7037K1Z7 | CK3: 16026, 16th Floor, Tower Oakwood, | CL3: Greater Noida, | CM3: Uttar Pradesh | CN3: India | CO3: 201306 | CP3: 8928163657 | CQ3: manas@jurisphere.ai | CR3: 0.00 | CS3: 0.00 | CT3: 18.00 | CU3: 0.00 | CV3: 0.00 | CW3: 0.00 | CX3: 5400.00 | CY3: 0.00 | CZ3: 0.00 | DA3: 0.00 | DB3: 5400.00 | DC3: 0.00 | DI3: 0.000 | DP3: 998313 | DQ3: 0 | DX3: service | EH3: Others | EK3: Sales | EM3: Taxable | EN3: 2297152000000031111 | EO3: IGST18 | EP3: 18.00 | EQ3: 5400 | ER3: ItemAmount
A4: 45749 | B4: 2297152000000050202 | C4: INV-25-26-000003 | D4: Closed | E4: 2297152000000050184 | F4: Veritas Legal Advocates and Solicitors | G4: MH | H4: 27-Maharashtra | I4: business_registered_composition | J4: false | K4: 45749 | M4: INR | N4: 1 | O4: item_level | P4: true | Q4: Tax Invoice | R4: 0.00 | U4: entity_level | V4: Technical Fees (2%) | W4: 2.00 | X4: 194J | Y4: Section 194 J | Z4: 19872.000 | AA4: 993600 | AB4: 1152576 | AC4: 0 | AD4: 0 | AE4: Adjustment | AG4: 45762 | AH4: 0 | AI4: Due On Receipt | AJ4: Thanks for your business. | AT4: Invoice | AU4: 0.0 | AV4: 0 | BD4: Jurisphere Enterprise Subscription | BE4: Duration - 6 months Subscriptions Description- 46 licenses of Rs. 4000 per month per license | BF4: 46 | BG4: 10.00 | BH4: 110400.000 | BI4: 993600 | BJ4: pcs | BK4: 24000 | BL4: 2297152000000039748 | BQ4: Tushar Raut | BR4: 1st Floor, Veritas Legal, Forbes Building, | BS4: Charanjit Rai Marg, Azad Maidan, Fort, | BT4: Mumbai | BU4: Maharashtra | BV4: India | BW4: 400001 | BX4: +91-22-43686700 | BZ4: Tushar Raut | CA4: 1st Floor, Veritas Legal, Forbes Building, | CB4: Charanjit Rai Marg, Azad Maidan, Fort, | CC4: Mumbai | CD4: Maharashtra | CE4: India | CF4: 400001 | CH4: +91-22-43686700 | CI4: Coresphere100 Technologies Pvt. Ltd. | CJ4: 09AALCC7037K1Z7 | CK4: 16026, 16th Floor, Tower Oakwood, | CL4: Greater Noida, | CM4: Uttar Pradesh | CN4: India | CO4: 201306 | CP4: 8928163657 | CQ4: manas@jurisphere.ai | CR4: 0.00 | CS4: 0.00 | CT4: 18.00 | CU4: 0.00 | CV4: 0.00 | CW4: 0.00 | CX4: 178848.00 | CY4: 0.00 | CZ4: 0.00 | DA4: 0.00 | DB4: 178848.00 | DC4: 0.00 | DL4: 27AANFV0524F1Z7 | DP4: 998313 | DQ4: 0 | DT4: tushar.raut@veritaslegal.in | DV4: +91-22-43686700 | DX4: service | EH4: Others | EK4: Sales | EM4: Taxable | EN4: 2297152000000031111 | EO4: IGST18 | EP4: 18.00 | EQ4: 178848 | ER4: ItemAmount
A5: 45749 | B5: 2297152000000051047 | C5: INV-25-26-000004 | D5: Closed | E5: 2297152000000051029 | F5: LEGALOGIC CONSULTING LLP | G5: MH | H5: 27-Maharashtra | I5: business_gst | J5: false | K5: 45749 | M5: INR | N5: 1 | O5: item_level | P5: true | Q5: Tax Invoice | R5: 0.00 | U5: entity_level | V5: Professional Fees | W5: 10.00 | X5: 194J | Y5: Section 194 J | Z5: 3000.000 | AA5: 30000 | AB5: 32400 | AC5: 0 | AD5: 0 | AE5: Adjustment | AG5: 45752 | AH5: 0 | AI5: Due On Receipt | AJ5: Thanks for your business. | AT5: Invoice | AU5: 0.0 | AV5: 0 | BD5: Jurisphere Enterprise Subscription | BE5: Subscription Period : monthly invoice 01 April 2025 to 30 June, 2025 Unlimited Access- Enterprise Tool (for 15 users) | BF5: 1 | BG5: 0.00 | BH5: 0.00 | BI5: 30000 | BJ5: pcs | BK5: 30000 | BL5: 2297152000000039748 | BR5: Unit No.3A, PV House, FP No. 85, | BS5: T.P. Scheme No. 1 55, Damle Road, Erandwane | BT5: Pune | BU5: Maharashtra | BV5: India | BW5: 411004 | CA5: Unit No.3A, PV House, FP No. 85, | CB5: T.P. Scheme No. 1 55, Damle Road, Erandwane | CC5: Pune | CD5: Maharashtra | CE5: India | CF5: 411004 | CI5: Coresphere100 Technologies Pvt. Ltd. | CJ5: 09AALCC7037K1Z7 | CK5: 16026, 16th Floor, Tower Oakwood, | CL5: Greater Noida, | CM5: Uttar Pradesh | CN5: India | CO5: 201306 | CP5: 8928163657 | CQ5: manas@jurisphere.ai | CR5: 0.00 | CS5: 0.00 | CT5: 18.00 | CU5: 0.00 | CV5: 0.00 | CW5: 0.00 | CX5: 5400.00 | CY5: 0.00 | CZ5: 0.00 | DA5: 0.00 | DB5: 5400.00 | DC5: 0.00 | DL5: 27AAFFL6917J1ZZ | DP5: 998313 | DQ5: 0 | DX5: service | EH5: Others | EK5: Sales | EM5: Taxable | EN5: 2297152000000031111 | EO5: IGST18 | EP5: 18.00 | EQ5: 5400 | ER5: ItemAmount
A6: 45750 | B6: 2297152000000051071 | C6: INV-25-26-000005 | D6: Overdue | E6: 2297152000000051011 | F6: VACUITAS COUNSELLOR LLP | G6: WB | H6: 19-West Bengal | I6: business_gst | J6: false | K6: 45750 | M6: INR | N6: 1 | O6: item_level | P6: true | Q6: Tax Invoice | R6: 0.00 | U6: item_level | W6: 0.00 | Z6: 0.000 | AA6: 99000 | AB6: 116820 | AC6: 116820 | AD6: 0 | AE6: Adjustment | AH6: 0 | AI6: Due On Receipt | AJ6: Thanks for your business. | AT6: Invoice | AU6: 0.0 | AV6: 0 | BD6: Jurisphere Enterprise Subscription | BE6: Subscription Period- 1 year Description- Unlimited Tool for 2 logins | BF6: 2 | BG6: 0.00 | BH6: 0.00 | BI6: 99000 | BJ6: pcs | BK6: 49500 | BL6: 2297152000000039748 | BR6: 6, Brabourne Road, | BT6: Kolkata | BU6: West Bengal | BV6: India | BW6: 700001 | CA6: 6, Brabourne Road, | CC6: Kolkata | CD6: West Bengal | CE6: India | CF6: 700001 | CI6: Coresphere100 Technologies Pvt. Ltd. | CJ6: 09AALCC7037K1Z7 | CK6: 16026, 16th Floor, Tower Oakwood, | CL6: Greater Noida, | CM6: Uttar Pradesh | CN6: India | CO6: 201306 | CP6: 8928163657 | CQ6: manas@jurisphere.ai | CR6: 0.00 | CS6: 0.00 | CT6: 18.00 | CU6: 0.00 | CV6: 0.00 | CW6: 0.00 | CX6: 17820.00 | CY6: 0.00 | CZ6: 0.00 | DA6: 0.00 | DB6: 17820.00 | DC6: 0.00 | DI6: 0.000 | DL6: 19AAVFV8769L1ZO | DP6: 998313 | DQ6: 0 | DX6: service | EH6: Others | EK6: Sales | EM6: Taxable | EN6: 2297152000000031111 | EO6: IGST18 | EP6: 18.00 | EQ6: 17820 | ER6: ItemAmount
A7: 45752 | B7: 2297152000000053035 | C7: INV-25-26-000006 | D7: Closed | E7: 2297152000000053017 | F7: Tvashta Law | G7: DL | H7: 07-Delhi | I7: business_none | J7: false | K7: 45752 | M7: INR | N7: 1 | O7: item_level | P7: true | Q7: Tax Invoice | R7: 0.00 | U7: item_level | W7: 0.00 | Z7: 0.000 | AA7: 2000 | AB7: 2360 | AC7: 0 | AD7: 0 | AE7: Adjustment | AG7: 45752 | AH7: 0 | AI7: Due On Receipt | AJ7: Thanks for your business. | AT7: Invoice | AU7: 0.0 | AV7: 0 | BD7: Jurisphere Enterprise Subscription | BE7: Description - 10 credits for MCA of INR 200/credit | BF7: 10 | BG7: 0.00 | BH7: 0.00 | BI7: 2000 | BJ7: pcs | BK7: 200 | BL7: 2297152000000039748 | BR7: C 36 Lower Ground Floor, | BS7: Mayfair Gardens, | BT7: New Delhi | BU7: Delhi | BV7: India | BW7: 110019 | CA7: C 36 Lower Ground Floor, | CB7: Mayfair Gardens, | CC7: New Delhi | CD7: Delhi | CE7: India | CF7: 110019 | CI7: Coresphere100 Technologies Pvt. Ltd. | CJ7: 09AALCC7037K1Z7 | CK7: 16026, 16th Floor, Tower Oakwood, | CL7: Greater Noida, | CM7: Uttar Pradesh | CN7: India | CO7: 201306 | CP7: 8928163657 | CQ7: manas@jurisphere.ai | CR7: 0.00 | CS7: 0.00 | CT7: 18.00 | CU7: 0.00 | CV7: 0.00 | CW7: 0.00 | CX7: 360.00 | CY7: 0.00 | CZ7: 0.00 | DA7: 0.00 | DB7: 360.00 | DC7: 0.00 | DI7: 0.000 | DP7: 998313 | DQ7: 0 | DX7: service | EH7: Others | EK7: Sales | EM7: Taxable | EN7: 2297152000000031111 | EO7: IGST18 | EP7: 18.00 | EQ7: 360 | ER7: ItemAmount
A8: 45754 | B8: 2297152000000054231 | C8: INV-25-26-000007 | D8: Closed | E8: 2297152000000054193 | F8: U. S. GANDHI & CO. | G8: MH | H8: 27-Maharashtra | I8: business_gst | J8: false | K8: 45754 | M8: INR | N8: 1 | O8: item_level | P8: true | Q8: Tax Invoice | R8: 0.00 | U8: item_level | W8: 0.00 | Z8: 0.000 | AA8: 8000 | AB8: 9440 | AC8: 0 | AD8: 0 | AE8: Adjustment | AG8: 45754 | AH8: 0 | AI8: Due On Receipt | AJ8: Thanks for your business. | AT8: Invoice | AU8: 0.0 | AV8: 0 | BD8: Jurisphere Enterprise Subscription | BE8: Description - Unlimited usage of 1 license for 2 months for Rs.4000/month | BF8: 1 | BG8: 0.00 | BH8: 0.00 | BI8: 8000 | BJ8: pcs | BK8: 8000 | BL8: 2297152000000039748 | BR8: 2ND FLOOR, 114, SUNDERVILLA, SV ROAD, | BS8: NEXT TO VIJAY SALES, SANTACRUZ WEST, Mumbai Suburban, | BT8: Mumbai | BU8: Maharashtra | BV8: India | BW8: 400054 | CA8: 2ND FLOOR, 114, SUNDERVILLA, SV ROAD, | CB8: NEXT TO VIJAY SALES, SANTACRUZ WEST, Mumbai Suburban, | CC8: Mumbai | CD8: Maharashtra | CE8: India | CF8: 400054 | CI8: Coresphere100 Technologies Pvt. Ltd. | CJ8: 09AALCC7037K1Z7 | CK8: 16026, 16th Floor, Tower Oakwood, | CL8: Greater Noida, | CM8: Uttar Pradesh | CN8: India | CO8: 201306 | CP8: 8928163657 | CQ8: manas@jurisphere.ai | CR8: 0.00 | CS8: 0.00 | CT8: 18.00 | CU8: 0.00 | CV8: 0.00 | CW8: 0.00 | CX8: 1440.00 | CY8: 0.00 | CZ8: 0.00 | DA8: 0.00 | DB8: 1440.00 | DC8: 0.00 | DI8: 0.000 | DL8: 27AACFU5143J1Z1 | DP8: 998313 | DQ8: 0 | DX8: service | EH8: Others | EK8: Sales | EM8: Taxable | EN8: 2297152000000031111 | EO8: IGST18 | EP8: 18.00 | EQ8: 1440 | ER8: ItemAmount
A9: 45754 | B9: 2297152000000054324 | C9: INV-25-26-000008 | D9: Closed | E9: 2297152000000061001 | F9: B2C | G9: UP | H9: 09-Uttar Pradesh | I9: business_none | J9: false | K9: 45754 | M9: INR | N9: 1 | O9: item_level | P9: true | Q9: Tax Invoice | R9: 0.00 | U9: item_level | W9: 0.00 | Z9: 0.000 | AA9: 12277.12 | AB9: 14487 | AC9: 0 | AD9: 0 | AE9: Adjustment | AG9: 45754 | AH9: 0 | AI9: Due On Receipt | AJ9: Thanks for your business. | AT9: Invoice | AU9: 0.0 | AV9: 0 | BD9: Jurisphere Enterprise Subscription | BE9: Razorpay B2C sales from 1st Apr to 7th Apr 25 | BF9: 1 | BG9: 0.00 | BH9: 0.00 | BI9: 12277.12 | BJ9: pcs | BK9: 12277.12 | BL9: 2297152000000039748 | CI9: Coresphere100 Technologies Pvt. Ltd. | CJ9: 09AALCC7037K1Z7 | CK9: 16026, 16th Floor, Tower Oakwood, | CL9: Greater Noida, | CM9: Uttar Pradesh | CN9: India | CO9: 201306 | CP9: 8928163657 | CQ9: manas@jurisphere.ai | CR9: 9.00 | CS9: 9.00 | CT9: 0.00 | CU9: 0.00 | CV9: 1104.94 | CW9: 1104.94 | CX9: 0.00 | CY9: 0.00 | CZ9: 1104.94 | DA9: 1104.94 | DB9: 0.00 | DC9: 0.00 | DI9: 0.000 | DP9: 998313 | DQ9: 0 | DX9: service | EH9: Others | EK9: Sales | EM9: Taxable | EN9: 2297152000000031213 | EO9: GST18 | EP9: 18.00 | EQ9: 2209.88 | ER9: Tax Group
A10: 45754 | B10: 2297152000000054375 | C10: INV-25-26-000009 | D10: Closed | E10: 2297152000000054306 | F10: Advocate Rohit Jaiswal | G10: UP | H10: 09-Uttar Pradesh | I10: business_none | J10: false | K10: 45754 | M10: INR | N10: 1 | O10: item_level | P10: true | Q10: Tax Invoice | R10: 0.00 | U10: item_level | W10: 0.00 | Z10: 0.000 | AA10: 5000 | AB10: 5900 | AC10: 0 | AD10: 0 | AE10: Adjustment | AG10: 45754 | AH10: 0 | AI10: Due On Receipt | AJ10: Thanks for your business. | AT10: Invoice | AU10: 0.0 | AV10: 0 | BD10: Jurisphere Enterprise Subscription | BE10: Subscription- Monthly for the period started from April 15, 2025 to April 14, 2026 Description- 1 License for INR 5000 | BF10: 1 | BG10: 0.00 | BH10: 0.000 | BI10: 5000 | BJ10: pcs | BK10: 5000 | BL10: 2297152000000039748 | BP10: Advocate Rohit Jaiswal | BT10: Lucknow | BU10: Uttar Pradesh | BV10: India | CC10: Lucknow | CD10: Uttar Pradesh | CE10: India | CI10: Coresphere100 Technologies Pvt. Ltd. | CJ10: 09AALCC7037K1Z7 | CK10: 16026, 16th Floor, Tower Oakwood, | CL10: Greater Noida, | CM10: Uttar Pradesh | CN10: India | CO10: 201306 | CP10: 8928163657 | CQ10: manas@jurisphere.ai | CR10: 9.00 | CS10: 9.00 | CT10: 0.00 | CU10: 0.00 | CV10: 450.00 | CW10: 450.00 | CX10: 0.00 | CY10: 0.00 | CZ10: 450.00 | DA10: 450.00 | DB10: 0.00 | DC10: 0.00 | DI10: 0.000 | DP10: 998313 | DQ10: 0 | DX10: service | EH10: Others | EK10: Sales | EM10: Taxable | EN10: 2297152000000031213 | EO10: GST18 | EP10: 18.00 | EQ10: 900 | ER10: Tax Group
A11: 45755 | B11: 2297152000000054400 | C11: INV-25-26-000010 | D11: Overdue | E11: 2297152000000054432 | F11: Dileep Poolakkot | G11: DL | H11: 07-Delhi | I11: business_none | J11: false | K11: 45755 | M11: INR | N11: 1 | O11: item_level | P11: true | Q11: Tax Invoice | R11: 0.00 | U11: item_level | W11: 0.00 | Z11: 0.000 | AA11: 60004 | AB11: 70804.72 | AC11: 4.72 | AD11: 0 | AE11: Adjustment | AG11: 45756 | AH11: 0 | AI11: Due On Receipt | AJ11: Thanks for your business. | AT11: Invoice | AU11: 0.0 | AV11: 0 | BD11: Jurisphere Enterprise Subscription | BE11: Subscription- Annual Subscription from 8th April 2025 Description- 1 License for INR 60000 | BF11: 1 | BG11: 14.28 | BH11: 9996.000 | BI11: 60004 | BJ11: pcs | BK11: 70000 | BL11: 2297152000000039748 | BP11: Advocate Rohit Jaiswal | BR11: 251, Tower-5, | BS11: Supreme Enclave, Mayur Vihar-1, | BT11: Delhi | BU11: Delhi | BV11: India | BW11: 110091 | CA11: 251, Tower-5, | CB11: Supreme Enclave, Mayur Vihar-1, | CC11: Delhi | CD11: Delhi | CE11: India | CF11: 110091 | CI11: Coresphere100 Technologies Pvt. Ltd. | CJ11: 09AALCC7037K1Z7 | CK11: 16026, 16th Floor, Tower Oakwood, | CL11: Greater Noida, | CM11: Uttar Pradesh | CN11: India | CO11: 201306 | CP11: 8928163657 | CQ11: manas@jurisphere.ai | CR11: 0.00 | CS11: 0.00 | CT11: 18.00 | CU11: 0.00 | CV11: 0.00 | CW11: 0.00 | CX11: 10800.72 | CY11: 0.00 | CZ11: 0.00 | DA11: 0.00 | DB11: 10800.72 | DC11: 0.00 | DI11: 0.000 | DP11: 998313 | DQ11: 0 | DX11: service | EH11: Others | EK11: Sales | EM11: Taxable | EN11: 2297152000000031111 | EO11: IGST18 | EP11: 18.00 | EQ11: 10800.72 | ER11: ItemAmount
A12: 45755 | B12: 2297152000000054492 | C12: INV-25-26-000011 | D12: Closed | E12: 2297152000000054474 | F12: Utkarsh Joshi | G12: DL | H12: 07-Delhi | I12: business_none | J12: false | K12: 45755 | M12: INR | N12: 1 | O12: item_level | P12: true | Q12: Tax Invoice | R12: 0.00 | U12: item_level | W12: 0.00 | Z12: 0.000 | AA12: 6000 | AB12: 7080 | AC12: 0 | AD12: 0 | AE12: Adjustment | AG12: 45755 | AH12: 0 | AI12: Due On Receipt | AJ12: Thanks for your business. | AT12: Invoice | AU12: 0.0 | AV12: 0 | BD12: Jurisphere Enterprise Subscription | BE12: Subscription- 2 Months Contract Description- 1 License for INR 3000/month. Customer may opt-out out of the contract with a pro-rata refund at anytime during the duration of the contract. | BF12: 1 | BG12: 0.00 | BH12: 0.00 | BI12: 6000 | BJ12: pcs | BK12: 6000 | BL12: 2297152000000039748 | BR12: Ground Floor, S-456, | BS12: GK 2, | BT12: Delhi | BU12: Delhi | BV12: India | BW12: 110048 | CA12: Ground Floor, S-456, | CB12: GK 2, | CC12: Delhi | CD12: Delhi | CE12: India | CF12: 110048 | CI12: Coresphere100 Technologies Pvt. Ltd. | CJ12: 09AALCC7037K1Z7 | CK12: 16026, 16th Floor, Tower Oakwood, | CL12: Greater Noida, | CM12: Uttar Pradesh | CN12: India | CO12: 201306 | CP12: 8928163657 | CQ12: manas@jurisphere.ai | CR12: 0.00 | CS12: 0.00 | CT12: 18.00 | CU12: 0.00 | CV12: 0.00 | CW12: 0.00 | CX12: 1080.00 | CY12: 0.00 | CZ12: 0.00 | DA12: 0.00 | DB12: 1080.00 | DC12: 0.00 | DI12: 0.000 | DP12: 998313 | DQ12: 0 | DX12: service | EH12: Others | EK12: Sales | EM12: Taxable | EN12: 2297152000000031111 | EO12: IGST18 | EP12: 18.00 | EQ12: 1080 | ER12: ItemAmount
A13: 45755 | B13: 2297152000000054539 | C13: INV-25-26-000012 | D13: Closed | E13: 2297152000000054510 | F13: Karan Butalia | G13: DL | H13: 07-Delhi | I13: business_gst | J13: false | K13: 45755 | M13: INR | N13: 1 | O13: item_level | P13: true | Q13: Tax Invoice | R13: 0.00 | U13: item_level | W13: 0.00 | Z13: 0.000 | AA13: 4000 | AB13: 4720 | AC13: 0 | AD13: 0 | AE13: Adjustment | AG13: 45755 | AH13: 0 | AI13: Due On Receipt | AJ13: Thanks for your business. | AT13: Invoice | AU13: 0.0 | AV13: 0 | BD13: Jurisphere Enterprise Subscription | BE13: Subscription Period- 2 months Description- 1 login of INR 4000 for 2 months, Only for document Review and Research | BF13: 1 | BG13: 0.00 | BH13: 0.00 | BI13: 4000 | BJ13: pcs | BK13: 4000 | BL13: 2297152000000039748 | BR13: 75, Qutab View Apartments, | BS13: Katwaria Sarai, | BT13: New Delhi | BU13: Delhi | BV13: India | BW13: 110016 | CA13: 75, Qutab View Apartments, | CB13: Katwaria Sarai, | CC13: New Delhi | CD13: Delhi | CE13: India | CF13: 110016 | CI13: Coresphere100 Technologies Pvt. Ltd. | CJ13: 09AALCC7037K1Z7 | CK13: 16026, 16th Floor, Tower Oakwood, | CL13: Greater Noida, | CM13: Uttar Pradesh | CN13: India | CO13: 201306 | CP13: 8928163657 | CQ13: manas@jurisphere.ai | CR13: 0.00 | CS13: 0.00 | CT13: 18.00 | CU13: 0.00 | CV13: 0.00 | CW13: 0.00 | CX13: 720.00 | CY13: 0.00 | CZ13: 0.00 | DA13: 0.00 | DB13: 720.00 | DC13: 0.00 | DI13: 0.000 | DL13: 07AEGPB1913B1ZC | DP13: 998313 | DQ13: 0 | DX13: service | EH13: Others | EK13: Sales | EM13: Taxable | EN13: 2297152000000031111 | EO13: IGST18 | EP13: 18.00 | EQ13: 720 | ER13: ItemAmount
A14: 45755 | B14: 2297152000000054571 | C14: INV-25-26-000013 | D14: Overdue | E14: 2297152000000054553 | F14: Agama Law Associates | G14: MH | H14: 27-Maharashtra | I14: business_none | J14: false | K14: 45755 | M14: INR | N14: 1 | O14: item_level | P14: true | Q14: Tax Invoice | R14: 0.00 | U14: entity_level | V14: Technical Fees (2%) | W14: 2.00 | X14: 194J | Y14: Section 194 J | Z14: 1355.940 | AA14: 67797 | AB14: 78644.06 | AC14: 1356.06 | AD14: -0.46 | AE14: Adjustment | AG14: 45757 | AH14: 0 | AI14: Due On Receipt | AJ14: Thanks for your business. | AT14: Invoice | AU14: 0.0 | AV14: 0 | BD14: Jurisphere Enterprise Subscription | BE14: Subscription Period- 1st April, 2025 to 30th June, 2025 | BF14: 1 | BG14: 0.00 | BH14: 0.00 | BI14: 67797 | BJ14: pcs | BK14: 67797 | BL14: 2297152000000039748 | BQ14: Nitin Jain | BR14: 13th Floor Oppt, MTNL Office, Lodha Supremus, | BS14: 1301, Saki Vihar Rd, Tunga Village, Chandivali, Powai, | BT14: Mumbai | BU14: Maharashtra | BV14: India | BW14: 400072 | BZ14: Nitin Jain | CA14: 13th Floor Oppt, MTNL Office, Lodha Supremus, | CB14: 1301, Saki Vihar Rd, Tunga Village, Chandivali, Powai, | CC14: Mumbai | CD14: Maharashtra | CE14: India | CF14: 400072 | CI14: Coresphere100 Technologies Pvt. Ltd. | CJ14: 09AALCC7037K1Z7 | CK14: 16026, 16th Floor, Tower Oakwood, | CL14: Greater Noida, | CM14: Uttar Pradesh | CN14: India | CO14: 201306 | CP14: 8928163657 | CQ14: manas@jurisphere.ai | CR14: 0.00 | CS14: 0.00 | CT14: 18.00 | CU14: 0.00 | CV14: 0.00 | CW14: 0.00 | CX14: 12203.46 | CY14: 0.00 | CZ14: 0.00 | DA14: 0.00 | DB14: 12203.46 | DC14: 0.00 | DP14: 998313 | DQ14: 0 | DT14: nitin@agamalaw.com | DU14: 7506122343 | DV14: 022-40229129 | DX14: service | EH14: Others | EK14: Sales | EM14: Taxable | EN14: 2297152000000031111 | EO14: IGST18 | EP14: 18.00 | EQ14: 12203.46 | ER14: ItemAmount
A15: 45755 | B15: 2297152000000054775 | C15: INV-25-26-000014 | D15: Closed | E15: 2297152000000054757 | F15: RAJANI ASSOCIATES | G15: MH | H15: 27-Maharashtra | I15: business_gst | J15: false | K15: 45755 | M15: INR | N15: 1 | O15: item_level | P15: true | Q15: Tax Invoice | R15: 0.00 | U15: item_level | W15: 0.00 | Z15: 0.000 | AA15: 21000 | AB15: 24780 | AC15: 0 | AD15: 0 | AE15: Adjustment | AG15: 45757 | AH15: 0 | AI15: Due On Receipt | AJ15: Thanks for your business. | AT15: Invoice | AU15: 0.0 | AV15: 0 | BD15: Jurisphere Enterprise Subscription | BE15: Subscription Period- 1 month started from 10th April, 2025 to 9th May, 2025 Description - 3 License for Rs. 7000 each for per month | BF15: 3 | BG15: 0.00 | BH15: 0.00 | BI15: 21000 | BJ15: pcs | BK15: 7000 | BL15: 2297152000000039748 | BQ15: RIshi Rajani | BR15: 204-207, Krishna Chambers, | BS15: 59 New Marine Lines, Churchgate, | BT15: Mumbai, | BU15: Maharashtra | BV15: India | BW15: 400020 | BZ15: RIshi Rajani | CA15: 204-207, Krishna Chambers, | CB15: 59 New Marine Lines, Churchgate, | CC15: Mumbai, | CD15: Maharashtra | CE15: India | CF15: 400020 | CI15: Coresphere100 Technologies Pvt. Ltd. | CJ15: 09AALCC7037K1Z7 | CK15: 16026, 16th Floor, Tower Oakwood, | CL15: Greater Noida, | CM15: Uttar Pradesh | CN15: India | CO15: 201306 | CP15: 8928163657 | CQ15: manas@jurisphere.ai | CR15: 0.00 | CS15: 0.00 | CT15: 18.00 | CU15: 0.00 | CV15: 0.00 | CW15: 0.00 | CX15: 3780.00 | CY15: 0.00 | CZ15: 0.00 | DA15: 0.00 | DB15: 3780.00 | DC15: 0.00 | DI15: 0.000 | DL15: 27AANFR0363C1ZC | DP15: 998313 | DQ15: 0 | DT15: rishi@rajaniassociates.net | DX15: service | EH15: Others | EK15: Sales | EM15: Taxable | EN15: 2297152000000031111 | EO15: IGST18 | EP15: 18.00 | EQ15: 3780 | ER15: ItemAmount
A16: 45756 | B16: 2297152000000060019 | C16: INV-25-26-000015 | D16: Closed | E16: 2297152000000060001 | F16: Venkatesh Dhond | G16: UP | H16: 09-Uttar Pradesh | I16: business_none | J16: false | K16: 45756 | M16: INR | N16: 1 | O16: item_level | P16: true | Q16: Tax Invoice | R16: 0.00 | U16: item_level | W16: 0.00 | Z16: 0.000 | AA16: 85500 | AB16: 100890 | AC16: 0 | AD16: 0 | AE16: Adjustment | AG16: 45762 | AH16: 0 | AI16: Due On Receipt | AJ16: Thanks for your business. | AT16: Invoice | AU16: 0.0 | AV16: 0 | BD16: Jurisphere Enterprise Subscription | BE16: Subscription Period- 28 February , 2025 to 27 August, 2025 | BF16: 1 | BG16: 5.00 | BH16: 4500.000 | BI16: 85500 | BJ16: pcs | BK16: 90000 | BL16: 2297152000000039748 | CI16: Coresphere100 Technologies Pvt. Ltd. | CJ16: 09AALCC7037K1Z7 | CK16: 16026, 16th Floor, Tower Oakwood, | CL16: Greater Noida, | CM16: Uttar Pradesh | CN16: India | CO16: 201306 | CP16: 8928163657 | CQ16: manas@jurisphere.ai | CR16: 9.00 | CS16: 9.00 | CT16: 0.00 | CU16: 0.00 | CV16: 7695.00 | CW16: 7695.00 | CX16: 0.00 | CY16: 0.00 | CZ16: 7695.00 | DA16: 7695.00 | DB16: 0.00 | DC16: 0.00 | DI16: 0.000 | DP16: 998313 | DQ16: 0 | DX16: service | EH16: Others | EK16: Sales | EM16: Taxable | EN16: 2297152000000031213 | EO16: GST18 | EP16: 18.00 | EQ16: 15390 | ER16: Tax Group
A17: 45756 | B17: 2297152000000060073 | C17: INV-25-26-000016 | D17: Closed | E17: 2297152000000060055 | F17: Harshit Malik | G17: DL | H17: 07-Delhi | I17: business_none | J17: false | K17: 45756 | M17: INR | N17: 1 | O17: item_level | P17: true | Q17: Tax Invoice | R17: 0.00 | U17: item_level | W17: 0.00 | Z17: 0.000 | AA17: 10000 | AB17: 11800 | AC17: 0 | AD17: 0 | AE17: Adjustment | AG17: 45757 | AH17: 0 | AI17: Due On Receipt | AJ17: Thanks for your business. | AT17: Invoice | AU17: 0.0 | AV17: 0 | BD17: Jurisphere Enterprise Subscription | BE17: Subscription Period- Apr 25 Monthly Subscription started from 9th Mar 2025 to 9th Mar 2026 Description - Monthly payment cycle | BF17: 1 | BG17: 0.00 | BH17: 0.00 | BI17: 10000 | BJ17: pcs | BK17: 10000 | BL17: 2297152000000039748 | BU17: Delhi | CD17: Delhi | CI17: Coresphere100 Technologies Pvt. Ltd. | CJ17: 09AALCC7037K1Z7 | CK17: 16026, 16th Floor, Tower Oakwood, | CL17: Greater Noida, | CM17: Uttar Pradesh | CN17: India | CO17: 201306 | CP17: 8928163657 | CQ17: manas@jurisphere.ai | CR17: 0.00 | CS17: 0.00 | CT17: 18.00 | CU17: 0.00 | CV17: 0.00 | CW17: 0.00 | CX17: 1800.00 | CY17: 0.00 | CZ17: 0.00 | DA17: 0.00 | DB17: 1800.00 | DC17: 0.00 | DI17: 0.000 | DP17: 998313 | DQ17: 0 | DX17: service | EH17: Others | EK17: Sales | EM17: Taxable | EN17: 2297152000000031111 | EO17: IGST18 | EP17: 18.00 | EQ17: 1800 | ER17: ItemAmount
A18: 45757 | B18: 2297152000000061097 | C18: INV-25-26-000017 | D18: Closed | E18: 2297152000000061081 | F18: PSN Legal Advocates and Legal Consultants | G18: MH | H18: 27-Maharashtra | I18: business_none | J18: false | K18: 45757 | M18: INR | N18: 1 | O18: item_level | P18: true | Q18: Tax Invoice | R18: 0.00 | U18: item_level | W18: 0.00 | Z18: 0.000 | AA18: 150012 | AB18: 177014.16 | AC18: 0 | AD18: 0 | AE18: Adjustment | AG18: 45771 | AH18: 0 | AI18: Due On Receipt | AJ18: Thanks for your business. | AT18: Invoice | AU18: 0.0 | AV18: 0 | BD18: Jurisphere Enterprise Subscription | BE18: Subscription Period- Annually Description- 6 licenses with unlimited usage (litigation) | BF18: 1 | BG18: 16.66 | BH18: 29988.000 | BI18: 150012 | BJ18: pcs | BK18: 180000 | BL18: 2297152000000039748 | BR18: A-3701, 37th Floor, Marathon Futurex, | BS18: Mafatlal Mill Compound, N M Joshi Marg, Lower Parel, | BT18: Mumbai | BU18: Maharashtra | BV18: India | BW18: 400013 | CA18: A-3701, 37th Floor, Marathon Futurex, | CB18: Mafatlal Mill Compound, N M Joshi Marg, Lower Parel, | CC18: Mumbai | CD18: Maharashtra | CE18: India | CF18: 400013 | CI18: Coresphere100 Technologies Pvt. Ltd. | CJ18: 09AALCC7037K1Z7 | CK18: 16026, 16th Floor, Tower Oakwood, | CL18: Greater Noida, | CM18: Uttar Pradesh | CN18: India | CO18: 201306 | CP18: 8928163657 | CQ18: manas@jurisphere.ai | CR18: 0.00 | CS18: 0.00 | CT18: 18.00 | CU18: 0.00 | CV18: 0.00 | CW18: 0.00 | CX18: 27002.16 | CY18: 0.00 | CZ18: 0.00 | DA18: 0.00 | DB18: 27002.16 | DC18: 0.00 | DI18: 0.000 | DP18: 998313 | DQ18: 0 | DX18: service | EH18: Others | EK18: Sales | EM18: Taxable | EN18: 2297152000000031111 | EO18: IGST18 | EP18: 18.00 | EQ18: 27002.16 | ER18: ItemAmount
A19: 45757 | B19: 2297152000000066035 | C19: INV-25-26-000019 | D19: Closed | E19: 2297152000000066001 | F19: Swapna Sheshadri | G19: DL | H19: 07-Delhi | I19: business_none | J19: false | K19: 45757 | M19: INR | N19: 1 | O19: item_level | P19: true | Q19: Tax Invoice | R19: 0.00 | U19: item_level | W19: 0.00 | Z19: 0.000 | AA19: 10000 | AB19: 11800 | AC19: 0 | AD19: 0 | AE19: Adjustment | AG19: 45757 | AH19: 0 | AI19: Due On Receipt | AJ19: Thanks for your business. | AT19: Invoice | AU19: 0.0 | AV19: 0 | BD19: Jurisphere Enterprise Subscription | BE19: Subscription Period- 10th Apr 25 to 9th Apr 26 Description- 1 year contract of monthly invoicing for payment of Rs 10,000 | BF19: 1 | BG19: 0.00 | BH19: 0.000 | BI19: 10000 | BJ19: pcs | BK19: 10000 | BL19: 2297152000000039748 | BP19: Swapna Sheshadri | BR19: D-246, Block D, | BS19: Defence Colony, | BT19: New Delhi | BU19: Delhi | BV19: India | BW19: 110024 | CA19: D-246, Block D, | CB19: Defence Colony, | CC19: New Delhi | CD19: Delhi | CE19: India | CF19: 110024 | CI19: Coresphere100 Technologies Pvt. Ltd. | CJ19: 09AALCC7037K1Z7 | CK19: 16026, 16th Floor, Tower Oakwood, | CL19: Greater Noida, | CM19: Uttar Pradesh | CN19: India | CO19: 201306 | CP19: 8928163657 | CQ19: manas@jurisphere.ai | CR19: 0.00 | CS19: 0.00 | CT19: 18.00 | CU19: 0.00 | CV19: 0.00 | CW19: 0.00 | CX19: 1800.00 | CY19: 0.00 | CZ19: 0.00 | DA19: 0.00 | DB19: 1800.00 | DC19: 0.00 | DI19: 0.000 | DP19: 998313 | DQ19: 0 | DX19: service | EH19: Others | EK19: Sales | EM19: Taxable | EN19: 2297152000000031111 | EO19: IGST18 | EP19: 18.00 | EQ19: 1800 | ER19: ItemAmount
A20: 45758 | B20: 2297152000000068017 | C20: INV-25-26-000020 | D20: Closed | E20: 2297152000000068001 | F20: Vutts & Associates LLP | G20: DL | H20: 07-Delhi | I20: business_none | J20: false | K20: 45758 | M20: INR | N20: 1 | O20: item_level | P20: true | Q20: Tax Invoice | R20: 0.00 | U20: entity_level | V20: Technical Fees (2%) | W20: 2.00 | X20: 194J | Y20: Section 194 J | Z20: 600.000 | AA20: 30000 | AB20: 34800 | AC20: 0 | AD20: 0 | AE20: Adjustment | AG20: 45764 | AH20: 0 | AI20: Due On Receipt | AJ20: Thanks for your business. | AT20: Invoice | AU20: 0.0 | AV20: 0 | BD20: Jurisphere Enterprise Subscription | BE20: Subscription Period- 2 months Description- Pilot Project for 2 months of Rs. 15000/month, unlimited usage | BF20: 1 | BG20: 0.00 | BH20: 0.00 | BI20: 30000 | BJ20: pcs | BK20: 30000 | BL20: 2297152000000039748 | BR20: C-5/8, Block C 5, | BS20: Safdarjung Development Area, Hauz Khas | BT20: New Delhi | BU20: Delhi | BV20: India | BW20: 110016 | CA20: C-5/8, Block C 5, | CB20: Safdarjung Development Area, Hauz Khas | CC20: New Delhi | CD20: Delhi | CE20: India | CF20: 110016 | CI20: Coresphere100 Technologies Pvt. Ltd. | CJ20: 09AALCC7037K1Z7 | CK20: 16026, 16th Floor, Tower Oakwood, | CL20: Greater Noida, | CM20: Uttar Pradesh | CN20: India | CO20: 201306 | CP20: 8928163657 | CQ20: manas@jurisphere.ai | CR20: 0.00 | CS20: 0.00 | CT20: 18.00 | CU20: 0.00 | CV20: 0.00 | CW20: 0.00 | CX20: 5400.00 | CY20: 0.00 | CZ20: 0.00 | DA20: 0.00 | DB20: 5400.00 | DC20: 0.00 | DP20: 998313 | DQ20: 0 | DX20: service | EH20: Others | EK20: Sales | EM20: Taxable | EN20: 2297152000000031111 | EO20: IGST18 | EP20: 18.00 | EQ20: 5400 | ER20: ItemAmount
A21: 45758 | B21: 2297152000000068067 | C21: INV-25-26-000021 | D21: Overdue | E21: 2297152000000068029 | F21: Darius J. Khambata | G21: MH | H21: 27-Maharashtra | I21: business_none | J21: false | K21: 45758 | M21: INR | N21: 1 | O21: item_level | P21: true | Q21: Tax Invoice | R21: 0.00 | U21: item_level | W21: 0.00 | Z21: 0.000 | AA21: 16949.15 | AB21: 20000 | AC21: 20000 | AD21: 0 | AE21: Adjustment | AH21: 0 | AI21: Due On Receipt | AJ21: Thanks for your business. | AT21: Invoice | AU21: 0.0 | AV21: 0 | BD21: Jurisphere Enterprise Subscription | BE21: Subscription Period- 07/03/2025 - 06/04/2025 Description- Monthly Invoice for Rs. 20,000 | BF21: 1 | BG21: 0.00 | BH21: 0.000 | BI21: 16949.15 | BJ21: pcs | BK21: 16949.15 | BL21: 2297152000000039748 | BP21: Darius- 07/03/2025 - 06/04/2025 | BR21: Mulla House 3rd floor 51, | BS21: Mahatma Gandhi Road, Fort, Near Central Bank | BT21: Mumbai | BU21: Maharashtra | BV21: India | BW21: 400001 | CA21: Mulla House 3rd floor 51, | CB21: Mahatma Gandhi Road, Fort, | CC21: Mumbai | CD21: Maharashtra | CE21: India | CF21: 400001 | CI21: Coresphere100 Technologies Pvt. Ltd. | CJ21: 09AALCC7037K1Z7 | CK21: 16026, 16th Floor, Tower Oakwood, | CL21: Greater Noida, | CM21: Uttar Pradesh | CN21: India | CO21: 201306 | CP21: 8928163657 | CQ21: manas@jurisphere.ai | CR21: 0.00 | CS21: 0.00 | CT21: 18.00 | CU21: 0.00 | CV21: 0.00 | CW21: 0.00 | CX21: 3050.85 | CY21: 0.00 | CZ21: 0.00 | DA21: 0.00 | DB21: 3050.85 | DC21: 0.00 | DI21: 0.000 | DP21: 998313 | DQ21: 0 | DX21: service | EH21: Others | EK21: Sales | EM21: Taxable | EN21: 2297152000000031111 | EO21: IGST18 | EP21: 18.00 | EQ21: 3050.85 | ER21: ItemAmount
A22: 45758 | B22: 2297152000000068112 | C22: INV-25-26-000022 | D22: Overdue | E22: 2297152000000068029 | F22: Darius J. Khambata | G22: MH | H22: 27-Maharashtra | I22: business_none | J22: false | K22: 45758 | M22: INR | N22: 1 | O22: item_level | P22: true | Q22: Tax Invoice | R22: 0.00 | U22: item_level | W22: 0.00 | Z22: 0.000 | AA22: 16949.15 | AB22: 20000 | AC22: 20000 | AD22: 0 | AE22: Adjustment | AH22: 0 | AI22: Due On Receipt | AJ22: Thanks for your business. | AT22: Invoice | AU22: 0.0 | AV22: 0 | BD22: Jurisphere Enterprise Subscription | BE22: Subscription Period- 07/04/2025 - 06/05/2025 Description- Monthly Invoice for Rs. 20,000 | BF22: 1 | BG22: 0.00 | BH22: 0.00 | BI22: 16949.15 | BJ22: pcs | BK22: 16949.15 | BL22: 2297152000000039748 | BP22: Darius- 07/03/2025 - 06/04/2025 | BR22: Mulla House 3rd floor 51, | BS22: Mahatma Gandhi Road, Fort, Near Central Bank | BT22: Mumbai | BU22: Maharashtra | BV22: India | BW22: 400001 | CA22: Mulla House 3rd floor 51, | CB22: Mahatma Gandhi Road, Fort, | CC22: Mumbai | CD22: Maharashtra | CE22: India | CF22: 400001 | CI22: Coresphere100 Technologies Pvt. Ltd. | CJ22: 09AALCC7037K1Z7 | CK22: 16026, 16th Floor, Tower Oakwood, | CL22: Greater Noida, | CM22: Uttar Pradesh | CN22: India | CO22: 201306 | CP22: 8928163657 | CQ22: manas@jurisphere.ai | CR22: 0.00 | CS22: 0.00 | CT22: 18.00 | CU22: 0.00 | CV22: 0.00 | CW22: 0.00 | CX22: 3050.85 | CY22: 0.00 | CZ22: 0.00 | DA22: 0.00 | DB22: 3050.85 | DC22: 0.00 | DI22: 0.000 | DP22: 998313 | DQ22: 0 | DX22: service | EH22: Others | EK22: Sales | EM22: Taxable | EN22: 2297152000000031111 | EO22: IGST18 | EP22: 18.00 | EQ22: 3050.85 | ER22: ItemAmount
A23: 45758 | B23: 2297152000000068144 | C23: INV-25-26-000023 | D23: Closed | E23: 2297152000000068128 | F23: Miglani Varma & Co. | G23: DL | H23: 07-Delhi | I23: business_none | J23: false | K23: 45758 | M23: INR | N23: 1 | O23: item_level | P23: true | Q23: Tax Invoice | R23: 0.00 | U23: item_level | W23: 0.00 | Z23: 0.000 | AA23: 15000 | AB23: 17700 | AC23: 0 | AD23: 0 | AE23: Adjustment | AG23: 45761 | AH23: 0 | AI23: Due On Receipt | AJ23: Thanks for your business. | AT23: Invoice | AU23: 0.0 | AV23: 0 | BD23: Jurisphere Enterprise Subscription | BE23: Subscription Period- 2 months Description- Pilot Project for 2 months, unlimited usage. | BF23: 1 | BG23: 0.00 | BH23: 0.00 | BI23: 15000 | BJ23: pcs | BK23: 15000 | BL23: 2297152000000039748 | BR23: D - 11 (LGF), | BS23: Gulmohar Park, | BT23: New Delhi | BU23: Delhi | BV23: India | BW23: 110049 | CA23: D - 11 (LGF), | CB23: Gulmohar Park, | CC23: New Delhi | CD23: Delhi | CE23: India | CF23: 110049 | CI23: Coresphere100 Technologies Pvt. Ltd. | CJ23: 09AALCC7037K1Z7 | CK23: 16026, 16th Floor, Tower Oakwood, | CL23: Greater Noida, | CM23: Uttar Pradesh | CN23: India | CO23: 201306 | CP23: 8928163657 | CQ23: manas@jurisphere.ai | CR23: 0.00 | CS23: 0.00 | CT23: 18.00 | CU23: 0.00 | CV23: 0.00 | CW23: 0.00 | CX23: 2700.00 | CY23: 0.00 | CZ23: 0.00 | DA23: 0.00 | DB23: 2700.00 | DC23: 0.00 | DI23: 0.000 | DP23: 998313 | DQ23: 0 | DX23: service | EH23: Others | EK23: Sales | EM23: Taxable | EN23: 2297152000000031111 | EO23: IGST18 | EP23: 18.00 | EQ23: 2700 | ER23: ItemAmount
A24: 45759 | B24: 2297152000000068206 | C24: INV-25-26-000024 | D24: Closed | E24: 2297152000000068190 | F24: Venkatesh Mohanraj | G24: TN | H24: 33-Tamil Nadu | I24: business_none | J24: false | K24: 45759 | M24: INR | N24: 1 | O24: item_level | P24: true | Q24: Tax Invoice | R24: 0.00 | U24: item_level | W24: 0.00 | Z24: 0.000 | AA24: 5000 | AB24: 5900 | AC24: 0 | AD24: 0 | AE24: Adjustment | AG24: 45760 | AH24: 0 | AI24: Due On Receipt | AJ24: Thanks for your business. | AT24: Invoice | AU24: 0.0 | AV24: 0 | BD24: Jurisphere Enterprise Subscription | BE24: Subscription Period- 1 month Description- 1 license for 1 month of Rs. 5,000 | BF24: 1 | BG24: 0.00 | BH24: 0.00 | BI24: 5000 | BJ24: pcs | BK24: 5000 | BL24: 2297152000000039748 | BR24: H 6/12, Coastal Road, Aishwarya Apartments, | BS24: Kalashetra Colony, Besant Nagar, | BT24: Chennai | BU24: Tamil Nadu | BV24: India | BW24: 600090 | CA24: H 6/12, Coastal Road, Aishwarya Apartments, | CB24: Kalashetra Colony, Besant Nagar, | CC24: Chennai | CD24: Tamil Nadu | CE24: India | CF24: 600090 | CI24: Coresphere100 Technologies Pvt. Ltd. | CJ24: 09AALCC7037K1Z7 | CK24: 16026, 16th Floor, Tower Oakwood, | CL24: Greater Noida, | CM24: Uttar Pradesh | CN24: India | CO24: 201306 | CP24: 8928163657 | CQ24: manas@jurisphere.ai | CR24: 0.00 | CS24: 0.00 | CT24: 18.00 | CU24: 0.00 | CV24: 0.00 | CW24: 0.00 | CX24: 900.00 | CY24: 0.00 | CZ24: 0.00 | DA24: 0.00 | DB24: 900.00 | DC24: 0.00 | DI24: 0.000 | DP24: 998313 | DQ24: 0 | DX24: service | EH24: Others | EK24: Sales | EM24: Taxable | EN24: 2297152000000031111 | EO24: IGST18 | EP24: 18.00 | EQ24: 900 | ER24: ItemAmount
A25: 45759 | B25: 2297152000000068376 | C25: INV-25-26-000025 | D25: Closed | E25: 2297152000000068360 | F25: Jade Lex Partners | G25: DL | H25: 07-Delhi | I25: business_none | J25: false | K25: 45759 | M25: INR | N25: 1 | O25: item_level | P25: true | Q25: Tax Invoice | R25: 0.00 | U25: item_level | W25: 0.00 | Z25: 0.000 | AA25: 6000 | AB25: 7080 | AC25: 0 | AD25: 0 | AE25: Adjustment | AG25: 45763 | AH25: 0 | AI25: Due On Receipt | AJ25: Thanks for your business. | AT25: Invoice | AU25: 0.0 | AV25: 0 | BD25: Jurisphere Enterprise Subscription | BE25: Subscription Period - 1 month Description - 1 month subscription of Rs. 6000 | BF25: 1 | BG25: 0.00 | BH25: 0.00 | BI25: 6000 | BJ25: pcs | BK25: 6000 | BL25: 2297152000000039748 | BR25: E 378, LGF, | BS25: GK-1, | BT25: New Delhi | BU25: Delhi | BV25: India | BW25: 110048 | CA25: E 378, LGF, | CB25: GK-1, | CC25: New Delhi | CD25: Delhi | CE25: India | CF25: 110048 | CI25: Coresphere100 Technologies Pvt. Ltd. | CJ25: 09AALCC7037K1Z7 | CK25: 16026, 16th Floor, Tower Oakwood, | CL25: Greater Noida, | CM25: Uttar Pradesh | CN25: India | CO25: 201306 | CP25: 8928163657 | CQ25: manas@jurisphere.ai | CR25: 0.00 | CS25: 0.00 | CT25: 18.00 | CU25: 0.00 | CV25: 0.00 | CW25: 0.00 | CX25: 1080.00 | CY25: 0.00 | CZ25: 0.00 | DA25: 0.00 | DB25: 1080.00 | DC25: 0.00 | DI25: 0.000 | DP25: 998313 | DQ25: 0 | DX25: service | EH25: Others | EK25: Sales | EM25: Taxable | EN25: 2297152000000031111 | EO25: IGST18 | EP25: 18.00 | EQ25: 1080 | ER25: ItemAmount
A26: 45759 | B26: 2297152000000068406 | C26: INV-25-26-000026 | D26: Closed | E26: 2297152000000068388 | F26: Alankrit Bajpai | G26: HR | H26: 06-Haryana | I26: business_none | J26: false | K26: 45759 | M26: INR | N26: 1 | O26: item_level | P26: true | Q26: Tax Invoice | R26: 0.00 | U26: item_level | W26: 0.00 | Z26: 0.000 | AA26: 5000 | AB26: 5900 | AC26: 0 | AD26: 0 | AE26: Adjustment | AG26: 45759 | AH26: 0 | AI26: Due On Receipt | AJ26: Thanks for your business. | AT26: Invoice | AU26: 0.0 | AV26: 0 | BD26: Jurisphere Enterprise Subscription | BE26: Subscription Period- 1 month | BF26: 1 | BG26: 0.00 | BH26: 0.00 | BI26: 5000 | BJ26: pcs | BK26: 5000 | BL26: 2297152000000039748 | BR26: C-67/A, Sushant Lok-3, | BS26: Sector 57, | BT26: Gurugram | BU26: Haryana | BV26: India | CA26: C-67/A, Sushant Lok-3, | CB26: Sector 57, | CC26: Gurugram | CD26: Haryana | CE26: India | CI26: Coresphere100 Technologies Pvt. Ltd. | CJ26: 09AALCC7037K1Z7 | CK26: 16026, 16th Floor, Tower Oakwood, | CL26: Greater Noida, | CM26: Uttar Pradesh | CN26: India | CO26: 201306 | CP26: 8928163657 | CQ26: manas@jurisphere.ai | CR26: 0.00 | CS26: 0.00 | CT26: 18.00 | CU26: 0.00 | CV26: 0.00 | CW26: 0.00 | CX26: 900.00 | CY26: 0.00 | CZ26: 0.00 | DA26: 0.00 | DB26: 900.00 | DC26: 0.00 | DI26: 0.000 | DP26: 998313 | DQ26: 0 | DX26: service | EH26: Others | EK26: Sales | EM26: Taxable | EN26: 2297152000000031111 | EO26: IGST18 | EP26: 18.00 | EQ26: 900 | ER26: ItemAmount
A27: 45760 | B27: 2297152000000069079 | C27: INV-25-26-000028 | D27: Overdue | E27: 2297152000000069063 | F27: Badar Durrez | G27: DL | H27: 07-Delhi | I27: business_none | J27: false | K27: 45760 | M27: INR | N27: 1 | O27: item_level | P27: true | Q27: Tax Invoice | R27: 0.00 | U27: item_level | W27: 0.00 | Z27: 0.000 | AA27: 5000 | AB27: 5900 | AC27: 5900 | AD27: 0 | AE27: Adjustment | AH27: 0 | AI27: Due On Receipt | AJ27: Thanks for your business. | AT27: Invoice | AU27: 0.0 | AV27: 0 | BD27: Jurisphere Enterprise Subscription | BE27: Subscription Period- 1 month Description- One month pilot unlimited usage | BF27: 1 | BG27: 0.00 | BH27: 0.00 | BI27: 5000 | BJ27: pcs | BK27: 5000 | BL27: 2297152000000039748 | BU27: Delhi | BV27: India | CD27: Delhi | CE27: India | CI27: Coresphere100 Technologies Pvt. Ltd. | CJ27: 09AALCC7037K1Z7 | CK27: 16026, 16th Floor, Tower Oakwood, | CL27: Greater Noida, | CM27: Uttar Pradesh | CN27: India | CO27: 201306 | CP27: 8928163657 | CQ27: manas@jurisphere.ai | CR27: 0.00 | CS27: 0.00 | CT27: 18.00 | CU27: 0.00 | CV27: 0.00 | CW27: 0.00 | CX27: 900.00 | CY27: 0.00 | CZ27: 0.00 | DA27: 0.00 | DB27: 900.00 | DC27: 0.00 | DI27: 0.000 | DP27: 998313 | DQ27: 0 | DX27: service | EH27: Others | EK27: Sales | EM27: Taxable | EN27: 2297152000000031111 | EO27: IGST18 | EP27: 18.00 | EQ27: 900 | ER27: ItemAmount
A28: 45761 | B28: 2297152000000074017 | C28: INV-25-26-000029 | D28: Closed | E28: 2297152000000074001 | F28: Rashmikant and Partners | G28: MH | H28: 27-Maharashtra | I28: business_none | J28: false | K28: 45761 | M28: INR | N28: 1 | O28: item_level | P28: true | Q28: Tax Invoice | R28: 0.00 | U28: entity_level | V28: Technical Fees (2%) | W28: 2.00 | X28: 194J | Y28: Section 194 J | Z28: 4400.020 | AA28: 220000.96 | AB28: 255201.11 | AC28: 0 | AD28: 0 | AE28: Adjustment | AG28: 45770 | AH28: 0 | AI28: Due On Receipt | AJ28: Thanks for your business. | AT28: Invoice | AU28: 0.0 | AV28: 0 | BD28: Jurisphere Enterprise Subscription | BE28: Subscription Period- Annual Description- Translation- 800 List of Downloads- 120 Redline-20 MCA Downloads- 200 | BF28: 1 | BG28: 37.20 | BH28: 41039.040 | BI28: 69280.96 | BJ28: pcs | BK28: 110320 | BL28: 2297152000000039748 | BR28: 1st Floor, Kalpataru Heritage, 1-1, 127, | BS28: Mahatma Gandhi Road | BT28: Mumbai | BU28: Maharashtra | BV28: India | BW28: 400001 | CA28: 1st Floor, Kalpataru Heritage, 1-1, 127, | CB28: Mahatma Gandhi Road | CC28: Mumbai | CD28: Maharashtra | CE28: India | CF28: 400001 | CI28: Coresphere100 Technologies Pvt. Ltd. | CJ28: 09AALCC7037K1Z7 | CK28: 16026, 16th Floor, Tower Oakwood, | CL28: Greater Noida, | CM28: Uttar Pradesh | CN28: India | CO28: 201306 | CP28: 8928163657 | CQ28: manas@jurisphere.ai | CR28: 0.00 | CS28: 0.00 | CT28: 18.00 | CU28: 0.00 | CV28: 0.00 | CW28: 0.00 | CX28: 12470.57 | CY28: 0.00 | CZ28: 0.00 | DA28: 0.00 | DB28: 12470.57 | DC28: 0.00 | DP28: 998313 | DQ28: 0 | DX28: service | EH28: Others | EK28: Sales | EM28: Taxable | EN28: 2297152000000031111 | EO28: IGST18 | EP28: 18.00 | EQ28: 12470.57 | ER28: ItemAmount
A29: 45762 | B29: 2297152000000074075 | C29: INV-25-26-000030 | D29: Overdue | E29: 2297152000000074043 | F29: Tatva Legal Hyderabad | G29: TS | H29: 36-Telangana | I29: business_registered_composition | J29: false | K29: 45762 | M29: INR | N29: 1 | O29: item_level | P29: true | Q29: Tax Invoice | R29: 0.00 | U29: entity_level | V29: Technical Fees (2%) | W29: 2.00 | X29: 194J | Y29: Section 194 J | Z29: 3000.000 | AA29: 150000 | AB29: 174000 | AC29: 174000 | AD29: 0 | AE29: Adjustment | AH29: 0 | AI29: Due On Receipt | AJ29: Thanks for your business. | AT29: Invoice | AU29: 0.0 | AV29: 0 | BD29: Jurisphere Enterprise Subscription | BE29: Subscription Period- Monthly invoicing for period started from 15th April,2025 Description- Number of Licenses 50 of Rs 150000 | BF29: 1 | BG29: 0.00 | BH29: 0.00 | BI29: 150000 | BJ29: pcs | BK29: 150000 | BL29: 2297152000000039748 | BP29: Tatva Legal Hyderabad- 15th april 2025 | BR29: Plot No.107A, Tatva House, Road No.72, | BS29: Jubilee Hills | BT29: Hyderabad | BU29: Telangana | BV29: India | BW29: 500033 | CA29: Plot No.107A, Tatva House, Road No.72, | CB29: Jubilee Hills | CC29: Hyderabad | CD29: Telangana | CE29: India | CF29: 500033 | CI29: Coresphere100 Technologies Pvt. Ltd. | CJ29: 09AALCC7037K1Z7 | CK29: 16026, 16th Floor, Tower Oakwood, | CL29: Greater Noida, | CM29: Uttar Pradesh | CN29: India | CO29: 201306 | CP29: 8928163657 | CQ29: manas@jurisphere.ai | CR29: 0.00 | CS29: 0.00 | CT29: 18.00 | CU29: 0.00 | CV29: 0.00 | CW29: 0.00 | CX29: 27000.00 | CY29: 0.00 | CZ29: 0.00 | DA29: 0.00 | DB29: 27000.00 | DC29: 0.00 | DL29: 36AAIFT2572Q1ZG | DP29: 998313 | DQ29: 0 | DX29: service | EH29: Others | EK29: Sales | EM29: Taxable | EN29: 2297152000000031111 | EO29: IGST18 | EP29: 18.00 | EQ29: 27000 | ER29: ItemAmount
A30: 45762 | B30: 2297152000000076001 | C30: INV-25-26-000031 | D30: Closed | E30: 2297152000000061001 | F30: B2C | G30: UP | H30: 09-Uttar Pradesh | I30: business_none | J30: false | K30: 45762 | M30: INR | N30: 1 | O30: item_level | P30: true | Q30: Tax Invoice | R30: 0.00 | U30: item_level | W30: 0.00 | Z30: 0.000 | AA30: 4651.7 | AB30: 5489 | AC30: 0 | AD30: 0 | AE30: Adjustment | AG30: 45762 | AH30: 0 | AI30: Due On Receipt | AJ30: Thanks for your business. | AT30: Invoice | AU30: 0.0 | AV30: 0 | BD30: Jurisphere Enterprise Subscription | BE30: Razorpay B2C invoices from 8 Apr to 14 Apr 25 | BF30: 1 | BG30: 0.00 | BH30: 0.000 | BI30: 4651.7 | BJ30: pcs | BK30: 4651.7 | BL30: 2297152000000039748 | BP30: Tatva Legal Hyderabad- 15th april 2025 | CI30: Coresphere100 Technologies Pvt. Ltd. | CJ30: 09AALCC7037K1Z7 | CK30: 16026, 16th Floor, Tower Oakwood, | CL30: Greater Noida, | CM30: Uttar Pradesh | CN30: India | CO30: 201306 | CP30: 8928163657 | CQ30: manas@jurisphere.ai | CR30: 9.00 | CS30: 9.00 | CT30: 0.00 | CU30: 0.00 | CV30: 418.65 | CW30: 418.65 | CX30: 0.00 | CY30: 0.00 | CZ30: 418.65 | DA30: 418.65 | DB30: 0.00 | DC30: 0.00 | DI30: 0.000 | DP30: 998313 | DQ30: 0 | DX30: service | EH30: Others | EK30: Sales | EM30: Taxable | EN30: 2297152000000031213 | EO30: GST18 | EP30: 18.00 | EQ30: 837.3 | ER30: Tax Group
A31: 45762 | B31: 2297152000000077017 | C31: INV-25-26-000032 | D31: Closed | E31: 2297152000000077001 | F31: Shreeyash Lalit | G31: DL | H31: 07-Delhi | I31: business_none | J31: false | K31: 45762 | M31: INR | N31: 1 | O31: item_level | P31: true | Q31: Tax Invoice | R31: 0.00 | U31: item_level | W31: 0.00 | Z31: 0.000 | AA31: 36000 | AB31: 42480 | AC31: 0 | AD31: 0 | AE31: Adjustment | AG31: 45769 | AH31: 0 | AI31: Due On Receipt | AJ31: Thanks for your business. | AT31: Invoice | AU31: 0.0 | AV31: 0 | BD31: Jurisphere Enterprise Subscription | BE31: Subscription Period- 6 months Description- Single license for unlimited usage (litigation) for 6 months. | BF31: 1 | BG31: 40.00 | BH31: 24000.000 | BI31: 36000 | BJ31: pcs | BK31: 60000 | BL31: 2297152000000039748 | BU31: Delhi | BV31: India | CD31: Delhi | CE31: India | CI31: Coresphere100 Technologies Pvt. Ltd. | CJ31: 09AALCC7037K1Z7 | CK31: 16026, 16th Floor, Tower Oakwood, | CL31: Greater Noida, | CM31: Uttar Pradesh | CN31: India | CO31: 201306 | CP31: 8928163657 | CQ31: manas@jurisphere.ai | CR31: 0.00 | CS31: 0.00 | CT31: 18.00 | CU31: 0.00 | CV31: 0.00 | CW31: 0.00 | CX31: 6480.00 | CY31: 0.00 | CZ31: 0.00 | DA31: 0.00 | DB31: 6480.00 | DC31: 0.00 | DI31: 0.000 | DP31: 998313 | DQ31: 0 | DX31: service | EH31: Others | EK31: Sales | EM31: Taxable | EN31: 2297152000000031111 | EO31: IGST18 | EP31: 18.00 | EQ31: 6480 | ER31: ItemAmount
A32: 45762 | B32: 2297152000000077357 | C32: INV-25-26-000033 | D32: Closed | E32: 2297152000000077341 | F32: Dewani Associates | G32: MH | H32: 27-Maharashtra | I32: business_none | J32: false | K32: 45762 | M32: INR | N32: 1 | O32: item_level | P32: true | Q32: Tax Invoice | R32: 0.00 | U32: item_level | W32: 0.00 | Z32: 0.000 | AA32: 20000 | AB32: 23600 | AC32: 0 | AD32: 0 | AE32: Adjustment | AG32: 45762 | AH32: 0 | AI32: Due On Receipt | AJ32: Thanks for your business. | AT32: Invoice | AU32: 0.0 | AV32: 0 | BD32: Jurisphere Enterprise Subscription | BE32: Subscription Period- 2 months Description- Pilot Project for 2 months for unlimited usage for up to 3 users | BF32: 1 | BG32: 0.00 | BH32: 0.00 | BI32: 20000 | BJ32: pcs | BK32: 20000 | BL32: 2297152000000039748 | BR32: 83 - B, Mittal Court Opp Vidhan Bhawan, | BS32: Nariman Point, | BT32: Mumbai | BU32: Maharashtra | BV32: India | BW32: 400021 | CA32: 83 - B, Mittal Court Opp Vidhan Bhawan, | CB32: Nariman Point, | CC32: Mumbai | CD32: Maharashtra | CE32: India | CF32: 400021 | CI32: Coresphere100 Technologies Pvt. Ltd. | CJ32: 09AALCC7037K1Z7 | CK32: 16026, 16th Floor, Tower Oakwood, | CL32: Greater Noida, | CM32: Uttar Pradesh | CN32: India | CO32: 201306 | CP32: 8928163657 | CQ32: manas@jurisphere.ai | CR32: 0.00 | CS32: 0.00 | CT32: 18.00 | CU32: 0.00 | CV32: 0.00 | CW32: 0.00 | CX32: 3600.00 | CY32: 0.00 | CZ32: 0.00 | DA32: 0.00 | DB32: 3600.00 | DC32: 0.00 | DI32: 0.000 | DP32: 998313 | DQ32: 0 | DX32: service | EH32: Others | EK32: Sales | EM32: Taxable | EN32: 2297152000000031111 | EO32: IGST18 | EP32: 18.00 | EQ32: 3600 | ER32: ItemAmount
A33: 45762 | B33: 2297152000000077399 | C33: INV-25-26-000034 | D33: Closed | E33: 2297152000000077369 | F33: R. Vishnu Kumar, Advocate | G33: DL | H33: 07-Delhi | I33: business_none | J33: false | K33: 45762 | M33: INR | N33: 1 | O33: item_level | P33: true | Q33: Tax Invoice | R33: 0.00 | U33: item_level | W33: 0.00 | Z33: 0.000 | AA33: 16950 | AB33: 20000 | AC33: 0 | AD33: -1 | AE33: Adjustment | AG33: 45762 | AH33: 0 | AI33: Due On Receipt | AJ33: Thanks for your business. | AT33: Invoice | AU33: 0.0 | AV33: 0 | BD33: Jurisphere Enterprise Subscription | BE33: Subscription Period- Annual Contract Description- 6 licenses for unlimited usage (litigation) of Rs. 20,000/- per month | BF33: 1 | BG33: 0.00 | BH33: 0.000 | BI33: 16950 | BJ33: pcs | BK33: 16950 | BL33: 2297152000000039748 | BP33: R. Vishnu Kumar, Advocate, | BR33: R Block, 159, Lower Ground Floor, | BS33: Greater Kailash, Part 1, | BT33: New Delhi | BU33: Delhi | BV33: India | BW33: 110048 | CA33: R Block, 159, Lower Ground Floor, | CB33: Greater Kailash, Part 1, | CC33: New Delhi | CD33: Delhi | CE33: India | CF33: 110048 | CI33: Coresphere100 Technologies Pvt. Ltd. | CJ33: 09AALCC7037K1Z7 | CK33: 16026, 16th Floor, Tower Oakwood, | CL33: Greater Noida, | CM33: Uttar Pradesh | CN33: India | CO33: 201306 | CP33: 8928163657 | CQ33: manas@jurisphere.ai | CR33: 0.00 | CS33: 0.00 | CT33: 18.00 | CU33: 0.00 | CV33: 0.00 | CW33: 0.00 | CX33: 3051.00 | CY33: 0.00 | CZ33: 0.00 | DA33: 0.00 | DB33: 3051.00 | DC33: 0.00 | DI33: 0.000 | DP33: 998313 | DQ33: 0 | DX33: service | EH33: Others | EK33: Sales | EM33: Taxable | EN33: 2297152000000031111 | EO33: IGST18 | EP33: 18.00 | EQ33: 3051 | ER33: ItemAmount
A34: 45763 | B34: 2297152000000079651 | C34: INV-25-26-000035 | D34: Closed | E34: 2297152000000079621 | F34: Yash Momaya | G34: MH | H34: 27-Maharashtra | I34: business_none | J34: false | K34: 45763 | M34: INR | N34: 1 | O34: item_level | P34: true | Q34: Tax Invoice | R34: 0.00 | U34: item_level | W34: 0.00 | Z34: 0.000 | AA34: 10000 | AB34: 11800 | AC34: 0 | AD34: 0 | AE34: Adjustment | AG34: 45774 | AH34: 0 | AI34: Due On Receipt | AJ34: Thanks for your business. | AT34: Invoice | AU34: 0.0 | AV34: 0 | BD34: Jurisphere Enterprise Subscription | BE34: Subscription Period- Monthly invoicing for Annual contract Description- Single license for unlimited usage (litigation) | BF34: 1 | BG34: 0.00 | BH34: 0.000 | BI34: 10000 | BJ34: pcs | BK34: 10000 | BL34: 2297152000000039748 | BP34: Yash Momaya | BT34: Mumbai | BV34: India | CC34: Mumbai | CE34: India | CI34: Coresphere100 Technologies Pvt. Ltd. | CJ34: 09AALCC7037K1Z7 | CK34: 16026, 16th Floor, Tower Oakwood, | CL34: Greater Noida, | CM34: Uttar Pradesh | CN34: India | CO34: 201306 | CP34: 8928163657 | CQ34: manas@jurisphere.ai | CR34: 0.00 | CS34: 0.00 | CT34: 18.00 | CU34: 0.00 | CV34: 0.00 | CW34: 0.00 | CX34: 1800.00 | CY34: 0.00 | CZ34: 0.00 | DA34: 0.00 | DB34: 1800.00 | DC34: 0.00 | DI34: 0.000 | DP34: 998313 | DQ34: 0 | DX34: service | EH34: Others | EK34: Sales | EM34: Taxable | EN34: 2297152000000031111 | EO34: IGST18 | EP34: 18.00 | EQ34: 1800 | ER34: ItemAmount
A35: 45763 | B35: 2297152000000079688 | C35: INV-25-26-000036 | D35: Closed | E35: 2297152000000079672 | F35: Chetan Dedhia | G35: MH | H35: 27-Maharashtra | I35: business_none | J35: false | K35: 45763 | M35: INR | N35: 1 | O35: item_level | P35: true | Q35: Tax Invoice | R35: 0.00 | U35: item_level | W35: 0.00 | Z35: 0.000 | AA35: 15000 | AB35: 17700 | AC35: 0 | AD35: 0 | AE35: Adjustment | AG35: 45763 | AH35: 0 | AI35: Due On Receipt | AJ35: Thanks for your business. | AT35: Invoice | AU35: 0.0 | AV35: 0 | BD35: Jurisphere Enterprise Subscription | BE35: Subscription Period- 1 month Description- 1 month access of 4 licenses for unlimited usage (litigation) | BF35: 1 | BG35: 0.00 | BH35: 0.00 | BI35: 15000 | BJ35: pcs | BK35: 15000 | BL35: 2297152000000039748 | BT35: Mumbai | BU35: Maharashtra | BV35: India | CC35: Mumbai | CD35: Maharashtra | CE35: India | CI35: Coresphere100 Technologies Pvt. Ltd. | CJ35: 09AALCC7037K1Z7 | CK35: 16026, 16th Floor, Tower Oakwood, | CL35: Greater Noida, | CM35: Uttar Pradesh | CN35: India | CO35: 201306 | CP35: 8928163657 | CQ35: manas@jurisphere.ai | CR35: 0.00 | CS35: 0.00 | CT35: 18.00 | CU35: 0.00 | CV35: 0.00 | CW35: 0.00 | CX35: 2700.00 | CY35: 0.00 | CZ35: 0.00 | DA35: 0.00 | DB35: 2700.00 | DC35: 0.00 | DI35: 0.000 | DP35: 998313 | DQ35: 0 | DX35: service | EH35: Others | EK35: Sales | EM35: Taxable | EN35: 2297152000000031111 | EO35: IGST18 | EP35: 18.00 | EQ35: 2700 | ER35: ItemAmount
A36: 45763 | B36: 2297152000000079806 | C36: INV-25-26-000037 | D36: Closed | E36: 2297152000000079790 | F36: NC Legal | G36: DL | H36: 07-Delhi | I36: business_none | J36: false | K36: 45763 | M36: INR | N36: 1 | O36: item_level | P36: true | Q36: Tax Invoice | R36: 0.00 | U36: item_level | W36: 0.00 | Z36: 0.000 | AA36: 68000 | AB36: 80240 | AC36: 0 | AD36: 0 | AE36: Adjustment | AG36: 45764 | AH36: 0 | AI36: Due On Receipt | AJ36: Thanks for your business. | AT36: Invoice | AU36: 0.0 | AV36: 0 | BD36: Jurisphere Enterprise Subscription | BE36: Subscription Period- from 1st May 25 to 30th Apr 26 Description- One license for one year with Unlimited tool- No MCA No Doc Table. | BF36: 1 | BG36: 0.00 | BH36: 0.00 | BI36: 68000 | BJ36: pcs | BK36: 68000 | BL36: 2297152000000039748 | BR36: B-22, Ground Floor, | BS36: Jungpura Extension, | BT36: New Delhi | BU36: Delhi | BV36: India | BW36: 110014 | CA36: B-22, Ground Floor, | CB36: Jungpura Extension, | CC36: New Delhi | CD36: Delhi | CE36: India | CF36: 110014 | CI36: Coresphere100 Technologies Pvt. Ltd. | CJ36: 09AALCC7037K1Z7 | CK36: 16026, 16th Floor, Tower Oakwood, | CL36: Greater Noida, | CM36: Uttar Pradesh | CN36: India | CO36: 201306 | CP36: 8928163657 | CQ36: manas@jurisphere.ai | CR36: 0.00 | CS36: 0.00 | CT36: 18.00 | CU36: 0.00 | CV36: 0.00 | CW36: 0.00 | CX36: 12240.00 | CY36: 0.00 | CZ36: 0.00 | DA36: 0.00 | DB36: 12240.00 | DC36: 0.00 | DI36: 0.000 | DP36: 998313 | DQ36: 0 | DT36: admin@nclegal.co | DX36: service | EH36: Others | EK36: Sales | EM36: Taxable | EN36: 2297152000000031111 | EO36: IGST18 | EP36: 18.00 | EQ36: 12240 | ER36: ItemAmount
A37: 45765 | B37: 2297152000000087017 | C37: INV-25-26-000038 | D37: Closed | E37: 2297152000000087001 | F37: Aakash Sharma | G37: UP | H37: 09-Uttar Pradesh | I37: business_none | J37: false | K37: 45765 | M37: INR | N37: 1 | O37: item_level | P37: true | Q37: Tax Invoice | R37: 0.00 | U37: item_level | W37: 0.00 | Z37: 0.000 | AA37: 5000 | AB37: 5900 | AC37: 0 | AD37: 0 | AE37: Adjustment | AG37: 45765 | AH37: 0 | AI37: Due On Receipt | AJ37: Thanks for your business. | AT37: Invoice | AU37: 0.0 | AV37: 0 | BD37: Jurisphere Enterprise Subscription | BE37: Subscription Period- 1 month Description- 1 month access for 1 licens for unlimited usage for Research, DocReview, Translation and List of Dates | BF37: 1 | BG37: 0.00 | BH37: 0.00 | BI37: 5000 | BJ37: pcs | BK37: 5000 | BL37: 2297152000000039748 | BR37: VR Legal Advocates and Consultants to be precise | BT37: Allahabad | BU37: Uttar Pradesh | BV37: India | CA37: VR Legal Advocates and Consultants to be precise | CC37: Allahabad | CD37: Uttar Pradesh | CE37: India | CI37: Coresphere100 Technologies Pvt. Ltd. | CJ37: 09AALCC7037K1Z7 | CK37: 16026, 16th Floor, Tower Oakwood, | CL37: Greater Noida, | CM37: Uttar Pradesh | CN37: India | CO37: 201306 | CP37: 8928163657 | CQ37: manas@jurisphere.ai | CR37: 9.00 | CS37: 9.00 | CT37: 0.00 | CU37: 0.00 | CV37: 450.00 | CW37: 450.00 | CX37: 0.00 | CY37: 0.00 | CZ37: 450.00 | DA37: 450.00 | DB37: 0.00 | DC37: 0.00 | DI37: 0.000 | DP37: 998313 | DQ37: 0 | DX37: service | EH37: Others | EK37: Sales | EM37: Taxable | EN37: 2297152000000031213 | EO37: GST18 | EP37: 18.00 | EQ37: 900 | ER37: Tax Group
A38: 45768 | B38: 2297152000000096021 | C38: INV-25-26-000039 | D38: Closed | E38: 2297152000000096003 | F38: SAGA LEGAL | G38: DL | H38: 07-Delhi | I38: business_gst | J38: false | K38: 45768 | M38: INR | N38: 1 | O38: item_level | P38: true | Q38: Tax Invoice | R38: 0.00 | U38: item_level | W38: 0.00 | Z38: 0.000 | AA38: 20000 | AB38: 23600 | AC38: 0 | AD38: 0 | AE38: Adjustment | AG38: 45768 | AH38: 0 | AI38: Due On Receipt | AJ38: Thanks for your business. | AT38: Invoice | AU38: 0.0 | AV38: 0 | BD38: Jurisphere Enterprise Subscription | BE38: Subscription Period- Start from 14 April to 14 May 25 Description- 15 license trial for Unlimited Doc Review, Research, Translation, LOD for Doc table 200 Cells | BF38: 1 | BG38: 0.00 | BH38: 0.00 | BI38: 20000 | BJ38: pcs | BK38: 20000 | BL38: 2297152000000039748 | BR38: 03rd Floor, 248, | BS38: Okhla Industrial Area, Phase -3, | BT38: New Delhi | BU38: Delhi | BV38: India | BW38: 110020 | CA38: 03rd Floor, 248, | CB38: Okhla Industrial Area, Phase -3, | CC38: New Delhi | CD38: Delhi | CE38: India | CF38: 110020 | CI38: Coresphere100 Technologies Pvt. Ltd. | CJ38: 09AALCC7037K1Z7 | CK38: 16026, 16th Floor, Tower Oakwood, | CL38: Greater Noida, | CM38: Uttar Pradesh | CN38: India | CO38: 201306 | CP38: 8928163657 | CQ38: manas@jurisphere.ai | CR38: 0.00 | CS38: 0.00 | CT38: 18.00 | CU38: 0.00 | CV38: 0.00 | CW38: 0.00 | CX38: 3600.00 | CY38: 0.00 | CZ38: 0.00 | DA38: 0.00 | DB38: 3600.00 | DC38: 0.00 | DI38: 0.000 | DL38: 07AFCFS2249L1ZQ | DP38: 998313 | DQ38: 0 | DX38: service | EH38: Others | EK38: Sales | EM38: Taxable | EN38: 2297152000000031111 | EO38: IGST18 | EP38: 18.00 | EQ38: 3600 | ER38: ItemAmount
A39: 45769 | B39: 2297152000000099973 | C39: INV-25-26-000040 | D39: Closed | E39: 2297152000000099957 | F39: RPV LEGAL | G39: DL | H39: 07-Delhi | I39: business_none | J39: false | K39: 45769 | M39: INR | N39: 1 | O39: item_level | P39: true | Q39: Tax Invoice | R39: 0.00 | U39: entity_level | V39: Technical Fees (2%) | W39: 2.00 | X39: 194J | Y39: Section 194 J | Z39: 2966.100 | AA39: 148305 | AB39: 172034 | AC39: 0 | AD39: 0.2 | AE39: Adjustment | AG39: 45778 | AH39: 0 | AI39: Due On Receipt | AJ39: Thanks for your business. | AT39: Invoice | AU39: 0.0 | AV39: 0 | BD39: Jurisphere Enterprise Subscription | BE39: Subscription Period- 22 Apr 2025 to 21 Apr 2026 Description- Annual payment for 6 licenses of Litigation | BF39: 1 | BG39: 0.00 | BH39: 0.00 | BI39: 148305 | BJ39: pcs | BK39: 148305 | BL39: 2297152000000039748 | BR39: D-19, 2ND FLOOR, GEETANJALI ENCLAVE, | BS39: MALVIYA NAGAR, | BT39: New Delhi | BU39: Delhi | BV39: India | BW39: 110017 | CA39: D-19, 2ND FLOOR, GEETANJALI ENCLAVE, | CB39: MALVIYA NAGAR, | CC39: New Delhi | CD39: Delhi | CE39: India | CF39: 110017 | CI39: Coresphere100 Technologies Pvt. Ltd. | CJ39: 09AALCC7037K1Z7 | CK39: 16026, 16th Floor, Tower Oakwood, | CL39: Greater Noida, | CM39: Uttar Pradesh | CN39: India | CO39: 201306 | CP39: 8928163657 | CQ39: manas@jurisphere.ai | CR39: 0.00 | CS39: 0.00 | CT39: 18.00 | CU39: 0.00 | CV39: 0.00 | CW39: 0.00 | CX39: 26694.90 | CY39: 0.00 | CZ39: 0.00 | DA39: 0.00 | DB39: 26694.90 | DC39: 0.00 | DP39: 998313 | DQ39: 0 | DX39: service | EH39: Others | EK39: Sales | EM39: Taxable | EN39: 2297152000000031111 | EO39: IGST18 | EP39: 18.00 | EQ39: 26694.9 | ER39: ItemAmount
A40: 45770 | B40: 2297152000000107021 | C40: INV-25-26-000041 | D40: Overdue | E40: 2297152000000107003 | F40: AP & Partners, Advocates | G40: DL | H40: 07-Delhi | I40: business_gst | J40: false | K40: 45770 | M40: INR | N40: 1 | O40: item_level | P40: true | Q40: Tax Invoice | R40: 0.00 | U40: item_level | W40: 0.00 | Z40: 0.000 | AA40: 24000 | AB40: 28320 | AC40: 28320 | AD40: 0 | AE40: Adjustment | AH40: 0 | AI40: Due On Receipt | AJ40: Thanks for your business. | AT40: Invoice | AU40: 0.0 | AV40: 0 | BD40: Jurisphere Enterprise Subscription | BE40: Subscription Period- 90 days from 24 Apr to 22 July 25 Description- The 90-day pilot run. This pilot includes unlimited access to the following features: Document Review List of Dates Legal Research Redline Analysis Translation | BF40: 1 | BG40: 0.00 | BH40: 0.00 | BI40: 24000 | BJ40: pcs | BK40: 24000 | BL40: 2297152000000039748 | BR40: B-62, Paschimi Marg, | BS40: Vasant Vihar, | BT40: New Delhi | BU40: Delhi | BV40: India | BW40: 110057 | CA40: B-62, Paschimi Marg, | CB40: Vasant Vihar, | CC40: New Delhi | CD40: Delhi | CE40: India | CF40: 110057 | CI40: Coresphere100 Technologies Pvt. Ltd. | CJ40: 09AALCC7037K1Z7 | CK40: 16026, 16th Floor, Tower Oakwood, | CL40: Greater Noida, | CM40: Uttar Pradesh | CN40: India | CO40: 201306 | CP40: 8928163657 | CQ40: manas@jurisphere.ai | CR40: 0.00 | CS40: 0.00 | CT40: 18.00 | CU40: 0.00 | CV40: 0.00 | CW40: 0.00 | CX40: 4320.00 | CY40: 0.00 | CZ40: 0.00 | DA40: 0.00 | DB40: 4320.00 | DC40: 0.00 | DI40: 0.000 | DL40: 07ABPFA8851M1ZP | DP40: 998313 | DQ40: 0 | DX40: service | EH40: Others | EK40: Sales | EM40: Taxable | EN40: 2297152000000031111 | EO40: IGST18 | EP40: 18.00 | EQ40: 4320 | ER40: ItemAmount
A41: 45770 | B41: 2297152000000107049 | C41: INV-25-26-000042 | D41: Closed | E41: 2297152000000107033 | F41: Pranay Chitale | G41: DL | H41: 07-Delhi | I41: business_none | J41: false | K41: 45770 | M41: INR | N41: 1 | O41: item_level | P41: true | Q41: Tax Invoice | R41: 0.00 | U41: item_level | W41: 0.00 | Z41: 0.000 | AA41: 15000 | AB41: 17700 | AC41: 0 | AD41: 0 | AE41: Adjustment | AG41: 45774 | AH41: 0 | AI41: Due On Receipt | AJ41: Thanks for your business. | AT41: Invoice | AU41: 0.0 | AV41: 0 | BD41: Jurisphere Enterprise Subscription | BE41: Subscription Period- Monthly Invoicing for the period from 23 Apr 25 to 22 Apr 26 Description- Monthly subscription of 5 licenses for unlimited usage (litigation) | BF41: 1 | BG41: 0.00 | BH41: 0.00 | BI41: 15000 | BJ41: pcs | BK41: 15000 | BL41: 2297152000000039748 | BR41: B-111, Lower Ground Floor, | BS41: Neeti Bagh, August Kranti Marg, | BT41: New Delhi | BU41: Delhi | BV41: India | BW41: 110049 | CA41: B-111, Lower Ground Floor, | CB41: Neeti Bagh, August Kranti Marg, | CC41: New Delhi | CD41: Delhi | CE41: India | CF41: 110049 | CI41: Coresphere100 Technologies Pvt. Ltd. | CJ41: 09AALCC7037K1Z7 | CK41: 16026, 16th Floor, Tower Oakwood, | CL41: Greater Noida, | CM41: Uttar Pradesh | CN41: India | CO41: 201306 | CP41: 8928163657 | CQ41: manas@jurisphere.ai | CR41: 0.00 | CS41: 0.00 | CT41: 18.00 | CU41: 0.00 | CV41: 0.00 | CW41: 0.00 | CX41: 2700.00 | CY41: 0.00 | CZ41: 0.00 | DA41: 0.00 | DB41: 2700.00 | DC41: 0.00 | DI41: 0.000 | DP41: 998313 | DQ41: 0 | DT41: pranaychitale@cvassociates.in | DX41: service | EH41: Others | EK41: Sales | EM41: Taxable | EN41: 2297152000000031111 | EO41: IGST18 | EP41: 18.00 | EQ41: 2700 | ER41: ItemAmount
A42: 45771 | B42: 2297152000000107135 | C42: INV-25-26-000043 | D42: Overdue | E42: 2297152000000107067 | F42: Spark Legal | G42: MH | H42: 27-Maharashtra | I42: business_none | J42: false | K42: 45771 | M42: INR | N42: 1 | O42: item_level | P42: true | Q42: Tax Invoice | R42: 0.00 | U42: item_level | W42: 0.00 | Z42: 0.000 | AA42: 10000 | AB42: 11800 | AC42: 11800 | AD42: 0 | AE42: Adjustment | AH42: 0 | AI42: Due On Receipt | AJ42: Thanks for your business. | AT42: Invoice | AU42: 0.0 | AV42: 0 | BD42: Jurisphere Enterprise Subscription | BE42: Subscription Period- 1 month Subscription started from 24-4-2025 Description- 3 licenses for 1 month | BF42: 1 | BG42: 0.00 | BH42: 0.00 | BI42: 10000 | BJ42: pcs | BK42: 10000 | BL42: 2297152000000039748 | BR42: WeWork C – 20, G Block, Bandra Kurla Complex, | BS42: Bandra East, | BT42: Mumbai | BU42: Maharashtra | BV42: India | BW42: 400051 | CA42: WeWork C – 20, G Block, Bandra Kurla Complex, | CB42: Bandra East, | CC42: Mumbai | CD42: Maharashtra | CE42: India | CF42: 400051 | CI42: Coresphere100 Technologies Pvt. Ltd. | CJ42: 09AALCC7037K1Z7 | CK42: 16026, 16th Floor, Tower Oakwood, | CL42: Greater Noida, | CM42: Uttar Pradesh | CN42: India | CO42: 201306 | CP42: 8928163657 | CQ42: manas@jurisphere.ai | CR42: 0.00 | CS42: 0.00 | CT42: 18.00 | CU42: 0.00 | CV42: 0.00 | CW42: 0.00 | CX42: 1800.00 | CY42: 0.00 | CZ42: 0.00 | DA42: 0.00 | DB42: 1800.00 | DC42: 0.00 | DI42: 0.000 | DP42: 998313 | DQ42: 0 | DX42: service | EH42: Others | EK42: Sales | EM42: Taxable | EN42: 2297152000000031111 | EO42: IGST18 | EP42: 18.00 | EQ42: 1800 | ER42: ItemAmount
A43: 45771 | B43: 2297152000000111017 | C43: INV-25-26-000044 | D43: Overdue | E43: 2297152000000111001 | F43: Bathiya Legal | G43: MH | H43: 27-Maharashtra | I43: business_none | J43: false | K43: 45771 | M43: INR | N43: 1 | O43: item_level | P43: true | Q43: Tax Invoice | R43: 0.00 | U43: item_level | W43: 0.00 | Z43: 0.000 | AA43: 30000 | AB43: 35400 | AC43: 35400 | AD43: 0 | AE43: Adjustment | AH43: 0 | AI43: Due on Receipt | AJ43: Thanks for your business. | AT43: Invoice | AU43: 0.0 | AV43: 0 | BD43: Jurisphere Enterprise Subscription | BE43: Subscription Period- 3 month contract Description- 5 Logins for Unlimited research, Docreview, translation, redline analysis, list of dates. 1000 DocTable Cells, 10 MCA downloads | BF43: 1 | BG43: 0.00 | BH43: 0.00 | BI43: 30000 | BJ43: pcs | BK43: 30000 | BL43: 2297152000000039748 | BR43: 909, Solaris One, Professor NS Phadke Rd, | BS43: Vijay Nagar, Andheri East, | BT43: Mumbai | BU43: Maharashtra | BV43: India | BW43: 400069 | CA43: 909, Solaris One, Professor NS Phadke Rd, | CB43: Vijay Nagar, Andheri East, | CC43: Mumbai | CD43: Maharashtra | CE43: India | CF43: 400069 | CI43: Coresphere100 Technologies Pvt. Ltd. | CJ43: 09AALCC7037K1Z7 | CK43: 16026, 16th Floor, Tower Oakwood, | CL43: Greater Noida, | CM43: Uttar Pradesh | CN43: India | CO43: 201306 | CP43: 8928163657 | CQ43: manas@jurisphere.ai | CR43: 0.00 | CS43: 0.00 | CT43: 18.00 | CU43: 0.00 | CV43: 0.00 | CW43: 0.00 | CX43: 5400.00 | CY43: 0.00 | CZ43: 0.00 | DA43: 0.00 | DB43: 5400.00 | DC43: 0.00 | DI43: 0.000 | DP43: 998313 | DQ43: 0 | DX43: service | EH43: Others | EK43: Sales | EM43: Taxable | EN43: 2297152000000031111 | EO43: IGST18 | EP43: 18.00 | EQ43: 5400 | ER43: ItemAmount
A44: 45771 | B44: 2297152000000111045 | C44: INV-25-26-000045 | D44: Closed | E44: 2297152000000100673 | F44: Justice (Retd.) Kurian Joseph | G44: DL | H44: 07-Delhi | I44: business_none | J44: false | K44: 45771 | M44: INR | N44: 1 | O44: item_level | P44: true | Q44: Tax Invoice | R44: 0.00 | U44: item_level | W44: 0.00 | Z44: 0.000 | AA44: 150000 | AB44: 177000 | AC44: 0 | AD44: 0 | AE44: Adjustment | AG44: 45776 | AH44: 0 | AI44: Due on Receipt | AJ44: Thanks for your business. | AT44: Invoice | AU44: 0.0 | AV44: 0 | BD44: Jurisphere Enterprise Subscription | BE44: Subscription Period- Annual Subscription Started from 27th Apr 2025 to 26th Apr 2026 Description- chamber subscription for unlimited usage (litigation) | BF44: 1 | BG44: 50.00 | BH44: 150000.000 | BI44: 150000 | BJ44: pcs | BK44: 300000 | BL44: 2297152000000039748 | BR44: 50, Poorvi Marg, | BS44: Vasant Vihar, | BT44: New Delhi | BU44: Delhi | BV44: India | BW44: 110057 | CA44: 50, Poorvi Marg, | CB44: Vasant Vihar, | CC44: New Delhi | CD44: Delhi | CE44: India | CF44: 110057 | CI44: Coresphere100 Technologies Pvt. Ltd. | CJ44: 09AALCC7037K1Z7 | CK44: 16026, 16th Floor, Tower Oakwood, | CL44: Greater Noida, | CM44: Uttar Pradesh | CN44: India | CO44: 201306 | CP44: 8928163657 | CQ44: manas@jurisphere.ai | CR44: 0.00 | CS44: 0.00 | CT44: 18.00 | CU44: 0.00 | CV44: 0.00 | CW44: 0.00 | CX44: 27000.00 | CY44: 0.00 | CZ44: 0.00 | DA44: 0.00 | DB44: 27000.00 | DC44: 0.00 | DI44: 0.000 | DP44: 998313 | DQ44: 0 | DX44: service | EH44: Others | EK44: Sales | EM44: Taxable | EN44: 2297152000000031111 | EO44: IGST18 | EP44: 18.00 | EQ44: 27000 | ER44: ItemAmount
A45: 45771 | B45: 2297152000000112017 | C45: INV-25-26-000046 | D45: Closed | E45: 2297152000000112001 | F45: SINHA & COMPANY | G45: WB | H45: 19-West Bengal | I45: business_none | J45: false | K45: 45771 | M45: INR | N45: 1 | O45: item_level | P45: true | Q45: Tax Invoice | R45: 0.00 | U45: entity_level | V45: Technical Fees (2%) | W45: 2.00 | X45: 194J | Y45: Section 194 J | Z45: 3456.000 | AA45: 172800 | AB45: 200448 | AC45: 0 | AD45: 0 | AE45: Adjustment | AG45: 45777 | AH45: 0 | AI45: Due on Receipt | AJ45: Thanks for your business. | AT45: Invoice | AU45: 0.0 | AV45: 0 | BD45: Jurisphere Enterprise Subscription | BE45: Contract Period- Annual Subscription from 25-4-2025 to 24-4-2026 Description- The pricing includes unlimited access to Document Review, Legal Research, Translation, Redlines, File Library, and List of Dates of 5 License. | BF45: 1 | BG45: 0.00 | BH45: 0.00 | BI45: 172800 | BJ45: pcs | BK45: 172800 | BL45: 2297152000000039748 | BR45: 5, KIRAN SHANKAR ROY ROAD, | BS45: 1ST FLOOR, | BT45: KOLKATA | BU45: West Bengal | BV45: India | BW45: 700001 | CA45: 5, KIRAN SHANKAR ROY ROAD, | CB45: 1ST FLOOR, | CC45: KOLKATA | CD45: West Bengal | CE45: India | CF45: 700001 | CI45: Coresphere100 Technologies Pvt. Ltd. | CJ45: 09AALCC7037K1Z7 | CK45: 16026, 16th Floor, Tower Oakwood, | CL45: Greater Noida, | CM45: Uttar Pradesh | CN45: India | CO45: 201306 | CP45: 8928163657 | CQ45: manas@jurisphere.ai | CR45: 0.00 | CS45: 0.00 | CT45: 18.00 | CU45: 0.00 | CV45: 0.00 | CW45: 0.00 | CX45: 31104.00 | CY45: 0.00 | CZ45: 0.00 | DA45: 0.00 | DB45: 31104.00 | DC45: 0.00 | DP45: 998313 | DQ45: 0 | DX45: service | EH45: Others | EK45: Sales | EM45: Taxable | EN45: 2297152000000031111 | EO45: IGST18 | EP45: 18.00 | EQ45: 31104 | ER45: ItemAmount
A46: 45772 | B46: 2297152000000115623 | C46: INV-25-26-000047 | D46: Closed | E46: 2297152000000115449 | F46: Darshit Jain | G46: MH | H46: 27-Maharashtra | I46: business_none | J46: false | K46: 45772 | M46: INR | N46: 1 | O46: item_level | P46: true | Q46: Tax Invoice | R46: 0.00 | U46: item_level | W46: 0.00 | Z46: 0.000 | AA46: 21600 | AB46: 25488 | AC46: 0 | AD46: 0 | AE46: Adjustment | AG46: 45772 | AH46: 0 | AI46: Due on Receipt | AJ46: Thanks for your business. | AT46: Invoice | AU46: 0.0 | AV46: 0 | BD46: Jurisphere Enterprise Subscription | BE46: Subscription Period- Annual Subscription started from 25th Apr 25 to 24th Apr 26 Description- Single license for unlimited usage (litigation) | BF46: 1 | BG46: 0.00 | BH46: 0.00 | BI46: 21600 | BJ46: pcs | BK46: 21600 | BL46: 2297152000000039748 | BT46: Mumbai | BU46: Maharashtra | BV46: India | CC46: Mumbai | CD46: Maharashtra | CE46: India | CI46: Coresphere100 Technologies Pvt. Ltd. | CJ46: 09AALCC7037K1Z7 | CK46: 16026, 16th Floor, Tower Oakwood, | CL46: Greater Noida, | CM46: Uttar Pradesh | CN46: India | CO46: 201306 | CP46: 8928163657 | CQ46: manas@jurisphere.ai | CR46: 0.00 | CS46: 0.00 | CT46: 18.00 | CU46: 0.00 | CV46: 0.00 | CW46: 0.00 | CX46: 3888.00 | CY46: 0.00 | CZ46: 0.00 | DA46: 0.00 | DB46: 3888.00 | DC46: 0.00 | DI46: 0.000 | DP46: 998313 | DQ46: 0 | DX46: service | EH46: Others | EK46: Sales | EM46: Taxable | EN46: 2297152000000031111 | EO46: IGST18 | EP46: 18.00 | EQ46: 3888 | ER46: ItemAmount
A47: 45772 | B47: 2297152000000115635 | C47: INV-25-26-000048 | D47: Closed | E47: 2297152000000115465 | F47: Sagar Ghogre | G47: MH | H47: 27-Maharashtra | I47: business_none | J47: false | K47: 45772 | M47: INR | N47: 1 | O47: item_level | P47: true | Q47: Tax Invoice | R47: 0.00 | U47: item_level | W47: 0.00 | Z47: 0.000 | AA47: 21600 | AB47: 25488 | AC47: 0 | AD47: 0 | AE47: Adjustment | AG47: 45772 | AH47: 0 | AI47: Due on Receipt | AJ47: Thanks for your business. | AT47: Invoice | AU47: 0.0 | AV47: 0 | BD47: Jurisphere Enterprise Subscription | BE47: Subscription Period- Annual Subscription started from 25th Apr 25 to 24th Apr 26 Description- Single license for unlimited usage (litigation) | BF47: 1 | BG47: 0.00 | BH47: 0.00 | BI47: 21600 | BJ47: pcs | BK47: 21600 | BL47: 2297152000000039748 | BT47: Mumbai | BU47: Maharashtra | BV47: India | CC47: Mumbai | CD47: Maharashtra | CE47: India | CI47: Coresphere100 Technologies Pvt. Ltd. | CJ47: 09AALCC7037K1Z7 | CK47: 16026, 16th Floor, Tower Oakwood, | CL47: Greater Noida, | CM47: Uttar Pradesh | CN47: India | CO47: 201306 | CP47: 8928163657 | CQ47: manas@jurisphere.ai | CR47: 0.00 | CS47: 0.00 | CT47: 18.00 | CU47: 0.00 | CV47: 0.00 | CW47: 0.00 | CX47: 3888.00 | CY47: 0.00 | CZ47: 0.00 | DA47: 0.00 | DB47: 3888.00 | DC47: 0.00 | DI47: 0.000 | DP47: 998313 | DQ47: 0 | DX47: service | EH47: Others | EK47: Sales | EM47: Taxable | EN47: 2297152000000031111 | EO47: IGST18 | EP47: 18.00 | EQ47: 3888 | ER47: ItemAmount
A48: 45772 | B48: 2297152000000115647 | C48: INV-25-26-000049 | D48: Closed | E48: 2297152000000115495 | F48: Chetan shah | G48: MH | H48: 27-Maharashtra | I48: business_none | J48: false | K48: 45772 | M48: INR | N48: 1 | O48: item_level | P48: true | Q48: Tax Invoice | R48: 0.00 | U48: item_level | W48: 0.00 | Z48: 0.000 | AA48: 21600 | AB48: 25488 | AC48: 0 | AD48: 0 | AE48: Adjustment | AG48: 45772 | AH48: 0 | AI48: Due on Receipt | AJ48: Thanks for your business. | AT48: Invoice | AU48: 0.0 | AV48: 0 | BD48: Jurisphere Enterprise Subscription | BE48: Subscription Period- Annual Subscription started from 25th Apr 25 to 24th Apr 26 Description- Single license for unlimited usage (litigation) | BF48: 1 | BG48: 0.00 | BH48: 0.00 | BI48: 21600 | BJ48: pcs | BK48: 21600 | BL48: 2297152000000039748 | BT48: Mumbai | BU48: Maharashtra | BV48: India | CC48: Mumbai | CD48: Maharashtra | CE48: India | CI48: Coresphere100 Technologies Pvt. Ltd. | CJ48: 09AALCC7037K1Z7 | CK48: 16026, 16th Floor, Tower Oakwood, | CL48: Greater Noida, | CM48: Uttar Pradesh | CN48: India | CO48: 201306 | CP48: 8928163657 | CQ48: manas@jurisphere.ai | CR48: 0.00 | CS48: 0.00 | CT48: 18.00 | CU48: 0.00 | CV48: 0.00 | CW48: 0.00 | CX48: 3888.00 | CY48: 0.00 | CZ48: 0.00 | DA48: 0.00 | DB48: 3888.00 | DC48: 0.00 | DI48: 0.000 | DP48: 998313 | DQ48: 0 | DX48: service | EH48: Others | EK48: Sales | EM48: Taxable | EN48: 2297152000000031111 | EO48: IGST18 | EP48: 18.00 | EQ48: 3888 | ER48: ItemAmount
A49: 45772 | B49: 2297152000000115659 | C49: INV-25-26-000050 | D49: Closed | E49: 2297152000000115511 | F49: Sneha Phene | G49: MH | H49: 27-Maharashtra | I49: business_none | J49: false | K49: 45772 | M49: INR | N49: 1 | O49: item_level | P49: true | Q49: Tax Invoice | R49: 0.00 | U49: item_level | W49: 0.00 | Z49: 0.000 | AA49: 21600 | AB49: 25488 | AC49: 0 | AD49: 0 | AE49: Adjustment | AG49: 45772 | AH49: 0 | AI49: Due on Receipt | AJ49: Thanks for your business. | AT49: Invoice | AU49: 0.0 | AV49: 0 | BD49: Jurisphere Enterprise Subscription | BE49: Subscription Period- Annual Subscription started from 25th Apr 25 to 24th Apr 26 Description- Single license for unlimited usage (litigation) | BF49: 1 | BG49: 0.00 | BH49: 0.00 | BI49: 21600 | BJ49: pcs | BK49: 21600 | BL49: 2297152000000039748 | BT49: Mumbai | BU49: Maharashtra | BV49: India | CC49: Mumbai | CD49: Maharashtra | CE49: India | CI49: Coresphere100 Technologies Pvt. Ltd. | CJ49: 09AALCC7037K1Z7 | CK49: 16026, 16th Floor, Tower Oakwood, | CL49: Greater Noida, | CM49: Uttar Pradesh | CN49: India | CO49: 201306 | CP49: 8928163657 | CQ49: manas@jurisphere.ai | CR49: 0.00 | CS49: 0.00 | CT49: 18.00 | CU49: 0.00 | CV49: 0.00 | CW49: 0.00 | CX49: 3888.00 | CY49: 0.00 | CZ49: 0.00 | DA49: 0.00 | DB49: 3888.00 | DC49: 0.00 | DI49: 0.000 | DP49: 998313 | DQ49: 0 | DX49: service | EH49: Others | EK49: Sales | EM49: Taxable | EN49: 2297152000000031111 | EO49: IGST18 | EP49: 18.00 | EQ49: 3888 | ER49: ItemAmount
A50: 45772 | B50: 2297152000000115671 | C50: INV-25-26-000051 | D50: Closed | E50: 2297152000000115527 | F50: Gunjan Mangla | G50: MH | H50: 27-Maharashtra | I50: business_none | J50: false | K50: 45772 | M50: INR | N50: 1 | O50: item_level | P50: true | Q50: Tax Invoice | R50: 0.00 | U50: item_level | W50: 0.00 | Z50: 0.000 | AA50: 21600 | AB50: 25488 | AC50: 0 | AD50: 0 | AE50: Adjustment | AG50: 45773 | AH50: 0 | AI50: Due on Receipt | AJ50: Thanks for your business. | AT50: Invoice | AU50: 0.0 | AV50: 0 | BD50: Jurisphere Enterprise Subscription | BE50: Subscription Period- Annual Subscription started from 25th Apr 25 to 24th Apr 26 Description- Single license for unlimited usage (litigation) | BF50: 1 | BG50: 0.00 | BH50: 0.00 | BI50: 21600 | BJ50: pcs | BK50: 21600 | BL50: 2297152000000039748 | BT50: Mumbai | BU50: Maharashtra | BV50: India | CC50: Mumbai | CD50: Maharashtra | CE50: India | CI50: Coresphere100 Technologies Pvt. Ltd. | CJ50: 09AALCC7037K1Z7 | CK50: 16026, 16th Floor, Tower Oakwood, | CL50: Greater Noida, | CM50: Uttar Pradesh | CN50: India | CO50: 201306 | CP50: 8928163657 | CQ50: manas@jurisphere.ai | CR50: 0.00 | CS50: 0.00 | CT50: 18.00 | CU50: 0.00 | CV50: 0.00 | CW50: 0.00 | CX50: 3888.00 | CY50: 0.00 | CZ50: 0.00 | DA50: 0.00 | DB50: 3888.00 | DC50: 0.00 | DI50: 0.000 | DP50: 998313 | DQ50: 0 | DX50: service | EH50: Others | EK50: Sales | EM50: Taxable | EN50: 2297152000000031111 | EO50: IGST18 | EP50: 18.00 | EQ50: 3888 | ER50: ItemAmount
A51: 45772 | B51: 2297152000000115683 | C51: INV-25-26-000052 | D51: Closed | E51: 2297152000000115543 | F51: Zulfiqar Jariwala | G51: MH | H51: 27-Maharashtra | I51: business_none | J51: false | K51: 45772 | M51: INR | N51: 1 | O51: item_level | P51: true | Q51: Tax Invoice | R51: 0.00 | U51: item_level | W51: 0.00 | Z51: 0.000 | AA51: 21600 | AB51: 25488 | AC51: 0 | AD51: 0 | AE51: Adjustment | AG51: 45773 | AH51: 0 | AI51: Due on Receipt | AJ51: Thanks for your business. | AT51: Invoice | AU51: 0.0 | AV51: 0 | BD51: Jurisphere Enterprise Subscription | BE51: Subscription Period- Annual Subscription started from 25th Apr 25 to 24th Apr 26 Description- Single license for unlimited usage (litigation) | BF51: 1 | BG51: 0.00 | BH51: 0.00 | BI51: 21600 | BJ51: pcs | BK51: 21600 | BL51: 2297152000000039748 | BT51: Mumbai | BU51: Maharashtra | BV51: India | CC51: Mumbai | CD51: Maharashtra | CE51: India | CI51: Coresphere100 Technologies Pvt. Ltd. | CJ51: 09AALCC7037K1Z7 | CK51: 16026, 16th Floor, Tower Oakwood, | CL51: Greater Noida, | CM51: Uttar Pradesh | CN51: India | CO51: 201306 | CP51: 8928163657 | CQ51: manas@jurisphere.ai | CR51: 0.00 | CS51: 0.00 | CT51: 18.00 | CU51: 0.00 | CV51: 0.00 | CW51: 0.00 | CX51: 3888.00 | CY51: 0.00 | CZ51: 0.00 | DA51: 0.00 | DB51: 3888.00 | DC51: 0.00 | DI51: 0.000 | DP51: 998313 | DQ51: 0 | DX51: service | EH51: Others | EK51: Sales | EM51: Taxable | EN51: 2297152000000031111 | EO51: IGST18 | EP51: 18.00 | EQ51: 3888 | ER51: ItemAmount
A52: 45772 | B52: 2297152000000115695 | C52: INV-25-26-000053 | D52: Closed | E52: 2297152000000115559 | F52: Manjari Shah | G52: MH | H52: 27-Maharashtra | I52: business_none | J52: false | K52: 45772 | M52: INR | N52: 1 | O52: item_level | P52: true | Q52: Tax Invoice | R52: 0.00 | U52: item_level | W52: 0.00 | Z52: 0.000 | AA52: 21600 | AB52: 25488 | AC52: 0 | AD52: 0 | AE52: Adjustment | AG52: 45772 | AH52: 0 | AI52: Due on Receipt | AJ52: Thanks for your business. | AT52: Invoice | AU52: 0.0 | AV52: 0 | BD52: Jurisphere Enterprise Subscription | BE52: Subscription Period- Annual Subscription started from 25th Apr 25 to 24th Apr 26 Description- Single license for unlimited usage (litigation) | BF52: 1 | BG52: 0.00 | BH52: 0.00 | BI52: 21600 | BJ52: pcs | BK52: 21600 | BL52: 2297152000000039748 | BT52: Mumbai | BU52: Maharashtra | BV52: India | CC52: Mumbai | CD52: Maharashtra | CE52: India | CI52: Coresphere100 Technologies Pvt. Ltd. | CJ52: 09AALCC7037K1Z7 | CK52: 16026, 16th Floor, Tower Oakwood, | CL52: Greater Noida, | CM52: Uttar Pradesh | CN52: India | CO52: 201306 | CP52: 8928163657 | CQ52: manas@jurisphere.ai | CR52: 0.00 | CS52: 0.00 | CT52: 18.00 | CU52: 0.00 | CV52: 0.00 | CW52: 0.00 | CX52: 3888.00 | CY52: 0.00 | CZ52: 0.00 | DA52: 0.00 | DB52: 3888.00 | DC52: 0.00 | DI52: 0.000 | DP52: 998313 | DQ52: 0 | DX52: service | EH52: Others | EK52: Sales | EM52: Taxable | EN52: 2297152000000031111 | EO52: IGST18 | EP52: 18.00 | EQ52: 3888 | ER52: ItemAmount
A53: 45772 | B53: 2297152000000115707 | C53: INV-25-26-000054 | D53: Closed | E53: 2297152000000115575 | F53: Sagar Sheth | G53: MH | H53: 27-Maharashtra | I53: business_none | J53: false | K53: 45772 | M53: INR | N53: 1 | O53: item_level | P53: true | Q53: Tax Invoice | R53: 0.00 | U53: item_level | W53: 0.00 | Z53: 0.000 | AA53: 21600 | AB53: 25488 | AC53: 0 | AD53: 0 | AE53: Adjustment | AG53: 45772 | AH53: 0 | AI53: Due on Receipt | AJ53: Thanks for your business. | AT53: Invoice | AU53: 0.0 | AV53: 0 | BD53: Jurisphere Enterprise Subscription | BE53: Subscription Period- Annual Subscription started from 25th Apr 25 to 24th Apr 26 Description- Single license for unlimited usage (litigation) | BF53: 1 | BG53: 0.00 | BH53: 0.00 | BI53: 21600 | BJ53: pcs | BK53: 21600 | BL53: 2297152000000039748 | BT53: Mumbai | BU53: Maharashtra | BV53: India | CC53: Mumbai | CD53: Maharashtra | CE53: India | CI53: Coresphere100 Technologies Pvt. Ltd. | CJ53: 09AALCC7037K1Z7 | CK53: 16026, 16th Floor, Tower Oakwood, | CL53: Greater Noida, | CM53: Uttar Pradesh | CN53: India | CO53: 201306 | CP53: 8928163657 | CQ53: manas@jurisphere.ai | CR53: 0.00 | CS53: 0.00 | CT53: 18.00 | CU53: 0.00 | CV53: 0.00 | CW53: 0.00 | CX53: 3888.00 | CY53: 0.00 | CZ53: 0.00 | DA53: 0.00 | DB53: 3888.00 | DC53: 0.00 | DI53: 0.000 | DP53: 998313 | DQ53: 0 | DX53: service | EH53: Others | EK53: Sales | EM53: Taxable | EN53: 2297152000000031111 | EO53: IGST18 | EP53: 18.00 | EQ53: 3888 | ER53: ItemAmount
A54: 45772 | B54: 2297152000000115719 | C54: INV-25-26-000055 | D54: Closed | E54: 2297152000000115591 | F54: Mahek Bookwala | G54: MH | H54: 27-Maharashtra | I54: business_none | J54: false | K54: 45772 | M54: INR | N54: 1 | O54: item_level | P54: true | Q54: Tax Invoice | R54: 0.00 | U54: item_level | W54: 0.00 | Z54: 0.000 | AA54: 21600 | AB54: 25488 | AC54: 0 | AD54: 0 | AE54: Adjustment | AG54: 45772 | AH54: 0 | AI54: Due on Receipt | AJ54: Thanks for your business. | AT54: Invoice | AU54: 0.0 | AV54: 0 | BD54: Jurisphere Enterprise Subscription | BE54: Subscription Period- Annual Subscription started from 25th Apr 25 to 24th Apr 26 Description- Single license for unlimited usage (litigation) | BF54: 1 | BG54: 0.00 | BH54: 0.00 | BI54: 21600 | BJ54: pcs | BK54: 21600 | BL54: 2297152000000039748 | BT54: Mumbai | BU54: Maharashtra | BV54: India | CC54: Mumbai | CD54: Maharashtra | CE54: India | CI54: Coresphere100 Technologies Pvt. Ltd. | CJ54: 09AALCC7037K1Z7 | CK54: 16026, 16th Floor, Tower Oakwood, | CL54: Greater Noida, | CM54: Uttar Pradesh | CN54: India | CO54: 201306 | CP54: 8928163657 | CQ54: manas@jurisphere.ai | CR54: 0.00 | CS54: 0.00 | CT54: 18.00 | CU54: 0.00 | CV54: 0.00 | CW54: 0.00 | CX54: 3888.00 | CY54: 0.00 | CZ54: 0.00 | DA54: 0.00 | DB54: 3888.00 | DC54: 0.00 | DI54: 0.000 | DP54: 998313 | DQ54: 0 | DX54: service | EH54: Others | EK54: Sales | EM54: Taxable | EN54: 2297152000000031111 | EO54: IGST18 | EP54: 18.00 | EQ54: 3888 | ER54: ItemAmount
A55: 45772 | B55: 2297152000000115731 | C55: INV-25-26-000056 | D55: Overdue | E55: 2297152000000115607 | F55: Pradeep Sancheti | G55: MH | H55: 27-Maharashtra | I55: business_none | J55: false | K55: 45772 | M55: INR | N55: 1 | O55: item_level | P55: true | Q55: Tax Invoice | R55: 0.00 | U55: item_level | W55: 0.00 | Z55: 0.000 | AA55: 21600 | AB55: 25488 | AC55: 25488 | AD55: 0 | AE55: Adjustment | AH55: 0 | AI55: Due on Receipt | AJ55: Thanks for your business. | AT55: Invoice | AU55: 0.0 | AV55: 0 | BD55: Jurisphere Enterprise Subscription | BE55: Subscription Period- Annual Subscription started from 25th Apr 25 to 24th Apr 26 Description- Single license for unlimited usage (litigation) | BF55: 1 | BG55: 0.00 | BH55: 0.00 | BI55: 21600 | BJ55: pcs | BK55: 21600 | BL55: 2297152000000039748 | BT55: Mumbai | BU55: Maharashtra | BV55: India | CC55: Mumbai | CD55: Maharashtra | CE55: India | CI55: Coresphere100 Technologies Pvt. Ltd. | CJ55: 09AALCC7037K1Z7 | CK55: 16026, 16th Floor, Tower Oakwood, | CL55: Greater Noida, | CM55: Uttar Pradesh | CN55: India | CO55: 201306 | CP55: 8928163657 | CQ55: manas@jurisphere.ai | CR55: 0.00 | CS55: 0.00 | CT55: 18.00 | CU55: 0.00 | CV55: 0.00 | CW55: 0.00 | CX55: 3888.00 | CY55: 0.00 | CZ55: 0.00 | DA55: 0.00 | DB55: 3888.00 | DC55: 0.00 | DI55: 0.000 | DP55: 998313 | DQ55: 0 | DX55: service | EH55: Others | EK55: Sales | EM55: Taxable | EN55: 2297152000000031111 | EO55: IGST18 | EP55: 18.00 | EQ55: 3888 | ER55: ItemAmount
A56: 45772 | B56: 2297152000000115775 | C56: INV-25-26-000057 | D56: Closed | E56: 2297152000000115745 | F56: AHUJA VALECHA & ASSOCIATES LLP | G56: MH | H56: 27-Maharashtra | I56: business_gst | J56: false | K56: 45772 | M56: INR | N56: 1 | O56: item_level | P56: true | Q56: Tax Invoice | R56: 0.00 | U56: entity_level | V56: Technical Fees (2%) | W56: 2.00 | X56: 194J | Y56: Section 194 J | Z56: 1500.000 | AA56: 75000 | AB56: 87000 | AC56: 0 | AD56: 0 | AE56: Adjustment | AG56: 45773 | AH56: 0 | AI56: Due on Receipt | AJ56: Thanks for your business. | AT56: Invoice | AU56: 0.0 | AV56: 0 | BD56: Jurisphere Enterprise Subscription | BE56: Subscription Period- 3 month from 28 Apr to 27 July 2025 Description- 3 licenses of Rs. 25k/month with unlimited usage | BF56: 1 | BG56: 0.00 | BH56: 0.00 | BI56: 75000 | BJ56: pcs | BK56: 75000 | BL56: 2297152000000039748 | BR56: Meera Madhav, Plot No.38, | BS56: Sainik Vihar, Cloud 9 Estate, Off Nibm Road, | BT56: Pune | BU56: Maharashtra | BV56: India | BW56: 411060 | CA56: Meera Madhav, Plot No.38, | CB56: Sainik Vihar, Cloud 9 Estate, Off Nibm Road, | CC56: Pune | CD56: Maharashtra | CE56: India | CF56: 411060 | CI56: Coresphere100 Technologies Pvt. Ltd. | CJ56: 09AALCC7037K1Z7 | CK56: 16026, 16th Floor, Tower Oakwood, | CL56: Greater Noida, | CM56: Uttar Pradesh | CN56: India | CO56: 201306 | CP56: 8928163657 | CQ56: manas@jurisphere.ai | CR56: 0.00 | CS56: 0.00 | CT56: 18.00 | CU56: 0.00 | CV56: 0.00 | CW56: 0.00 | CX56: 13500.00 | CY56: 0.00 | CZ56: 0.00 | DA56: 0.00 | DB56: 13500.00 | DC56: 0.00 | DL56: 27AAOFA7053K1Z2 | DP56: 998313 | DQ56: 0 | DX56: service | EH56: Others | EK56: Sales | EM56: Taxable | EN56: 2297152000000031111 | EO56: IGST18 | EP56: 18.00 | EQ56: 13500 | ER56: ItemAmount
A57: 45773 | B57: 2297152000000117223 | C57: INV-25-26-000058 | D57: Overdue | E57: 2297152000000117207 | F57: IC Legal | G57: MH | H57: 27-Maharashtra | I57: business_none | J57: false | K57: 45773 | M57: INR | N57: 1 | O57: item_level | P57: true | Q57: Tax Invoice | R57: 0.00 | U57: entity_level | V57: Technical Fees (2%) | W57: 2.00 | X57: 194J | Y57: Section 194 J | Z57: 800.000 | AA57: 40000 | AB57: 46400 | AC57: 46400 | AD57: 0 | AE57: Adjustment | AH57: 0 | AI57: Due on Receipt | AJ57: Thanks for your business. | AT57: Invoice | AU57: 0.0 | AV57: 0 | BD57: Jurisphere Enterprise Subscription | BE57: Subscription Period- 2 month period from April 25, 2025 to June 24, 2025 Description- 20 licenses for Unlimited usage for doc review, research, redline, translation, list of dates. 2000 cells for Doctable and 5 MCA searches | BF57: 1 | BG57: 0.00 | BH57: 0.00 | BI57: 40000 | BJ57: pcs | BK57: 40000 | BL57: 2297152000000039748 | BR57: Times Square Building, Suite 3, | BS57: 12th Floor, E-Wing, Marol, Andheri (East) | BT57: Mumbai | BU57: Maharashtra | BV57: India | BW57: 400059 | CA57: Times Square Building, Suite 3, | CB57: 12th Floor, E-Wing, Marol, Andheri (East) | CC57: Mumbai | CD57: Maharashtra | CE57: India | CF57: 400059 | CI57: Coresphere100 Technologies Pvt. Ltd. | CJ57: 09AALCC7037K1Z7 | CK57: 16026, 16th Floor, Tower Oakwood, | CL57: Greater Noida, | CM57: Uttar Pradesh | CN57: India | CO57: 201306 | CP57: 8928163657 | CQ57: manas@jurisphere.ai | CR57: 0.00 | CS57: 0.00 | CT57: 18.00 | CU57: 0.00 | CV57: 0.00 | CW57: 0.00 | CX57: 7200.00 | CY57: 0.00 | CZ57: 0.00 | DA57: 0.00 | DB57: 7200.00 | DC57: 0.00 | DP57: 998313 | DQ57: 0 | DX57: service | EH57: Others | EK57: Sales | EM57: Taxable | EN57: 2297152000000031111 | EO57: IGST18 | EP57: 18.00 | EQ57: 7200 | ER57: ItemAmount
A58: 45773 | B58: 2297152000000117485 | C58: INV-25-26-000059 | D58: Overdue | E58: 2297152000000039613 | F58: Argus Partners | G58: MH | H58: 27-Maharashtra | I58: business_gst | J58: false | K58: 45773 | M58: INR | N58: 1 | O58: item_level | P58: true | Q58: Tax Invoice | R58: 0.00 | U58: item_level | W58: 0.00 | Z58: 0.000 | AA58: 10000 | AB58: 11800 | AC58: 11800 | AD58: 0 | AE58: Adjustment | AH58: 0 | AI58: Due on Receipt | AJ58: Thanks for your business. | AT58: Invoice | AU58: 0.0 | AV58: 0 | BD58: Jurisphere Enterprise Subscription | BE58: Subscription Period - One time Description- 1000 pages of translation | BF58: 1 | BG58: 0.00 | BH58: 0.00 | BI58: 10000 | BJ58: pcs | BK58: 10000 | BL58: 2297152000000039748 | BR58: 11, 1st Floor, Free Press House, | BS58: 215, Nariman Point, | BT58: Mumbai, | BU58: Maharashtra | BV58: India | BW58: 400021 | CA58: 11, 1st Floor, Free Press House, | CB58: 215, Nariman Point, | CC58: Mumbai, | CD58: Maharashtra | CE58: India | CF58: 400021 | CI58: Coresphere100 Technologies Pvt. Ltd. | CJ58: 09AALCC7037K1Z7 | CK58: 16026, 16th Floor, Tower Oakwood, | CL58: Greater Noida, | CM58: Uttar Pradesh | CN58: India | CO58: 201306 | CP58: 8928163657 | CQ58: manas@jurisphere.ai | CR58: 0.00 | CS58: 0.00 | CT58: 18.00 | CU58: 0.00 | CV58: 0.00 | CW58: 0.00 | CX58: 1800.00 | CY58: 0.00 | CZ58: 0.00 | DA58: 0.00 | DB58: 1800.00 | DC58: 0.00 | DI58: 0.000 | DL58: 27AAAFU4617P2ZP | DP58: 998313 | DQ58: 0 | DX58: service | EH58: Others | EK58: Sales | EM58: Taxable | EN58: 2297152000000031111 | EO58: IGST18 | EP58: 18.00 | EQ58: 1800 | ER58: ItemAmount
A59: 45773 | B59: 2297152000000117519 | C59: INV-25-26-000060 | D59: Closed | E59: 2297152000000117503 | F59: Pratik Patnaik | G59: DL | H59: 07-Delhi | I59: business_none | J59: false | K59: 45773 | M59: INR | N59: 1 | O59: item_level | P59: true | Q59: Tax Invoice | R59: 0.00 | U59: item_level | W59: 0.00 | Z59: 0.000 | AA59: 12000 | AB59: 14160 | AC59: 0 | AD59: 0 | AE59: Adjustment | AG59: 45773 | AH59: 0 | AI59: Due on Receipt | AJ59: Thanks for your business. | AT59: Invoice | AU59: 0.0 | AV59: 0 | BD59: Jurisphere Enterprise Subscription | BE59: Subscription Period- 1 month started from 26 Apr to 25 May 2025 Description- 4 licenses unlimited (litigation) | BF59: 1 | BG59: 0.00 | BH59: 0.00 | BI59: 12000 | BJ59: pcs | BK59: 12000 | BL59: 2297152000000039748 | BR59: 2nd Floor, Uday Park | BT59: New Delhi | BU59: Delhi | BV59: India | CA59: 2nd Floor, Uday Park | CC59: New Delhi | CD59: Delhi | CE59: India | CI59: Coresphere100 Technologies Pvt. Ltd. | CJ59: 09AALCC7037K1Z7 | CK59: 16026, 16th Floor, Tower Oakwood, | CL59: Greater Noida, | CM59: Uttar Pradesh | CN59: India | CO59: 201306 | CP59: 8928163657 | CQ59: manas@jurisphere.ai | CR59: 0.00 | CS59: 0.00 | CT59: 18.00 | CU59: 0.00 | CV59: 0.00 | CW59: 0.00 | CX59: 2160.00 | CY59: 0.00 | CZ59: 0.00 | DA59: 0.00 | DB59: 2160.00 | DC59: 0.00 | DI59: 0.000 | DP59: 998313 | DQ59: 0 | DX59: service | EH59: Others | EK59: Sales | EM59: Taxable | EN59: 2297152000000031111 | EO59: IGST18 | EP59: 18.00 | EQ59: 2160 | ER59: ItemAmount
A60: 45775 | B60: 2297152000000126015 | C60: INV-25-26-000061 | D60: Closed | E60: 2297152000000097825 | F60: Saswat Mohanty | G60: DL | H60: 07-Delhi | I60: business_none | J60: false | K60: 45775 | M60: INR | N60: 1 | O60: item_level | P60: true | Q60: Tax Invoice | R60: 0.00 | U60: item_level | W60: 0.00 | Z60: 0.000 | AA60: 44915.5 | AB60: 53000 | AC60: 0 | AD60: -0.29 | AE60: Adjustment | AG60: 45775 | AH60: 0 | AI60: Due on Receipt | AJ60: Thanks for your business. | AT60: Invoice | AU60: 0.0 | AV60: 0 | BD60: Jurisphere Enterprise Subscription | BE60: Subscription Period- 2nd instalment Invoice started from 30th Jan 2025 to 30th Jan 2026 Description- The balance due is Rs. 53,000/- | BF60: 1 | BG60: 0.00 | BH60: 0.00 | BI60: 44915.5 | BJ60: pcs | BK60: 44915.5 | BL60: 2297152000000039748 | BP60: Every 4 month invoice Saswat Mohanty | CI60: Coresphere100 Technologies Pvt. Ltd. | CJ60: 09AALCC7037K1Z7 | CK60: 16026, 16th Floor, Tower Oakwood, | CL60: Greater Noida, | CM60: Uttar Pradesh | CN60: India | CO60: 201306 | CP60: 8928163657 | CQ60: manas@jurisphere.ai | CR60: 0.00 | CS60: 0.00 | CT60: 18.00 | CU60: 0.00 | CV60: 0.00 | CW60: 0.00 | CX60: 8084.79 | CY60: 0.00 | CZ60: 0.00 | DA60: 0.00 | DB60: 8084.79 | DC60: 0.00 | DI60: 0.000 | DP60: 998313 | DQ60: 0 | DX60: service | EH60: Others | EK60: Sales | EM60: Taxable | EN60: 2297152000000031111 | EO60: IGST18 | EP60: 18.00 | EQ60: 8084.79 | ER60: ItemAmount
A61: 45775 | B61: 2297152000000126082 | C61: INV-25-26-000062 | D61: Closed | E61: 2297152000000126066 | F61: Chambers of Aman Vachher | G61: DL | H61: 07-Delhi | I61: business_none | J61: false | K61: 45775 | M61: INR | N61: 1 | O61: item_level | P61: true | Q61: Tax Invoice | R61: 0.00 | U61: item_level | W61: 0.00 | Z61: 0.000 | AA61: 172800 | AB61: 203904 | AC61: 0 | AD61: 0 | AE61: Adjustment | AG61: 45775 | AH61: 0 | AI61: Due on Receipt | AJ61: Thanks for your business. | AT61: Invoice | AU61: 0.0 | AV61: 0 | BD61: Jurisphere Enterprise Subscription | BE61: Subscription Period- Subscription Period started from 28th Mar 2025 to 28th Mar 26 Description - 4 licenses for Rs.48000 each | BF61: 1 | BG61: 10.00 | BH61: 19200.000 | BI61: 172800 | BJ61: pcs | BK61: 192000 | BL61: 2297152000000039748 | BR61: Ground Floor, A-335, | BS61: Defence Colony, | BT61: Delhi | BU61: Delhi | BV61: India | CA61: Ground Floor, A-335, | CB61: Defence Colony, | CC61: Delhi | CD61: Delhi | CE61: India | CI61: Coresphere100 Technologies Pvt. Ltd. | CJ61: 09AALCC7037K1Z7 | CK61: 16026, 16th Floor, Tower Oakwood, | CL61: Greater Noida, | CM61: Uttar Pradesh | CN61: India | CO61: 201306 | CP61: 8928163657 | CQ61: manas@jurisphere.ai | CR61: 0.00 | CS61: 0.00 | CT61: 18.00 | CU61: 0.00 | CV61: 0.00 | CW61: 0.00 | CX61: 31104.00 | CY61: 0.00 | CZ61: 0.00 | DA61: 0.00 | DB61: 31104.00 | DC61: 0.00 | DI61: 0.000 | DP61: 998313 | DQ61: 0 | DX61: service | EH61: Others | EK61: Sales | EM61: Taxable | EN61: 2297152000000031111 | EO61: IGST18 | EP61: 18.00 | EQ61: 31104 | ER61: ItemAmount
A62: 45775 | B62: 2297152000000126126 | C62: INV-25-26-000063 | D62: Closed | E62: 2297152000000126110 | F62: SK Singhi and Partners | G62: WB | H62: 19-West Bengal | I62: business_none | J62: false | K62: 45775 | M62: INR | N62: 1 | O62: item_level | P62: true | Q62: Tax Invoice | R62: 0.00 | U62: entity_level | V62: Professional Fees | W62: 10.00 | X62: 194J | Y62: Section 194 J | Z62: 27000.000 | AA62: 270000 | AB62: 291600 | AC62: 0 | AD62: 0 | AE62: Adjustment | AG62: 45776 | AH62: 0 | AI62: Due on Receipt | AJ62: Thanks for your business. | AT62: Invoice | AU62: 0.0 | AV62: 0 | BD62: Jurisphere Enterprise Subscription | BE62: Subscription Period- Subscription Period started from 28th Mar 2025 to 28th Mar 2026 Description- 6 licenses for Rs. 50,000 each | BF62: 1 | BG62: 10.00 | BH62: 30000.000 | BI62: 270000 | BJ62: pcs | BK62: 300000 | BL62: 2297152000000039748 | BR62: Raja Chambers, 1st Floor, | BS62: 4 Kiran Shankar Roy Road, | BT62: Kolkata | BU62: West Bengal | BV62: India | BW62: 700001 | CA62: Raja Chambers, 1st Floor, | CB62: 4 Kiran Shankar Roy Road, | CC62: Kolkata | CD62: West Bengal | CE62: India | CF62: 700001 | CI62: Coresphere100 Technologies Pvt. Ltd. | CJ62: 09AALCC7037K1Z7 | CK62: 16026, 16th Floor, Tower Oakwood, | CL62: Greater Noida, | CM62: Uttar Pradesh | CN62: India | CO62: 201306 | CP62: 8928163657 | CQ62: manas@jurisphere.ai | CR62: 0.00 | CS62: 0.00 | CT62: 18.00 | CU62: 0.00 | CV62: 0.00 | CW62: 0.00 | CX62: 48600.00 | CY62: 0.00 | CZ62: 0.00 | DA62: 0.00 | DB62: 48600.00 | DC62: 0.00 | DP62: 998313 | DQ62: 0 | DX62: service | EH62: Others | EK62: Sales | EM62: Taxable | EN62: 2297152000000031111 | EO62: IGST18 | EP62: 18.00 | EQ62: 48600 | ER62: ItemAmount
A63: 45775 | B63: 2297152000000126168 | C63: INV-25-26-000064 | D63: Closed | E63: 2297152000000126152 | F63: Centre for Law and Policy Research Trust | G63: KA | H63: 29-Karnataka | I63: business_none | J63: false | K63: 45775 | M63: INR | N63: 1 | O63: item_level | P63: true | Q63: Tax Invoice | R63: 0.00 | U63: item_level | W63: 0.00 | Z63: 0.000 | AA63: 4000 | AB63: 4720 | AC63: 0 | AD63: 0 | AE63: Adjustment | AG63: 45775 | AH63: 0 | AI63: Due on Receipt | AJ63: Thanks for your business. | AT63: Invoice | AU63: 0.0 | AV63: 0 | BD63: Jurisphere Enterprise Subscription | BE63: Subscription Period- 1 month subscription stated from 29th Apr 25 to 28th May 25 Description- Translation of 400 pages & unlimited document review. | BF63: 1 | BG63: 0.00 | BH63: 0.00 | BI63: 4000 | BJ63: pcs | BK63: 4000 | BL63: 2297152000000039748 | BR63: D6, Dona Cynthia Apartments, | BS63: 35, Primrose Road, Ashok Nagar, | BT63: Bengaluru | BU63: Karnataka | BV63: India | BW63: 560025 | CA63: D6, Dona Cynthia Apartments, | CB63: 35, Primrose Road, Ashok Nagar, | CC63: Bengaluru | CD63: Karnataka | CE63: India | CF63: 560025 | CI63: Coresphere100 Technologies Pvt. Ltd. | CJ63: 09AALCC7037K1Z7 | CK63: 16026, 16th Floor, Tower Oakwood, | CL63: Greater Noida, | CM63: Uttar Pradesh | CN63: India | CO63: 201306 | CP63: 8928163657 | CQ63: manas@jurisphere.ai | CR63: 0.00 | CS63: 0.00 | CT63: 18.00 | CU63: 0.00 | CV63: 0.00 | CW63: 0.00 | CX63: 720.00 | CY63: 0.00 | CZ63: 0.00 | DA63: 0.00 | DB63: 720.00 | DC63: 0.00 | DI63: 0.000 | DP63: 998313 | DQ63: 0 | DX63: service | EH63: Others | EK63: Sales | EM63: Taxable | EN63: 2297152000000031111 | EO63: IGST18 | EP63: 18.00 | EQ63: 720 | ER63: ItemAmount
A64: 45775 | B64: 2297152000000126220 | C64: INV-25-26-000065 | D64: Overdue | E64: 2297152000000126186 | F64: SKR & associates | G64: WB | H64: 19-West Bengal | I64: business_none | J64: false | K64: 45775 | M64: INR | N64: 1 | O64: item_level | P64: true | Q64: Tax Invoice | R64: 0.00 | U64: item_level | W64: 0.00 | Z64: 0.000 | AA64: 8729 | AB64: 10300 | AC64: 10300 | AD64: -0.22 | AE64: Adjustment | AH64: 0 | AI64: Due on Receipt | AJ64: Thanks for your business. | AT64: Invoice | AU64: 0.0 | AV64: 0 | BD64: Jurisphere Enterprise Subscription | BE64: Subscription Period- Monthly invoice fro the period started from 10th Apr 25 Description- 1 license of Rs. 8729/- per month for Litigation | BF64: 1 | BG64: 0.00 | BH64: 0.00 | BI64: 8729 | BJ64: pcs | BK64: 8729 | BL64: 2297152000000039748 | BP64: SKR & Associates - Monthly | BR64: Punwani chamber, 5th Floor, | BS64: 7B Kiran Shankar Roy Road, | BT64: Kolkata | BU64: West Bengal | BV64: India | BW64: 700001 | CA64: Punwani chamber, 5th Floor, | CB64: 7B Kiran Shankar Roy Road, | CC64: Kolkata | CD64: West Bengal | CE64: India | CF64: 700001 | CI64: Coresphere100 Technologies Pvt. Ltd. | CJ64: 09AALCC7037K1Z7 | CK64: 16026, 16th Floor, Tower Oakwood, | CL64: Greater Noida, | CM64: Uttar Pradesh | CN64: India | CO64: 201306 | CP64: 8928163657 | CQ64: manas@jurisphere.ai | CR64: 0.00 | CS64: 0.00 | CT64: 18.00 | CU64: 0.00 | CV64: 0.00 | CW64: 0.00 | CX64: 1571.22 | CY64: 0.00 | CZ64: 0.00 | DA64: 0.00 | DB64: 1571.22 | DC64: 0.00 | DI64: 0.000 | DP64: 998313 | DQ64: 0 | DX64: service | EH64: Others | EK64: Sales | EM64: Taxable | EN64: 2297152000000031111 | EO64: IGST18 | EP64: 18.00 | EQ64: 1571.22 | ER64: ItemAmount
A65: 45776 | B65: 2297152000000126384 | C65: INV-25-26-000066 | D65: Closed | E65: 2297152000000126368 | F65: Srivastava & Company | G65: WB | H65: 19-West Bengal | I65: business_none | J65: false | K65: 45776 | M65: INR | N65: 1 | O65: item_level | P65: true | Q65: Tax Invoice | R65: 0.00 | U65: item_level | W65: 0.00 | Z65: 0.000 | AA65: 33898.4 | AB65: 40000 | AC65: 0 | AD65: -0.11 | AE65: Adjustment | AG65: 45776 | AH65: 0 | AI65: Due on Receipt | AJ65: Thanks for your business. | AT65: Invoice | AU65: 0.0 | AV65: 0 | BD65: Jurisphere Enterprise Subscription | BE65: Subscription Period- Half yearly invoicing for Annual Subscription started from 29th Apr 25 to 28th Apr 26 Description- 1 license for Litigation. Rs. 80,000 (Inclusive of GST) is contract amt. | BF65: 1 | BG65: 0.00 | BH65: 0.00 | BI65: 33898.4 | BJ65: pcs | BK65: 33898.4 | BL65: 2297152000000039748 | BR65: 10 old post office street, | BS65: 3rd floor | BT65: Kolkata | BU65: West Bengal | BV65: India | CA65: 10 old post office street, | CB65: 3rd floor | CC65: Kolkata | CD65: West Bengal | CE65: India | CI65: Coresphere100 Technologies Pvt. Ltd. | CJ65: 09AALCC7037K1Z7 | CK65: 16026, 16th Floor, Tower Oakwood, | CL65: Greater Noida, | CM65: Uttar Pradesh | CN65: India | CO65: 201306 | CP65: 8928163657 | CQ65: manas@jurisphere.ai | CR65: 0.00 | CS65: 0.00 | CT65: 18.00 | CU65: 0.00 | CV65: 0.00 | CW65: 0.00 | CX65: 6101.71 | CY65: 0.00 | CZ65: 0.00 | DA65: 0.00 | DB65: 6101.71 | DC65: 0.00 | DI65: 0.000 | DP65: 998313 | DQ65: 0 | DT65: calcutta@srivastavaandcompany.com | DX65: service | EH65: Others | EK65: Sales | EM65: Taxable | EN65: 2297152000000031111 | EO65: IGST18 | EP65: 18.00 | EQ65: 6101.71 | ER65: ItemAmount
A66: 45776 | B66: 2297152000000126504 | C66: INV-25-26-000067 | D66: Closed | E66: 2297152000000126408 | F66: Piyush Raheja | G66: MH | H66: 27-Maharashtra | I66: business_none | J66: false | K66: 45776 | M66: INR | N66: 1 | O66: item_level | P66: true | Q66: Tax Invoice | R66: 0.00 | U66: item_level | W66: 0.00 | Z66: 0.000 | AA66: 22033.9 | AB66: 26000 | AC66: 0 | AD66: 0 | AE66: Adjustment | AG66: 45776 | AH66: 0 | AI66: Due on Receipt | AJ66: Thanks for your business. | AT66: Invoice | AU66: 0.0 | AV66: 0 | BD66: Jurisphere Enterprise Subscription | BE66: Subscription Period- Annual subscription started from 29th Apr 2025 to 28th Apr 2026 Description- Single license for Unlimited usage (litigation) on the annual subscription value of Rs. 22,033.90/- | BF66: 1 | BG66: 0.00 | BH66: 0.00 | BI66: 22033.9 | BJ66: pcs | BK66: 22033.9 | BL66: 2297152000000039748 | BT66: Mumbai | BU66: Maharashtra | BV66: India | CC66: Mumbai | CD66: Maharashtra | CE66: India | CI66: Coresphere100 Technologies Pvt. Ltd. | CJ66: 09AALCC7037K1Z7 | CK66: 16026, 16th Floor, Tower Oakwood, | CL66: Greater Noida, | CM66: Uttar Pradesh | CN66: India | CO66: 201306 | CP66: 8928163657 | CQ66: manas@jurisphere.ai | CR66: 0.00 | CS66: 0.00 | CT66: 18.00 | CU66: 0.00 | CV66: 0.00 | CW66: 0.00 | CX66: 3966.10 | CY66: 0.00 | CZ66: 0.00 | DA66: 0.00 | DB66: 3966.10 | DC66: 0.00 | DI66: 0.000 | DP66: 998313 | DQ66: 0 | DX66: service | EH66: Others | EK66: Sales | EM66: Taxable | EN66: 2297152000000031111 | EO66: IGST18 | EP66: 18.00 | EQ66: 3966.1 | ER66: ItemAmount
A67: 45776 | B67: 2297152000000126516 | C67: INV-25-26-000068 | D67: Closed | E67: 2297152000000126424 | F67: ⁠Feroze Patel | G67: MH | H67: 27-Maharashtra | I67: business_none | J67: false | K67: 45776 | M67: INR | N67: 1 | O67: item_level | P67: true | Q67: Tax Invoice | R67: 0.00 | U67: item_level | W67: 0.00 | Z67: 0.000 | AA67: 22033.9 | AB67: 26000 | AC67: 0 | AD67: 0 | AE67: Adjustment | AG67: 45777 | AH67: 0 | AI67: Due on Receipt | AJ67: Thanks for your business. | AT67: Invoice | AU67: 0.0 | AV67: 0 | BD67: Jurisphere Enterprise Subscription | BE67: Subscription Period- Annual subscription started from 29th Apr 2025 to 28th Apr 2026 Description- Single license for Unlimited usage (litigation) on the annual subscription value of Rs. 22,033.90/- | BF67: 1 | BG67: 0.00 | BH67: 0.00 | BI67: 22033.9 | BJ67: pcs | BK67: 22033.9 | BL67: 2297152000000039748 | BT67: Mumbai | BU67: Maharashtra | BV67: India | CC67: Mumbai | CD67: Maharashtra | CE67: India | CI67: Coresphere100 Technologies Pvt. Ltd. | CJ67: 09AALCC7037K1Z7 | CK67: 16026, 16th Floor, Tower Oakwood, | CL67: Greater Noida, | CM67: Uttar Pradesh | CN67: India | CO67: 201306 | CP67: 8928163657 | CQ67: manas@jurisphere.ai | CR67: 0.00 | CS67: 0.00 | CT67: 18.00 | CU67: 0.00 | CV67: 0.00 | CW67: 0.00 | CX67: 3966.10 | CY67: 0.00 | CZ67: 0.00 | DA67: 0.00 | DB67: 3966.10 | DC67: 0.00 | DI67: 0.000 | DP67: 998313 | DQ67: 0 | DX67: service | EH67: Others | EK67: Sales | EM67: Taxable | EN67: 2297152000000031111 | EO67: IGST18 | EP67: 18.00 | EQ67: 3966.1 | ER67: ItemAmount
A68: 45776 | B68: 2297152000000126528 | C68: INV-25-26-000069 | D68: Closed | E68: 2297152000000126440 | F68: Kazan Shroff | G68: MH | H68: 27-Maharashtra | I68: business_none | J68: false | K68: 45776 | M68: INR | N68: 1 | O68: item_level | P68: true | Q68: Tax Invoice | R68: 0.00 | U68: item_level | W68: 0.00 | Z68: 0.000 | AA68: 22033.9 | AB68: 26000 | AC68: 0 | AD68: 0 | AE68: Adjustment | AG68: 45776 | AH68: 0 | AI68: Due on Receipt | AJ68: Thanks for your business. | AT68: Invoice | AU68: 0.0 | AV68: 0 | BD68: Jurisphere Enterprise Subscription | BE68: Subscription Period- Annual subscription started from 29th Apr 2025 to 28th Apr 2026 Description- Single license for Unlimited usage (litigation) on the annual subscription value of Rs. 22,033.90/- | BF68: 1 | BG68: 0.00 | BH68: 0.00 | BI68: 22033.9 | BJ68: pcs | BK68: 22033.9 | BL68: 2297152000000039748 | BT68: Mumbai | BU68: Maharashtra | BV68: India | CC68: Mumbai | CD68: Maharashtra | CE68: India | CI68: Coresphere100 Technologies Pvt. Ltd. | CJ68: 09AALCC7037K1Z7 | CK68: 16026, 16th Floor, Tower Oakwood, | CL68: Greater Noida, | CM68: Uttar Pradesh | CN68: India | CO68: 201306 | CP68: 8928163657 | CQ68: manas@jurisphere.ai | CR68: 0.00 | CS68: 0.00 | CT68: 18.00 | CU68: 0.00 | CV68: 0.00 | CW68: 0.00 | CX68: 3966.10 | CY68: 0.00 | CZ68: 0.00 | DA68: 0.00 | DB68: 3966.10 | DC68: 0.00 | DI68: 0.000 | DP68: 998313 | DQ68: 0 | DX68: service | EH68: Others | EK68: Sales | EM68: Taxable | EN68: 2297152000000031111 | EO68: IGST18 | EP68: 18.00 | EQ68: 3966.1 | ER68: ItemAmount
A69: 45776 | B69: 2297152000000126540 | C69: INV-25-26-000070 | D69: Closed | E69: 2297152000000126456 | F69: Kajol Punjabi | G69: MH | H69: 27-Maharashtra | I69: business_none | J69: false | K69: 45776 | M69: INR | N69: 1 | O69: item_level | P69: true | Q69: Tax Invoice | R69: 0.00 | U69: item_level | W69: 0.00 | Z69: 0.000 | AA69: 22033.9 | AB69: 26000 | AC69: 0 | AD69: 0 | AE69: Adjustment | AG69: 45776 | AH69: 0 | AI69: Due on Receipt | AJ69: Thanks for your business. | AT69: Invoice | AU69: 0.0 | AV69: 0 | BD69: Jurisphere Enterprise Subscription | BE69: Subscription Period- Annual subscription started from 29th Apr 2025 to 28th Apr 2026 Description- Single license for Unlimited usage (litigation) on the annual subscription value of Rs. 22,033.90/- | BF69: 1 | BG69: 0.00 | BH69: 0.00 | BI69: 22033.9 | BJ69: pcs | BK69: 22033.9 | BL69: 2297152000000039748 | BT69: Mumbai | BU69: Maharashtra | BV69: India | CC69: Mumbai | CD69: Maharashtra | CE69: India | CI69: Coresphere100 Technologies Pvt. Ltd. | CJ69: 09AALCC7037K1Z7 | CK69: 16026, 16th Floor, Tower Oakwood, | CL69: Greater Noida, | CM69: Uttar Pradesh | CN69: India | CO69: 201306 | CP69: 8928163657 | CQ69: manas@jurisphere.ai | CR69: 0.00 | CS69: 0.00 | CT69: 18.00 | CU69: 0.00 | CV69: 0.00 | CW69: 0.00 | CX69: 3966.10 | CY69: 0.00 | CZ69: 0.00 | DA69: 0.00 | DB69: 3966.10 | DC69: 0.00 | DI69: 0.000 | DP69: 998313 | DQ69: 0 | DX69: service | EH69: Others | EK69: Sales | EM69: Taxable | EN69: 2297152000000031111 | EO69: IGST18 | EP69: 18.00 | EQ69: 3966.1 | ER69: ItemAmount
A70: 45776 | B70: 2297152000000126552 | C70: INV-25-26-000071 | D70: Closed | E70: 2297152000000126472 | F70: Neeta Jain | G70: MH | H70: 27-Maharashtra | I70: business_none | J70: false | K70: 45776 | M70: INR | N70: 1 | O70: item_level | P70: true | Q70: Tax Invoice | R70: 0.00 | U70: item_level | W70: 0.00 | Z70: 0.000 | AA70: 22033.9 | AB70: 26000 | AC70: 0 | AD70: 0 | AE70: Adjustment | AG70: 45776 | AH70: 0 | AI70: Due on Receipt | AJ70: Thanks for your business. | AT70: Invoice | AU70: 0.0 | AV70: 0 | BD70: Jurisphere Enterprise Subscription | BE70: Subscription Period- Annual subscription started from 29th Apr 2025 to 28th Apr 2026 Description- Single license for Unlimited usage (litigation) on the annual subscription value of Rs. 22,033.90/- | BF70: 1 | BG70: 0.00 | BH70: 0.00 | BI70: 22033.9 | BJ70: pcs | BK70: 22033.9 | BL70: 2297152000000039748 | BT70: Mumbai | BU70: Maharashtra | BV70: India | CC70: Mumbai | CD70: Maharashtra | CE70: India | CI70: Coresphere100 Technologies Pvt. Ltd. | CJ70: 09AALCC7037K1Z7 | CK70: 16026, 16th Floor, Tower Oakwood, | CL70: Greater Noida, | CM70: Uttar Pradesh | CN70: India | CO70: 201306 | CP70: 8928163657 | CQ70: manas@jurisphere.ai | CR70: 0.00 | CS70: 0.00 | CT70: 18.00 | CU70: 0.00 | CV70: 0.00 | CW70: 0.00 | CX70: 3966.10 | CY70: 0.00 | CZ70: 0.00 | DA70: 0.00 | DB70: 3966.10 | DC70: 0.00 | DI70: 0.000 | DP70: 998313 | DQ70: 0 | DX70: service | EH70: Others | EK70: Sales | EM70: Taxable | EN70: 2297152000000031111 | EO70: IGST18 | EP70: 18.00 | EQ70: 3966.1 | ER70: ItemAmount
A71: 45776 | B71: 2297152000000126564 | C71: INV-25-26-000072 | D71: Closed | E71: 2297152000000126488 | F71: Amrut Joshi | G71: MH | H71: 27-Maharashtra | I71: business_none | J71: false | K71: 45776 | M71: INR | N71: 1 | O71: item_level | P71: true | Q71: Tax Invoice | R71: 0.00 | U71: item_level | W71: 0.00 | Z71: 0.000 | AA71: 22033.9 | AB71: 26000 | AC71: 0 | AD71: 0 | AE71: Adjustment | AG71: 45776 | AH71: 0 | AI71: Due on Receipt | AJ71: Thanks for your business. | AT71: Invoice | AU71: 0.0 | AV71: 0 | BD71: Jurisphere Enterprise Subscription | BE71: Subscription Period- Annual subscription started from 29th Apr 2025 to 28th Apr 2026 Description- Single license for Unlimited usage (litigation) on the annual subscription value of Rs. 22,033.90/- | BF71: 1 | BG71: 0.00 | BH71: 0.00 | BI71: 22033.9 | BJ71: pcs | BK71: 22033.9 | BL71: 2297152000000039748 | BT71: Mumbai | BU71: Maharashtra | BV71: India | CC71: Mumbai | CD71: Maharashtra | CE71: India | CI71: Coresphere100 Technologies Pvt. Ltd. | CJ71: 09AALCC7037K1Z7 | CK71: 16026, 16th Floor, Tower Oakwood, | CL71: Greater Noida, | CM71: Uttar Pradesh | CN71: India | CO71: 201306 | CP71: 8928163657 | CQ71: manas@jurisphere.ai | CR71: 0.00 | CS71: 0.00 | CT71: 18.00 | CU71: 0.00 | CV71: 0.00 | CW71: 0.00 | CX71: 3966.10 | CY71: 0.00 | CZ71: 0.00 | DA71: 0.00 | DB71: 3966.10 | DC71: 0.00 | DI71: 0.000 | DP71: 998313 | DQ71: 0 | DX71: service | EH71: Others | EK71: Sales | EM71: Taxable | EN71: 2297152000000031111 | EO71: IGST18 | EP71: 18.00 | EQ71: 3966.1 | ER71: ItemAmount
A72: 45776 | B72: 2297152000000126582 | C72: INV-25-26-000073 | D72: Closed | E72: 2297152000000097457 | F72: Gaurav Joshi | G72: MH | H72: 27-Maharashtra | I72: business_none | J72: false | K72: 45776 | M72: INR | N72: 1 | O72: item_level | P72: true | Q72: Tax Invoice | R72: 0.00 | U72: item_level | W72: 0.00 | Z72: 0.000 | AA72: 44067.8 | AB72: 52000 | AC72: 0 | AD72: 0 | AE72: Adjustment | AG72: 45777 | AH72: 0 | AI72: Due on Receipt | AJ72: Thanks for your business. | AT72: Invoice | AU72: 0.0 | AV72: 0 | BD72: Jurisphere Enterprise Subscription | BE72: Subscription Period- Annual subscription started from 29th Apr 2025 to 28th Apr 2026 Description- 2 license for Unlimited usage (litigation) on the annual subscription value of Rs. 44,067.80/- | BF72: 1 | BG72: 0.00 | BH72: 0.00 | BI72: 44067.8 | BJ72: pcs | BK72: 44067.8 | BL72: 2297152000000039748 | CI72: Coresphere100 Technologies Pvt. Ltd. | CJ72: 09AALCC7037K1Z7 | CK72: 16026, 16th Floor, Tower Oakwood, | CL72: Greater Noida, | CM72: Uttar Pradesh | CN72: India | CO72: 201306 | CP72: 8928163657 | CQ72: manas@jurisphere.ai | CR72: 0.00 | CS72: 0.00 | CT72: 18.00 | CU72: 0.00 | CV72: 0.00 | CW72: 0.00 | CX72: 7932.20 | CY72: 0.00 | CZ72: 0.00 | DA72: 0.00 | DB72: 7932.20 | DC72: 0.00 | DI72: 0.000 | DP72: 998313 | DQ72: 0 | DX72: service | EH72: Others | EK72: Sales | EM72: Taxable | EN72: 2297152000000031111 | EO72: IGST18 | EP72: 18.00 | EQ72: 7932.2 | ER72: ItemAmount
A73: 45777 | B73: 2297152000000132335 | C73: INV-25-26-000074 | D73: Closed | E73: 2297152000000132319 | F73: Kamaljeet Singh | G73: DL | H73: 07-Delhi | I73: business_none | J73: false | K73: 45777 | M73: INR | N73: 1 | O73: item_level | P73: true | Q73: Tax Invoice | R73: 0.00 | U73: item_level | W73: 0.00 | Z73: 0.000 | AA73: 36000 | AB73: 42480 | AC73: 0 | AD73: 0 | AE73: Adjustment | AG73: 45777 | AH73: 0 | AI73: Due on Receipt | AJ73: Thanks for your business. | AT73: Invoice | AU73: 0.0 | AV73: 0 | BD73: Jurisphere Enterprise Subscription | BE73: Subscription Period- 6 months contract started from 29th Apr 25 to 28th Oct 25 Description- Unlmited research, docreview, translation, redline analysis, list of dates. | BF73: 1 | BG73: 0.00 | BH73: 0.00 | BI73: 36000 | BJ73: pcs | BK73: 36000 | BL73: 2297152000000039748 | BU73: Delhi | BV73: India | CD73: Delhi | CE73: India | CI73: Coresphere100 Technologies Pvt. Ltd. | CJ73: 09AALCC7037K1Z7 | CK73: 16026, 16th Floor, Tower Oakwood, | CL73: Greater Noida, | CM73: Uttar Pradesh | CN73: India | CO73: 201306 | CP73: 8928163657 | CQ73: manas@jurisphere.ai | CR73: 0.00 | CS73: 0.00 | CT73: 18.00 | CU73: 0.00 | CV73: 0.00 | CW73: 0.00 | CX73: 6480.00 | CY73: 0.00 | CZ73: 0.00 | DA73: 0.00 | DB73: 6480.00 | DC73: 0.00 | DI73: 0.000 | DP73: 998313 | DQ73: 0 | DX73: service | EH73: Others | EK73: Sales | EM73: Taxable | EN73: 2297152000000031111 | EO73: IGST18 | EP73: 18.00 | EQ73: 6480 | ER73: ItemAmount
A74: 45777 | B74: 2297152000000132367 | C74: INV-25-26-000075 | D74: Closed | E74: 2297152000000132349 | F74: Saraf and Partners | G74: UP | H74: 09-Uttar Pradesh | I74: business_gst | J74: false | K74: 45777 | M74: INR | N74: 1 | O74: item_level | P74: true | Q74: Tax Invoice | R74: 0.00 | U74: entity_level | V74: Professional Fees | W74: 10.00 | X74: 194J | Y74: Section 194 J | Z74: 4250.000 | AA74: 42500 | AB74: 45900 | AC74: 0 | AD74: 0 | AE74: Adjustment | AG74: 45779 | AH74: 0 | AI74: Due on Receipt | AJ74: Thanks for your business. | AT74: Invoice | AU74: 0.0 | AV74: 0 | BD74: Jurisphere Enterprise Subscription | BE74: Subscription Period- 1 month Pilot started from 1st May 25 to 31st May 25 Description- 17 licenses of Rs 2500/- per license per month for Unlimited usage & 5000 DocTable questions | BF74: 1 | BG74: 0.00 | BH74: 0.00 | BI74: 42500 | BJ74: pcs | BK74: 42500 | BL74: 2297152000000039748 | BR74: FC-10 and 11, Sector16A | BS74: Film City, | BT74: Noida | BU74: Uttar Pradesh | BV74: India | BW74: 201301 | CA74: FC-10 and 11, Sector16A | CB74: Film City, | CC74: Noida | CD74: Uttar Pradesh | CE74: India | CF74: 201301 | CI74: Coresphere100 Technologies Pvt. Ltd. | CJ74: 09AALCC7037K1Z7 | CK74: 16026, 16th Floor, Tower Oakwood, | CL74: Greater Noida, | CM74: Uttar Pradesh | CN74: India | CO74: 201306 | CP74: 8928163657 | CQ74: manas@jurisphere.ai | CR74: 9.00 | CS74: 9.00 | CT74: 0.00 | CU74: 0.00 | CV74: 3825.00 | CW74: 3825.00 | CX74: 0.00 | CY74: 0.00 | CZ74: 3825.00 | DA74: 3825.00 | DB74: 0.00 | DC74: 0.00 | DL74: 09AELFS3206H1ZX | DP74: 998313 | DQ74: 0 | DX74: service | EH74: Others | EK74: Sales | EM74: Taxable | EN74: 2297152000000031213 | EO74: GST18 | EP74: 18.00 | EQ74: 7650 | ER74: Tax Group
A75: 45777 | B75: 2297152000000132403 | C75: INV-25-26-000076 | D75: Overdue | E75: 2297152000000132385 | F75: Pioneer Legal | G75: MH | H75: 27-Maharashtra | I75: business_gst | J75: false | K75: 45777 | M75: INR | N75: 1 | O75: item_level | P75: true | Q75: Tax Invoice | R75: 0.00 | U75: item_level | W75: 0.00 | Z75: 0.000 | AA75: 15000 | AB75: 17700 | AC75: 17700 | AD75: 0 | AE75: Adjustment | AH75: 0 | AI75: Due on Receipt | AJ75: Thanks for your business. | AT75: Invoice | AU75: 0.0 | AV75: 0 | BD75: Jurisphere Enterprise Subscription | BE75: Subscription Period- 1 month pilot started from 29th April to 31st May 25 Description- DocReview - Unlimited Research - Unlimited Translation - Unlimited Redline Analysis - Unlimited File Library - Unlimited Auto-folderize - Unlimited Doc table - 2000 cells MCA Downloads - 10 | BF75: 1 | BG75: 0.00 | BH75: 0.00 | BI75: 15000 | BJ75: pcs | BK75: 15000 | BL75: 2297152000000039748 | BR75: Nariman Bhavan, 901/9th Floor | BS75: 227, Backbay Reclamation, Nariman Point, | BT75: Mumbai | BU75: Maharashtra | BV75: India | BW75: 400021 | CA75: Nariman Bhavan, 901/9th Floor | CB75: 227, Backbay Reclamation, Nariman Point, | CC75: Mumbai | CD75: Maharashtra | CE75: India | CF75: 400021 | CI75: Coresphere100 Technologies Pvt. Ltd. | CJ75: 09AALCC7037K1Z7 | CK75: 16026, 16th Floor, Tower Oakwood, | CL75: Greater Noida, | CM75: Uttar Pradesh | CN75: India | CO75: 201306 | CP75: 8928163657 | CQ75: manas@jurisphere.ai | CR75: 0.00 | CS75: 0.00 | CT75: 18.00 | CU75: 0.00 | CV75: 0.00 | CW75: 0.00 | CX75: 2700.00 | CY75: 0.00 | CZ75: 0.00 | DA75: 0.00 | DB75: 2700.00 | DC75: 0.00 | DI75: 0.000 | DL75: 27AAXFP2308P1ZG | DP75: 998313 | DQ75: 0 | DX75: service | EH75: Others | EK75: Sales | EM75: Taxable | EN75: 2297152000000031111 | EO75: IGST18 | EP75: 18.00 | EQ75: 2700 | ER75: ItemAmount
A76: 45777 | B76: 2297152000000132441 | C76: INV-25-26-000077 | D76: Overdue | E76: 2297152000000132423 | F76: Dua Associates | G76: DL | H76: 07-Delhi | I76: business_gst | J76: false | K76: 45777 | M76: INR | N76: 1 | O76: item_level | P76: true | Q76: Tax Invoice | R76: 0.00 | U76: item_level | W76: 0.00 | Z76: 0.000 | AA76: 16000 | AB76: 18880 | AC76: 18880 | AD76: 0 | AE76: Adjustment | AH76: 0 | AI76: Due on Receipt | AJ76: Thanks for your business. | AT76: Invoice | AU76: 0.0 | AV76: 0 | BD76: Jurisphere Enterprise Subscription | BE76: Subscription Period- 2 months subscription started from 1st May 2025 to 30th June 25 Description- 4 Licenses of Rs. 2000/license per month | BF76: 1 | BG76: 0.00 | BH76: 0.00 | BI76: 16000 | BJ76: pcs | BK76: 16000 | BL76: 2297152000000039748 | BR76: 202/206, Tolstoy House, | BS76: 15, Tolstoy Marg, | BT76: New Delhi | BU76: Delhi | BV76: India | BW76: 110001 | CA76: 202/206, Tolstoy House, | CB76: 15, Tolstoy Marg, | CC76: New Delhi | CD76: Delhi | CE76: India | CF76: 110001 | CI76: Coresphere100 Technologies Pvt. Ltd. | CJ76: 09AALCC7037K1Z7 | CK76: 16026, 16th Floor, Tower Oakwood, | CL76: Greater Noida, | CM76: Uttar Pradesh | CN76: India | CO76: 201306 | CP76: 8928163657 | CQ76: manas@jurisphere.ai | CR76: 0.00 | CS76: 0.00 | CT76: 18.00 | CU76: 0.00 | CV76: 0.00 | CW76: 0.00 | CX76: 2880.00 | CY76: 0.00 | CZ76: 0.00 | DA76: 0.00 | DB76: 2880.00 | DC76: 0.00 | DI76: 0.000 | DL76: 07AAAFD2611A1ZE | DP76: 998313 | DQ76: 0 | DX76: service | EH76: Others | EK76: Sales | EM76: Taxable | EN76: 2297152000000031111 | EO76: IGST18 | EP76: 18.00 | EQ76: 2880 | ER76: ItemAmount
A77: 45777 | B77: 2297152000000132479 | C77: INV-25-26-000078 | D77: Closed | E77: 2297152000000062297 | F77: Manish kelker | G77: DL | H77: 07-Delhi | I77: business_none | J77: false | K77: 45777 | M77: INR | N77: 1 | O77: item_level | P77: true | Q77: Tax Invoice | R77: 0.00 | U77: item_level | W77: 0.00 | Z77: 0.000 | AA77: 3388.98 | AB77: 3999 | AC77: 0 | AD77: 0 | AE77: Adjustment | AG77: 45777 | AH77: 0 | AI77: Due on Receipt | AJ77: Thanks for your business. | AT77: Invoice | AU77: 0.0 | AV77: 0 | BD77: Jurisphere Enterprise Subscription | BE77: Monthly Subscription for Apr 25 month Payment Id- pay_QGGnDtmfiSDKz3 | BF77: 1 | BG77: 0.00 | BH77: 0.00 | BI77: 3388.98 | BJ77: pcs | BK77: 3388.98 | BL77: 2297152000000039748 | CI77: Coresphere100 Technologies Pvt. Ltd. | CJ77: 09AALCC7037K1Z7 | CK77: 16026, 16th Floor, Tower Oakwood, | CL77: Greater Noida, | CM77: Uttar Pradesh | CN77: India | CO77: 201306 | CP77: 8928163657 | CQ77: manas@jurisphere.ai | CR77: 0.00 | CS77: 0.00 | CT77: 18.00 | CU77: 0.00 | CV77: 0.00 | CW77: 0.00 | CX77: 610.02 | CY77: 0.00 | CZ77: 0.00 | DA77: 0.00 | DB77: 610.02 | DC77: 0.00 | DI77: 0.000 | DP77: 998313 | DQ77: 0 | DX77: service | EH77: Others | EK77: Sales | EM77: Taxable | EN77: 2297152000000031111 | EO77: IGST18 | EP77: 18.00 | EQ77: 610.02 | ER77: ItemAmount
A78: 45777 | B78: 2297152000000132493 | C78: INV-25-26-000079 | D78: Closed | E78: 2297152000000065001 | F78: Diwan Law Associates | G78: UP | H78: 09-Uttar Pradesh | I78: business_none | J78: false | K78: 45777 | M78: INR | N78: 1 | O78: item_level | P78: true | Q78: Tax Invoice | R78: 0.00 | U78: item_level | W78: 0.00 | Z78: 0.000 | AA78: 4237.29 | AB78: 5000 | AC78: 0 | AD78: -0.01 | AE78: Adjustment | AG78: 45777 | AH78: 0 | AI78: Due on Receipt | AJ78: Thanks for your business. | AT78: Invoice | AU78: 0.0 | AV78: 0 | BD78: Jurisphere Enterprise Subscription | BE78: Subscription Period- Monthly Invoicing for Anuual Subscription started from Dec 11, 2024 to Dec 11, 2025 | BF78: 1 | BG78: 0.00 | BH78: 0.00 | BI78: 4237.29 | BJ78: pcs | BK78: 4237.29 | BL78: 2297152000000039748 | CI78: Coresphere100 Technologies Pvt. Ltd. | CJ78: 09AALCC7037K1Z7 | CK78: 16026, 16th Floor, Tower Oakwood, | CL78: Greater Noida, | CM78: Uttar Pradesh | CN78: India | CO78: 201306 | CP78: 8928163657 | CQ78: manas@jurisphere.ai | CR78: 9.00 | CS78: 9.00 | CT78: 0.00 | CU78: 0.00 | CV78: 381.36 | CW78: 381.36 | CX78: 0.00 | CY78: 0.00 | CZ78: 381.36 | DA78: 381.36 | DB78: 0.00 | DC78: 0.00 | DI78: 0.000 | DP78: 998313 | DQ78: 0 | DX78: service | EH78: Others | EK78: Sales | EM78: Taxable | EN78: 2297152000000031213 | EO78: GST18 | EP78: 18.00 | EQ78: 762.72 | ER78: Tax Group
A79: 45777 | B79: 2297152000000132507 | C79: INV-25-26-000080 | D79: Closed | E79: 2297152000000062113 | F79: SRCO Legal / Salvador Raghav & Co. | G79: DL | H79: 07-Delhi | I79: business_none | J79: false | K79: 45777 | M79: INR | N79: 1 | O79: item_level | P79: true | Q79: Tax Invoice | R79: 0.00 | U79: item_level | W79: 0.00 | Z79: 0.000 | AA79: 6779.66 | AB79: 8000 | AC79: 0 | AD79: 0 | AE79: Adjustment | AG79: 45777 | AH79: 0 | AI79: Due on Receipt | AJ79: Thanks for your business. | AT79: Invoice | AU79: 0.0 | AV79: 0 | BD79: Jurisphere Enterprise Subscription | BE79: Subscription Period- Apr 25 Monthly Invoicing for Annual Subscription from Oct 29, 2024 to Oct 29, 2025 | BF79: 1 | BG79: 0.00 | BH79: 0.00 | BI79: 6779.66 | BJ79: pcs | BK79: 6779.66 | BL79: 2297152000000039748 | CI79: Coresphere100 Technologies Pvt. Ltd. | CJ79: 09AALCC7037K1Z7 | CK79: 16026, 16th Floor, Tower Oakwood, | CL79: Greater Noida, | CM79: Uttar Pradesh | CN79: India | CO79: 201306 | CP79: 8928163657 | CQ79: manas@jurisphere.ai | CR79: 0.00 | CS79: 0.00 | CT79: 18.00 | CU79: 0.00 | CV79: 0.00 | CW79: 0.00 | CX79: 1220.34 | CY79: 0.00 | CZ79: 0.00 | DA79: 0.00 | DB79: 1220.34 | DC79: 0.00 | DI79: 0.000 | DP79: 998313 | DQ79: 0 | DX79: service | EH79: Others | EK79: Sales | EM79: Taxable | EN79: 2297152000000031111 | EO79: IGST18 | EP79: 18.00 | EQ79: 1220.34 | ER79: ItemAmount
A80: 45777 | B80: 2297152000000132521 | C80: INV-25-26-000081 | D80: Closed | E80: 2297152000000061001 | F80: B2C | G80: UP | H80: 09-Uttar Pradesh | I80: business_none | J80: false | K80: 45777 | M80: INR | N80: 1 | O80: item_level | P80: true | Q80: Tax Invoice | R80: 0.00 | U80: item_level | W80: 0.00 | Z80: 0.000 | AA80: 5497.46 | AB80: 6487 | AC80: 0 | AD80: 0 | AE80: Adjustment | AG80: 45777 | AH80: 0 | AI80: Due on Receipt | AJ80: Thanks for your business. | AT80: Invoice | AU80: 0.0 | AV80: 0 | BD80: Jurisphere Enterprise Subscription | BE80: B2C Sales from 17th Apr to 30th Apr 25 | BF80: 1 | BG80: 0.00 | BH80: 0.00 | BI80: 5497.46 | BJ80: pcs | BK80: 5497.46 | BL80: 2297152000000039748 | CI80: Coresphere100 Technologies Pvt. Ltd. | CJ80: 09AALCC7037K1Z7 | CK80: 16026, 16th Floor, Tower Oakwood, | CL80: Greater Noida, | CM80: Uttar Pradesh | CN80: India | CO80: 201306 | CP80: 8928163657 | CQ80: manas@jurisphere.ai | CR80: 9.00 | CS80: 9.00 | CT80: 0.00 | CU80: 0.00 | CV80: 494.77 | CW80: 494.77 | CX80: 0.00 | CY80: 0.00 | CZ80: 494.77 | DA80: 494.77 | DB80: 0.00 | DC80: 0.00 | DI80: 0.000 | DP80: 998313 | DQ80: 0 | DX80: service | EH80: Others | EK80: Sales | EM80: Taxable | EN80: 2297152000000031213 | EO80: GST18 | EP80: 18.00 | EQ80: 989.54 | ER80: Tax Group
A81: 45777 | B81: 2297152000000132535 | C81: INV-25-26-000082 | D81: Closed | E81: 2297152000000061001 | F81: B2C | G81: UP | H81: 09-Uttar Pradesh | I81: business_none | J81: false | K81: 45777 | M81: INR | N81: 1 | O81: item_level | P81: true | Q81: Tax Invoice | R81: 0.00 | U81: item_level | W81: 0.00 | Z81: 0.000 | AA81: 5000 | AB81: 5900 | AC81: 0 | AD81: 0 | AE81: Adjustment | AG81: 45777 | AH81: 0 | AI81: Due on Receipt | AJ81: Thanks for your business. | AT81: Invoice | AU81: 0.0 | AV81: 0 | BD81: Jurisphere Enterprise Subscription | BE81: awaisahmedji@gmail.com | BF81: 1 | BG81: 0.00 | BH81: 0.00 | BI81: 5000 | BJ81: pcs | BK81: 5000 | BL81: 2297152000000039748 | CI81: Coresphere100 Technologies Pvt. Ltd. | CJ81: 09AALCC7037K1Z7 | CK81: 16026, 16th Floor, Tower Oakwood, | CL81: Greater Noida, | CM81: Uttar Pradesh | CN81: India | CO81: 201306 | CP81: 8928163657 | CQ81: manas@jurisphere.ai | CR81: 9.00 | CS81: 9.00 | CT81: 0.00 | CU81: 0.00 | CV81: 450.00 | CW81: 450.00 | CX81: 0.00 | CY81: 0.00 | CZ81: 450.00 | DA81: 450.00 | DB81: 0.00 | DC81: 0.00 | DI81: 0.000 | DP81: 998313 | DQ81: 0 | DX81: service | EH81: Others | EK81: Sales | EM81: Taxable | EN81: 2297152000000031213 | EO81: GST18 | EP81: 18.00 | EQ81: 900 | ER81: Tax Group
A82: 45777 | B82: 2297152000000132549 | C82: INV-25-26-000083 | D82: Draft | E82: 2297152000000061001 | F82: B2C | G82: UP | H82: 09-Uttar Pradesh | I82: business_none | J82: false | K82: 45777 | M82: INR | N82: 1 | O82: item_level | P82: true | Q82: Tax Invoice | R82: 0.00 | U82: item_level | W82: 0.00 | Z82: 0.000 | AA82: 1 | AB82: 1.18 | AC82: 1.18 | AD82: 0 | AE82: Adjustment | AH82: 0 | AI82: Due on Receipt | AJ82: Thanks for your business. | AT82: Invoice | AU82: 0.0 | AV82: 0 | BD82: Jurisphere Enterprise Subscription | BF82: 1 | BG82: 0.00 | BH82: 0.00 | BI82: 1 | BJ82: pcs | BK82: 1 | BL82: 2297152000000039748 | CI82: Coresphere100 Technologies Pvt. Ltd. | CJ82: 09AALCC7037K1Z7 | CK82: 16026, 16th Floor, Tower Oakwood, | CL82: Greater Noida, | CM82: Uttar Pradesh | CN82: India | CO82: 201306 | CP82: 8928163657 | CQ82: manas@jurisphere.ai | CR82: 9.00 | CS82: 9.00 | CT82: 0.00 | CU82: 0.00 | CV82: 0.09 | CW82: 0.09 | CX82: 0.00 | CY82: 0.00 | CZ82: 0.09 | DA82: 0.09 | DB82: 0.00 | DC82: 0.00 | DI82: 0.000 | DP82: 998313 | DQ82: 0 | DX82: service | EH82: Others | EK82: Sales | EM82: Taxable | EN82: 2297152000000031213 | EO82: GST18 | EP82: 18.00 | EQ82: 0.18 | ER82: Tax Group
A83: 45777 | B83: 2297152000000132563 | C83: INV-25-26-000084 | D83: Draft | E83: 2297152000000061001 | F83: B2C | G83: UP | H83: 09-Uttar Pradesh | I83: business_none | J83: false | K83: 45777 | M83: INR | N83: 1 | O83: item_level | P83: true | Q83: Tax Invoice | R83: 0.00 | U83: item_level | W83: 0.00 | Z83: 0.000 | AA83: 1 | AB83: 1.18 | AC83: 1.18 | AD83: 0 | AE83: Adjustment | AH83: 0 | AI83: Due on Receipt | AJ83: Thanks for your business. | AT83: Invoice | AU83: 0.0 | AV83: 0 | BD83: Jurisphere Enterprise Subscription | BF83: 1 | BG83: 0.00 | BH83: 0.00 | BI83: 1 | BJ83: pcs | BK83: 1 | BL83: 2297152000000039748 | CI83: Coresphere100 Technologies Pvt. Ltd. | CJ83: 09AALCC7037K1Z7 | CK83: 16026, 16th Floor, Tower Oakwood, | CL83: Greater Noida, | CM83: Uttar Pradesh | CN83: India | CO83: 201306 | CP83: 8928163657 | CQ83: manas@jurisphere.ai | CR83: 9.00 | CS83: 9.00 | CT83: 0.00 | CU83: 0.00 | CV83: 0.09 | CW83: 0.09 | CX83: 0.00 | CY83: 0.00 | CZ83: 0.09 | DA83: 0.09 | DB83: 0.00 | DC83: 0.00 | DI83: 0.000 | DP83: 998313 | DQ83: 0 | DX83: service | EH83: Others | EK83: Sales | EM83: Taxable | EN83: 2297152000000031213 | EO83: GST18 | EP83: 18.00 | EQ83: 0.18 | ER83: Tax Group
